Workbook
Name A_65: Assumptions!$B$30
Name A_aging: Assumptions!$B$18
Name A_b0: Assumptions!$B$12
Name A_b1: Assumptions!$B$13
Name A_b2: Assumptions!$B$11
Name A_b3: Assumptions!$B$14
Name A_bankroll: Assumptions!$B$32
Name A_cilevel: Assumptions!$B$35
Name A_contshrink: Assumptions!$B$47
Name A_contthr: Assumptions!$B$46
Name A_cupcross: Assumptions!$B$28
Name A_cupneutral: Assumptions!$B$27
Name A_deterrent: Assumptions!$B$22
Name A_devig: Assumptions!$B$31
Name A_games: Assumptions!$B$52
Name A_HashCurrent: Assumptions!$B$59
Name A_hca: Assumptions!$B$8
Name A_kappa: Assumptions!$B$21
Name A_kelly: Assumptions!$B$33
Name A_kwins: Assumptions!$B$15
Name A_lambda: Assumptions!$B$23
Name A_leaguew: Assumptions!$B$57
Name A_lgortg: Assumptions!$B$56
Name A_longthr: Assumptions!$B$45
Name A_maxbet: Assumptions!$B$36
Name A_maxexp: Assumptions!$B$37
Name A_minev: Assumptions!$B$34
Name A_ndraws: Assumptions!$B$25
Name A_nsims: Assumptions!$B$26
Name A_paceblend: Assumptions!$B$54
Name A_playin_slots: Assumptions!$B$55
Name A_poconf: Assumptions!$B$50
Name A_podef: Assumptions!$B$49
Name A_poinj: Assumptions!$B$24
Name A_rookie: Assumptions!$B$19
Name A_Scenario: Assumptions!$B$5
Name A_sdscale: Assumptions!$B$51
Name A_shrink: Assumptions!$B$38
Name A_sigma_game: Assumptions!$B$9
Name A_sigma_team: Assumptions!$B$10
Name A_t1_cap: Assumptions!$B$43
Name A_t1_engcap: Assumptions!$B$44
Name A_t1_fair: Assumptions!$B$41
Name A_t1_shrink: Assumptions!$B$42
Name A_tank_on: Assumptions!$B$20
Name A_teamminutes: Assumptions!$B$53
Name A_tier2_on: Assumptions!$B$40
Name A_tpg: Assumptions!$B$29
Name A_wbox: Assumptions!$B$17
Name A_wdarko: Assumptions!$B$16
Name A_zs_delta: Assumptions!$B$48
Name A_zs_on: Assumptions!$B$39
Name Sim_Stale: M_Sims!$B$11

Sheet Cover
A1: NBA 2026-27 Futures Model
A2: Cover
A3: Version: v1 | 2026-10-15
A5: NBA 2026-27 Futures Model
A7: Version | B7: v1 (G5) - 2026-10-15
A8: Data timestamp | B8: Odds 2026-10-15; rosters/injuries ESPN 2026-10-15; DARKO through 2026-06-03
A9: Sim N | B9: =M_Sims!B6 -> 100000
A10: Run hash | B10: =M_Sims!B8 -> 30ca9e5eb89d8e39
A11: Run timestamp (UTC) | B11: =M_Sims!B5 -> 2026-10-15T21:35:36+00:00
A12: Sim status | B12: =Sim_Stale -> OK - sims match current assumptions
A13: Model independence | B13: Market odds are never a model input; they enter only de-vig, edges, staking shrink and backtest benchmarks.
A14: First locks | B14: Tue 10/20 2:10 PM CST (BOS/DET wins & playoffs; all title, conference, division, play-in, award markets)
A17: Navigation
A18: =HYPERLINK("#'Assumptions'!A1","Assumptions") -> Assumptions
A19: =HYPERLINK("#'Overrides'!A1","Overrides") -> Overrides
A20: =HYPERLINK("#'Odds_Input'!A1","Odds_Input") -> Odds_Input
A21: =HYPERLINK("#'M_DeVig'!A1","M_DeVig") -> M_DeVig
A22: =HYPERLINK("#'M_TeamRatings'!A1","M_TeamRatings") -> M_TeamRatings
A23: =HYPERLINK("#'M_WinDist'!A1","M_WinDist") -> M_WinDist
A24: =HYPERLINK("#'M_Sims'!A1","M_Sims") -> M_Sims
A25: =HYPERLINK("#'M_Lottery2027'!A1","M_Lottery2027") -> M_Lottery2027
A26: =HYPERLINK("#'M_Players'!A1","M_Players") -> M_Players
A27: =HYPERLINK("#'S_Markets'!A1","S_Markets") -> S_Markets
A28: =HYPERLINK("#'Bet_Card'!A1","Bet_Card") -> Bet_Card
A29: =HYPERLINK("#'Tier1_Card'!A1","Tier1_Card") -> Tier1_Card
A30: =HYPERLINK("#'Exposure'!A1","Exposure") -> Exposure
A31: =HYPERLINK("#'Dashboard'!A1","Dashboard") -> Dashboard
A32: =HYPERLINK("#'Sensitivity'!A1","Sensitivity") -> Sensitivity
A33: =HYPERLINK("#'Backtest'!A1","Backtest") -> Backtest
A34: =HYPERLINK("#'Tracker'!A1","Tracker") -> Tracker
A35: =HYPERLINK("#'Checks'!A1","Checks") -> Checks
A36: =HYPERLINK("#'Data_Sources'!A1","Data_Sources") -> Data_Sources
A37: =HYPERLINK("#'Raw_Teams'!A1","Raw_Teams") -> Raw_Teams
A38: =HYPERLINK("#'Raw_Players'!A1","Raw_Players") -> Raw_Players
A39: =HYPERLINK("#'Raw_Schedule'!A1","Raw_Schedule") -> Raw_Schedule
A41: Open items: PLAYOFFS = 16-team playoff field (user-confirmed from implied sums) - CONFIRM WITH BOOK. Tier 1 (Tier1_Card) is the staked card; Tier 2 (Bet_Card) has no stake by default. Player markets: see M_Players.

Sheet Assumptions
A1: NBA 2026-27 Futures Model
A2: Assumptions - every knob in one table
A3: Version: v1 | 2026-10-15
A5: Scenario selector (Bull / Base / Bear) | B5: Base | C5: Bull = lower sigma_team / higher DARKO weight / no tank; Bear = higher sigma_team / lower DARKO weight / upper-CI tank. Reprices the analytic layer live; sims must be rerun.
A7: Name | B7: Value (active) | C7: Units | D7: Description | E7: Provenance | F7: Default | G7: Bull | H7: Base | I7: Bear
A8: HCA | B8: 1.8856964 | C8: pts | D8: Home-court advantage (regular season), margin points | E8: params/provenance.json:game_hca (2021-22..2025-26) | F8: 1.8856964 | G8: - | H8: - | I8: -
A9: sigma_game | B9: 13.486413 | C9: pts | D9: Game margin standard deviation | E9: game_sigma_game | F9: 13.486413 | G9: - | H9: - | I9: -
A10: sigma_team | B10: =CHOOSE(MATCH(A_Scenario,{"Bull","Base","Bear"},0),G10,H10,I10) -> 3.5 | C10: SRS pts | D10: True-strength shock SD (season) - LOSO CV with mean-matched sims, availability draws on | E10: sigma_team_srs (G5 refit) | F10: 3.5 | G10: 3.15 | H10: 3.5 | I10: 3.85
A11: prior_blend_weight (coef on prior SRS) | B11: -0.17034812 | C11: coef | D11: Team layer: coefficient on prior-season SRS | E11: team_layer_beta[2] | F11: -0.17034812 | G11: - | H11: - | I11: -
A12: team_layer_const | B12: -0.034051248 | C12: coef | D12: Team layer: intercept | E12: team_layer_beta[0] | F12: -0.034051248 | G12: - | H12: - | I12: -
A13: team_layer_rating_coef | B13: 1.077687 | C13: coef | D13: Team layer: coefficient on minutes-weighted player rating sum | E13: team_layer_beta[1] | F13: 1.077687 | G13: - | H13: - | I13: -
A14: team_layer_continuity_coef | B14: 0.13476864 | C14: coef | D14: Team layer: coefficient on continuity x prior SRS | E14: team_layer_beta[3] | F14: 0.13476864 | G14: - | H14: - | I14: -
A15: k_wins | B15: 2.4403038 | C15: wins/SRS pt | D15: Wins per SRS point (wins = 41 + k x SRS) | E15: k_wins_per_srs | F15: 2.4403038 | G15: - | H15: - | I15: -
A16: DARKO_weight (player-metric blend) | B16: =CHOOSE(MATCH(A_Scenario,{"Bull","Base","Bear"},0),G16,H16,I16) -> 0.5 | C16: share | D16: Production DARKO vs box-prior blend (documented rule, untested) | E16: w_darko (G2 addendum); engine input | F16: 0.5 | G16: 0.7 | H16: 0.5 | I16: 0.3
A17: box_prior_weight | B17: =1-A_wdarko -> 0.5 | C17: share | D17: Equals 1 minus DARKO weight (engine input) | E17: derived | F17: 0.5 | G17: - | H17: - | I17: -
A18: aging_curve_on | B18: 1 | C18: 0/1 | D18: Aging curve in player projections (engine input; informational) | E18: ratings fit | F18: 1 | G18: - | H18: - | I18: -
A19: rookie_prior_weight | B19: 1 | C19: share | D19: Rookie draft-slot + college translation model weight (engine input; informational) | E19: rookie_college_model_beta | F19: 1 | G19: - | H19: - | I19: -
A20: tank_on | B20: =CHOOSE(MATCH(A_Scenario,{"Bull","Base","Bear"},0),G20,H20,I20) -> 1 | C20: 0/1 | D20: 3-2-1 tank module on (engine input) | E20: G3 | F20: 1 | G20: 0 | H20: 1 | I20: 1
A21: tank_kappa | B21: =CHOOSE(MATCH(A_Scenario,{"Bull","Base","Bear"},0),G21,H21,I21) -> 0.28086944 | C21: net-rating pts/unit | D21: Post-deadline effort suppression per unit normalized incentive (CI includes 0) | E21: tank_kappa (G3) | F21: 0.28086944 | G21: 0 | H21: 0.28086944 | I21: 1.57
A22: tank_deterrent | B22: 0 | C22: share | D22: Commissioner deterrent (1 = no tanking) | E22: tank_deterrent (assumption) | F22: 0 | G22: - | H22: - | I22: -
A23: playoff_adj_lambda | B23: 0.57637298 | C23: share | D23: Playoff minutes-concentration rating adjustment multiplier (fit 0.58 [0.32,0.80]) | E23: po_lambda | F23: 0.57637298 | G23: - | H23: - | I23: -
A24: playoff_injury_prob | B24: 0.07 | C24: prob | D24: Per top-8 player chance of missing the postseason (assumption) | E24: po_inj_prob | F24: 0.07 | G24: - | H24: - | I24: -
A25: lottery_n_draws | B25: 16 | C25: draws | D25: Lottery draws (all 16 picks drawn; NBA.com) | E25: assumptions.json | F25: 16 | G25: - | H25: - | I25: -
A26: sim_N | B26: 100000 | C26: seasons | D26: Simulated seasons in the last run | E26: sims/run_meta.json | F26: 100000 | G26: - | H26: - | I26: -
A27: cup_semis_neutral | B27: 0 | C27: 0/1 | D27: NBA.com: semis at higher seed home arena | E27: assumptions.json | F27: 0 | G27: - | H27: - | I27: -
A28: cup_nonqualifier_cross_conf_games | B28: 2 | C28: games | D28: NBA.com: 2 of the 22 non-qualifier games are cross-conference | E28: assumptions.json | F28: 2 | G28: - | H28: - | I28: -
A29: tpg_min_games_pct | B29: 0.7 | C29: share | D29: Turnover-leader qualifier (58-game rule; UNCONFIRMED with the book) | E29: assumptions.json | F29: 0.7 | G29: - | H29: - | I29: -
A30: games_65_rule_on | B30: 1 | C30: 0/1 | D30: 65-game eligibility rule for awards (G4) | E30: SPEC | F30: 1 | G30: - | H30: - | I30: -
A31: devig_method | B31: Shin | C31: list | D31: De-vig method for fair probabilities (Multiplicative / Power / Shin) | E31: SPEC | F31: Shin | G31: - | H31: - | I31: -
A32: bankroll | C32: $ | D32: Bankroll (blank input; stakes show '-' until entered) | E32: user input | F32: - | G32: - | H32: - | I32: -
A33: kelly_fraction | B33: 0.25 | C33: share | D33: Fractional Kelly multiplier | E33: SPEC | F33: 0.25 | G33: - | H33: - | I33: -
A34: min_EV | B34: 0.03 | C34: per $1 | D34: Minimum EV to qualify for the Bet Card | E34: SPEC | F34: 0.03 | G34: - | H34: - | I34: -
A35: CI_level | B35: 0.8 | C35: prob | D35: Confidence level of the edge CI (engine output is computed at 80%) | E35: SPEC | F35: 0.8 | G35: - | H35: - | I35: -
A36: max_bet | B36: 1000 | C36: $ | D36: Max single bet | E36: SPEC / book MAX | F36: 1000 | G36: - | H36: - | I36: -
A37: max_total_exposure | B37: 0.25 | C37: share of bankroll | D37: Max total exposure | E37: SPEC | F37: 0.25 | G37: - | H37: - | I37: -
A38: staking_shrink_to_market | B38: 0.5 | C38: share | D38: Model-to-market shrink (0 = pure model). 0.5 after the G5 miscalibration diagnosis (model-vs-market wins RMSE > 4); also applied to the edge test; the model itself is never shrunk | E38: SPEC default 0.25; raised to 0.5 (G5 report) | F38: 0.5 | G38: - | H38: - | I38: -
A39: zero_sum_filter_on | B39: 1 | C39: 0/1 | D39: WINS bets must survive rescaling model win means to the book's sum of lines (removes edges that are only market inflation) | E39: G5 report | F39: 1 | G39: - | H39: - | I39: -
A40: tier2_staking_on | B40: 0 | C40: 0/1 | D40: Tier 2 (the full 52-bet card) has NO stake by default; set 1 to show Tier 2 Kelly stakes | E40: G5 Tier 1 spec | F40: 0 | G40: - | H40: - | I40: -
A41: tier1_fair_min | B41: 0.05 | C41: prob | D41: Tier 1: market fair probability must be at least this (no longshots) | E41: G5 Tier 1 spec | F41: 0.05 | G41: - | H41: - | I41: -
A42: tier1_shrink | B42: 0.75 | C42: share | D42: Tier 1: edge must survive this shrink toward the market (model weight 0.25) | E42: G5 Tier 1 spec | F42: 0.75 | G42: - | H42: - | I42: -
A43: tier1_exposure_cap | B43: 0.1 | C43: share of bankroll | D43: Tier 1 total exposure cap for the season | E43: G5 Tier 1 spec | F43: 0.1 | G43: - | H43: - | I43: -
A44: tier1_engine_cap | B44: 0.1 | C44: share of bankroll | D44: Cap the engine used when solving Tier 1 portfolio Kelly (stakes scale by the ratio) | E44: engine | F44: 0.1 | G44: - | H44: - | I44: -
... A47: low_continuity_shrink | B47: 0.75 | C47: share | D47: Shrink applied to the edge test for low-continuity teams | E47: G5 report | F47: 0.75 | G47: - | H47: - | I47: -
A48: zero_sum_shift | B48: =(SUMIFS(Odds_Input!$E$8:$E$694,Odds_Input!$B$8:$B$694,"WINS",Odds_Input!$D$8:$D$694,"OVER")-A_leaguew)/30 -> 0.36666667 | C48: wins/team | D48: Book sum of win lines minus 1,230, per team (live) | E48: derived from Odds_Input | F48: - | G48: - | H48: - | I48: -
A49: playoffs_definition | B49: Bracket | C49: list | D49: PLAYOFFS market definition: Bracket (16-team playoffs; matches book prices) or Top10 (play-in counts; spec reading) | E49: UNCONFIRMED - see G5 report | F49: Bracket | G49: - | H49: - | I49: -
A50: playoffs_rule_confirmed | B50: 1 | C50: 0/1 | D50: PLAYOFFS = 16-team playoff field (top-8, including via play-in): user-confirmed from implied sums (~8.7/conf). CONFIRM WITH BOOK. Set 0 to block PLAYOFFS bets | E50: G5 report | F50: 1 | G50: - | H50: - | I50: -
A51: analytic_sd_scale | B51: 0.94 | C51: ratio | D51: Analytic layer: SD scale vs delta-method SD (fit to sim SDs) | E51: G5: fit of analytic layer to the engine | F51: 0.94 | G51: - | H51: - | I51: -
A52: games_per_season | B52: 82 | C52: games | D52: Games per team (structural constant) | E52: SPEC | F52: 82 | G52: - | H52: - | I52: -
A53: team_minutes_per_season | B53: 19680 | C53: minutes | D53: 240 minutes x 82 games (structural constant) | E53: SPEC | F53: 19680 | G53: - | H53: - | I53: -
A54: pace_blend_prior | B54: 0.7 | C54: share | D54: Pace projection = share x prior pace + (1 - share) x league mean (assumption, untested) | E54: provenance pace_blend | F54: 0.7 | G54: - | H54: - | I54: -
A55: playin_slots | B55: 4 | C55: slots | D55: Play-in participants per conference (finish 7-10); target sum for PLAYIN fair probabilities | E55: NBA rules | F55: 4 | G55: - | H55: - | I55: -
A56: lg_ortg | B56: 115.78 | C56: pts/100 | D56: League average ORtg 2025-26 (anchor for ORtg/DRtg) | E56: ratings_fit_2027.json | F56: 115.78 | G56: - | H56: - | I56: -
A57: league_wins_total | B57: 1230 | C57: wins | D57: Zero-sum constraint on projected wins | E57: SPEC | F57: 1230 | G57: - | H57: - | I57: -
A59: Sim assumptions key (current) | B59: =TEXT(A_sigma_team,"0.0000")&"|"&TEXT(A_hca,"0.0000")&"|"&TEXT(A_sigma_game,"0.0000")&"|"&TEXT(A_wdarko,"0.0000")&"|"&TEXT(A_kappa,"0.0000")&"|"&TEXT(A_deterrent,"0.0000")&"|"&TEXT(A_tank_on,"0.0000")&"|"&TEXT(A_lambda,"0.0000")&"|"&TEXT(A_poinj,"0.0000")&"|"&TEXT(A_ndraws,"0.0000")&"|"&TEXT(A_cupneutral,"0.0000")&"|"&TEXT(IF(A_cupcross>0,1,0),"0.0000")&"|"&TEXT(A_b0,"0.0000")&"|"&TEXT(A_b1,"0.0000")&"|"&TEXT(A_b2,"0.0000")&"|"&TEXT(A_b3,"0.0000")&"|"&TEXT(A_kwins,"0.0000") -> 3.5000|1.8857|13.4864|0.5000|0.2809|0.0000|1.0000|0.5764|0.0700|16.0000|0.0000|1.0000|-0.0341|1.0777|-0.1703|0.1348|2.4403 | D59: Compared with the key stored with the last sim run (M_Sims); a mismatch flags sim-dependent cells STALE - rerun sims

Sheet Overrides
A1: NBA 2026-27 Futures Model
A2: Overrides - per-player minutes / games / rating adjustments, per-team rating adjustments (blue = input)
A3: Version: v1 | 2026-10-15
A5: Player overrides (leave blank for no override). Minutes/game and Games replace the projection; rating adjustment is in BPM points per 100 poss.
A7: Player | B7: Minutes per game override | C7: Games override | D7: Rating adjustment | E7: Note
A50: Team rating adjustments (SRS pts, applied after the team layer, re-centered to zero-sum)
A51: Team | B51: SRS adjustment | C51: Note
A52: ATL | B52: 0
A53: BKN | B53: 0
A54: BOS | B54: 0
A55: CHA | B55: 0
A56: CHI | B56: 0
A57: CLE | B57: 0
A58: DAL | B58: 0
A59: DEN | B59: 0
A60: DET | B60: 0
A61: GSW | B61: 0
A62: HOU | B62: 0
A63: IND | B63: 0
... A81: WAS | B81: 0

Sheet Odds_Input
A1: NBA 2026-27 Futures Model
A2: Odds_Input - paste area (blue) + parsed book odds; orange fill = imputed/backfilled
A3: Version: v1 | 2026-10-15
A5: Paste/parse book odds here. Command: run.py parse-odds <file>. Source file: odds_2026-10-15.csv (687 rows). Orange = backfilled/imputed (imputed sides are never bet).
A7: Row id | B7: Market | C7: Selection | D7: Side | E7: Line | F7: American odds | G7: Flag
A8: 0 | B8: TITLE | C8: Atlanta Hawks | D8: YES | E8: - | F8: 6200 | G8: -
A9: 1 | B9: TITLE | C9: Boston Celtics | D9: YES | E9: - | F9: 1400 | G9: -
A10: 2 | B10: TITLE | C10: Brooklyn Nets | D10: YES | E10: - | F10: 25000 | G10: -
A11: 3 | B11: TITLE | C11: Charlotte Hornets | D11: YES | E11: - | F11: 8600 | G11: -
A12: 4 | B12: TITLE | C12: Chicago Bulls | D12: YES | E12: - | F12: 25000 | G12: -
A13: 5 | B13: TITLE | C13: Cleveland Cavaliers | D13: YES | E13: - | F13: 2400 | G13: -
A14: 6 | B14: TITLE | C14: Dallas Mavericks | D14: YES | E14: - | F14: 16000 | G14: -
A15: 7 | B15: TITLE | C15: Denver Nuggets | D15: YES | E15: - | F15: 2700 | G15: -
A16: 8 | B16: TITLE | C16: Detroit Pistons | D16: YES | E16: - | F16: 3000 | G16: -
A17: 9 | B17: TITLE | C17: Golden State Warriors | D17: YES | E17: - | F17: 5300 | G17: -
A18: 10 | B18: TITLE | C18: Houston Rockets | D18: YES | E18: - | F18: 4900 | G18: -
A19: 11 | B19: TITLE | C19: Indiana Pacers | D19: YES | E19: - | F19: 5000 | G19: -
... A127: 119 | B127: PLAYIN_WEST | C127: Utah Jazz | D127: YES | E127: - | F127: 115 | G127: -
A128: 120 | B128: WINS | C128: Boston Celtics | D128: OVER | E128: 51.5 | F128: 110 | G128: -
A129: 121 | B129: WINS | C129: Boston Celtics | D129: UNDER | E129: 51.5 | F129: -130 | G129: -
A130: 122 | B130: WINS | C130: Detroit Pistons | D130: OVER | E130: 49.5 | F130: 115 | G130: -
A131: 123 | B131: WINS | C131: Detroit Pistons | D131: UNDER | E131: 49.5 | F131: -135 | G131: -
A132: 124 | B132: WINS | C132: New York Knicks | D132: OVER | E132: 52.5 | F132: 135 | G132: -
A133: 125 | B133: WINS | C133: New York Knicks | D133: UNDER | E133: 52.5 | F133: -155 | G133: -
A134: 126 | B134: WINS | C134: Philadelphia 76ers | D134: OVER | E134: 50.5 | F134: 100 | G134: BACKFILL_PDF_TEXT
A135: 127 | B135: WINS | C135: Philadelphia 76ers | D135: UNDER | E135: 50.5 | F135: -120 | G135: -
A136: 128 | B136: WINS | C136: Oklahoma City Thunder | D136: OVER | E136: 61.5 | F136: -125 | G136: -
A137: 129 | B137: WINS | C137: Oklahoma City Thunder | D137: UNDER | E137: 61.5 | F137: 105 | G137: -
A138: 130 | B138: WINS | C138: San Antonio Spurs | D138: OVER | E138: 59.5 | F138: -135 | G138: -
A139: 131 | B139: WINS | C139: San Antonio Spurs | D139: UNDER | E139: 59.5 | F139: 115 | G139: -
... A187: 179 | B187: WINS | C187: Denver Nuggets | D187: UNDER | E187: 49.5 | F187: -140 | G187: -
A188: 180 | B188: PLAYOFFS | C188: Boston Celtics | D188: YES | E188: - | F188: -875 | G188: -
A189: 181 | B189: PLAYOFFS | C189: Boston Celtics | D189: NO | E189: - | F189: 475 | G189: -
A190: 182 | B190: PLAYOFFS | C190: Detroit Pistons | D190: YES | E190: - | F190: -550 | G190: -
A191: 183 | B191: PLAYOFFS | C191: Detroit Pistons | D191: NO | E191: - | F191: 375 | G191: -
A192: 184 | B192: PLAYOFFS | C192: New York Knicks | D192: YES | E192: - | F192: -1100 | G192: -
A193: 185 | B193: PLAYOFFS | C193: New York Knicks | D193: NO | E193: - | F193: 650 | G193: -
A194: 186 | B194: PLAYOFFS | C194: Philadelphia 76ers | D194: YES | E194: - | F194: -900 | G194: -
A195: 187 | B195: PLAYOFFS | C195: Philadelphia 76ers | D195: NO | E195: - | F195: 500 | G195: -
A196: 188 | B196: PLAYOFFS | C196: Oklahoma City Thunder | D196: YES | E196: - | F196: -10000 | G196: -
A197: 189 | B197: PLAYOFFS | C197: Oklahoma City Thunder | D197: NO | E197: - | F197: 2350 | G197: -
A198: 190 | B198: PLAYOFFS | C198: San Antonio Spurs | D198: YES | E198: - | F198: -10000 | G198: -
A199: 191 | B199: PLAYOFFS | C199: San Antonio Spurs | D199: NO | E199: - | F199: 2350 | G199: -
... A694: 686 | B694: LDR_TPG | C694: Coby White | D694: YES | E694: - | F694: 25000 | G694: -

Sheet M_DeVig
A1: NBA 2026-27 Futures Model
A2: M_DeVig - implied probabilities, overround, fair probabilities (Multiplicative / Power / Shin); two-way markets de-vigged as pairs
A3: Version: v1 | 2026-10-15
A5: PLAYIN markets target a sum of 4 (four play-in slots per conference); Shin is undefined for S<>1 so those use the Power method. Solver blocks (right) are grouped, not hidden.
A7: Row id | B7: Market | C7: Selection | D7: Side | E7: Line | F7: American | G7: Group key | H7: Decimal | I7: Implied prob | J7: Target sum S | K7: Outcomes in group | L7: Sum of implied | M7: Overround | N7: Fair - Multiplicative | O7: Fair - Power | P7: Fair - Shin | Q7: Fair - selected | R7: Power k | S7: Shin z | X7: Solver key | Y7: S | Z7: Sum implied | AA7: Power lo0 | AB7: Power hi0 | AC7: P1 mid | AD7: P1 g | AE7: P1 lo | AF7: P1 hi | AG7: P2 mid | AH7: P2 g | AI7: P2 lo | AJ7: P2 hi | AK7: P3 mid | AL7: P3 g | AM7: P3 lo | AN7: P3 hi | AO7: P4 mid | AP7: P4 g | AQ7: P4 lo | AR7: P4 hi | AS7: P5 mid | AT7: P5 g | AU7: P5 lo | AV7: P5 hi | AW7: P6 mid | AX7: P6 g | AY7: P6 lo | AZ7: P6 hi | BA7: P7 mid | BB7: P7 g | BC7: P7 lo | BD7: P7 hi | BE7: P8 mid | BF7: P8 g | BG7: P8 lo | BH7: P8 hi | BI7: P9 mid | BJ7: P9 g | BK7: P9 lo | BL7: P9 hi | BM7: P10 mid | BN7: P10 g | BO7: P10 lo | BP7: P10 hi | BQ7: P11 mid | BR7: P11 g | BS7: P11 lo | BT7: P11 hi | BU7: P12 mid | BV7: P12 g | BW7: P12 lo | BX7: P12 hi | BY7: P13 mid | BZ7: P13 g | CA7: P13 lo | CB7: P13 hi | CC7: P14 mid | CD7: P14 g | CE7: P14 lo | CF7: P14 hi | CG7: P15 mid | CH7: P15 g | CI7: P15 lo | CJ7: P15 hi | CK7: P16 mid | CL7: P16 g | CM7: P16 lo | CN7: P16 hi | CO7: P17 mid | CP7: P17 g | CQ7: P17 lo | CR7: P17 hi | CS7: P18 mid | CT7: P18 g | CU7: P18 lo | CV7: P18 hi | CW7: P19 mid | CX7: P19 g | CY7: P19 lo | CZ7: P19 hi | DA7: P20 mid | DB7: P20 g | DC7: P20 lo | DD7: P20 hi | DE7: P21 mid | DF7: P21 g | DG7: P21 lo | DH7: P21 hi | DI7: P22 mid | DJ7: P22 g | DK7: P22 lo | DL7: P22 hi | DM7: P23 mid | DN7: P23 g | DO7: P23 lo | DP7: P23 hi | DQ7: P24 mid | DR7: P24 g | DS7: P24 lo | DT7: P24 hi | DU7: P25 mid | DV7: P25 g | DW7: P25 lo | DX7: P25 hi | DY7: P26 mid | DZ7: P26 g | EA7: P26 lo | EB7: P26 hi | EC7: P27 mid | ED7: P27 g | EE7: P27 lo | EF7: P27 hi | EG7: P28 mid | EH7: P28 g | EI7: P28 lo | EJ7: P28 hi | EK7: P29 mid | EL7: P29 g | EM7: P29 lo | EN7: P29 hi | EO7: P30 mid | EP7: P30 g | EQ7: P30 lo | ER7: P30 hi | ES7: P31 mid | ET7: P31 g | EU7: P31 lo | EV7: P31 hi | EW7: P32 mid | EX7: P32 g | EY7: P32 lo | EZ7: P32 hi | FA7: Shin lo0 | FB7: Shin hi0 | FC7: Z1 mid | FD7: Z1 g | FE7: Z1 lo | FF7: Z1 hi | FG7: Z2 mid | FH7: Z2 g | FI7: Z2 lo | FJ7: Z2 hi | FK7: Z3 mid | FL7: Z3 g | FM7: Z3 lo | FN7: Z3 hi | FO7: Z4 mid | FP7: Z4 g | FQ7: Z4 lo | FR7: Z4 hi | FS7: Z5 mid | FT7: Z5 g | FU7: Z5 lo | FV7: Z5 hi | FW7: Z6 mid | FX7: Z6 g | FY7: Z6 lo | FZ7: Z6 hi | GA7: Z7 mid | GB7: Z7 g | GC7: Z7 lo | GD7: Z7 hi | GE7: Z8 mid | GF7: Z8 g | GG7: Z8 lo | GH7: Z8 hi | GI7: Z9 mid | GJ7: Z9 g | GK7: Z9 lo | GL7: Z9 hi | GM7: Z10 mid | GN7: Z10 g | GO7: Z10 lo | GP7: Z10 hi | GQ7: Z11 mid | GR7: Z11 g | GS7: Z11 lo | GT7: Z11 hi | GU7: Z12 mid | GV7: Z12 g | GW7: Z12 lo | GX7: Z12 hi | GY7: Z13 mid | GZ7: Z13 g | HA7: Z13 lo | HB7: Z13 hi | HC7: Z14 mid | HD7: Z14 g | HE7: Z14 lo | HF7: Z14 hi | HG7: Z15 mid | HH7: Z15 g | HI7: Z15 lo | HJ7: Z15 hi | HK7: Z16 mid | HL7: Z16 g | HM7: Z16 lo | HN7: Z16 hi | HO7: Z17 mid | HP7: Z17 g | HQ7: Z17 lo | HR7: Z17 hi | HS7: Z18 mid | HT7: Z18 g | HU7: Z18 lo | HV7: Z18 hi | HW7: Z19 mid | HX7: Z19 g | HY7: Z19 lo | HZ7: Z19 hi | IA7: Z20 mid | IB7: Z20 g | IC7: Z20 lo | ID7: Z20 hi | IE7: Z21 mid | IF7: Z21 g | IG7: Z21 lo | IH7: Z21 hi | II7: Z22 mid | IJ7: Z22 g | IK7: Z22 lo | IL7: Z22 hi | IM7: Z23 mid | IN7: Z23 g | IO7: Z23 lo | IP7: Z23 hi | IQ7: Z24 mid | IR7: Z24 g | IS7: Z24 lo | IT7: Z24 hi | IU7: Z25 mid | IV7: Z25 g | IW7: Z25 lo | IX7: Z25 hi | IY7: Z26 mid | IZ7: Z26 g | JA7: Z26 lo | JB7: Z26 hi | JC7: Z27 mid | JD7: Z27 g | JE7: Z27 lo | JF7: Z27 hi | JG7: Z28 mid | JH7: Z28 g | JI7: Z28 lo | JJ7: Z28 hi | JK7: Z29 mid | JL7: Z29 g | JM7: Z29 lo | JN7: Z29 hi | JO7: Z30 mid | JP7: Z30 g | JQ7: Z30 lo | JR7: Z30 hi | JS7: Z31 mid | JT7: Z31 g | JU7: Z31 lo | JV7: Z31 hi | JW7: Z32 mid | JX7: Z32 g | JY7: Z32 lo | JZ7: Z32 hi | KA7: Power k* | KB7: Shin z*
A8: =Odds_Input!A8 -> 0 | B8: =Odds_Input!B8 -> TITLE | C8: =Odds_Input!C8 -> Atlanta Hawks | D8: =Odds_Input!D8 -> YES | E8: =Odds_Input!E8 -> - | F8: =Odds_Input!F8 -> 6200 | G8: =IF(OR(B8="WINS",B8="PLAYOFFS"),B8&"|"&C8&IF(B8="WINS","|"&TEXT(E8,"0.0"),""),B8) -> TITLE | H8: =IF(F8>0,1+F8/100,1+100/ABS(F8)) -> 63 | I8: =1/H8 -> 0.015873016 | J8: =IF(LEFT(B8,6)="PLAYIN",A_playin_slots,1) -> 1 | K8: =COUNTIF($G$8:$G$694,G8) -> 30 | L8: =SUMIF($G$8:$G$694,G8,$I$8:$I$694) -> 1.2525652 | M8: =L8/J8-1 -> 0.25256519 | N8: =I8*J8/L8 -> 0.012672407 | O8: =I8^R8 -> 0.010522945 | P8: =IF(J8<>1,O8,IF(L8<=1,I8/L8,(SQRT(S8^2+4*(1-S8)*I8^2/L8)-S8)/(2*(1-S8)))) -> 0.0097295801 | Q8: =IF(A_devig="Multiplicative",N8,IF(A_devig="Power",O8,P8)) -> 0.0097295801 | R8: =INDEX($KA$8:$KA$96,MATCH(G8,$X$8:$X$96,0)) -> 1.0992153 | S8: =INDEX($KB$8:$KB$96,MATCH(G8,$X$8:$X$96,0)) -> 0.011051948 | X8: TITLE | Y8: =IF(LEFT(X8,6)="PLAYIN",A_playin_slots,1) -> 1 | Z8: =SUMIF($G$8:$G$694,X8,$I$8:$I$694) -> 1.2525652 | AA8: 0.2 | AB8: 10 | AC8: =(AA8+AB8)/2 -> 5.1 | AD8: =SUMPRODUCT(($G$8:$G$694=X8)*($I$8:$I$694^AC8))-Y8 -> -0.9966218 | AE8: =IF(AD8>0,AC8,AA8) -> 0.2 | AF8: =IF(AD8>0,AB8,AC8) -> 5.1 | AG8: =(AE8+AF8)/2 -> 2.65 | AH8: =SUMPRODUCT(($G$8:$G$694=X8)*($I$8:$I$694^AG8))-Y8 -> -0.9211095 | AI8: =IF(AH8>0,AG8,AE8) -> 0.2 | AJ8: =IF(AH8>0,AF8,AG8) -> 2.65 | AK8: =(AI8+AJ8)/2 -> 1.425 | AL8: =SUMPRODUCT(($G$8:$G$694=X8)*($I$8:$I$694^AK8))-Y8 -> -0.48196858 | AM8: =IF(AL8>0,AK8,AI8) -> 0.2 | AN8: =IF(AL8>0,AJ8,AK8) -> 1.425 | AO8: =(AM8+AN8)/2 -> 0.8125 | AP8: =SUMPRODUCT(($G$8:$G$694=X8)*($I$8:$I$694^AO8))-Y8 -> 0.99289234 | AQ8: =IF(AP8>0,AO8,AM8) -> 0.8125 | AR8: =IF(AP8>0,AN8,AO8) -> 1.425 | AS8: =(AQ8+AR8)/2 -> 1.11875 | AT8: =SUMPRODUCT(($G$8:$G$694=X8)*($I$8:$I$694^AS8))-Y8 -> -0.041910903 | AU8: =IF(AT8>0,AS8,AQ8) -> 0.8125 | AV8: =IF(AT8>0,AR8,AS8) -> 1.11875 | AW8: =(AU8+AV8)/2 -> 0.965625 | AX8: =SUMPRODUCT(($G$8:$G$694=X8)*($I$8:$I$694^AW8))-Y8 -> 0.35850666 | AY8: =IF(AX8>0,AW8,AU8) -> 0.965625 | AZ8: =IF(AX8>0,AV8,AW8) -> 1.11875 | BA8: =(AY8+AZ8)/2 -> 1.0421875 | BB8: =SUMPRODUCT(($G$8:$G$694=X8)*($I$8:$I$694^BA8))-Y8 -> 0.13634575 | BC8: =IF(BB8>0,BA8,AY8) -> 1.0421875 | BD8: =IF(BB8>0,AZ8,BA8) -> 1.11875 | BE8: =(BC8+BD8)/2 -> 1.0804687 | BF8: =SUMPRODUCT(($G$8:$G$694=X8)*($I$8:$I$694^BE8))-Y8 -> 0.042421245 | BG8: =IF(BF8>0,BE8,BC8) -> 1.0804687 | BH8: =IF(BF8>0,BD8,BE8) -> 1.11875 | BI8: =(BG8+BH8)/2 -> 1.0996094 | BJ8: =SUMPRODUCT(($G$8:$G$694=X8)*($I$8:$I$694^BI8))-Y8 -> -0.00086805204 | BK8: =IF(BJ8>0,BI8,BG8) -> 1.0804687 | BL8: =IF(BJ8>0,BH8,BI8) -> 1.0996094 | BM8: =(BK8+BL8)/2 -> 1.0900391 | BN8: =SUMPRODUCT(($G$8:$G$694=X8)*($I$8:$I$694^BM8))-Y8 -> 0.020486741 | BO8: =IF(BN8>0,BM8,BK8) -> 1.0900391 | BP8: =IF(BN8>0,BL8,BM8) -> 1.0996094 | BQ8: =(BO8+BP8)/2 -> 1.0948242 | BR8: =SUMPRODUCT(($G$8:$G$694=X8)*($I$8:$I$694^BQ8))-Y8 -> 0.0097380373 | BS8: =IF(BR8>0,BQ8,BO8) -> 1.0948242 | BT8: =IF(BR8>0,BP8,BQ8) -> 1.0996094 | BU8: =(BS8+BT8)/2 -> 1.0972168 | BV8: =SUMPRODUCT(($G$8:$G$694=X8)*($I$8:$I$694^BU8))-Y8 -> 0.0044173082 | BW8: =IF(BV8>0,BU8,BS8) -> 1.0972168 | BX8: =IF(BV8>0,BT8,BU8) -> 1.0996094 | BY8: =(BW8+BX8)/2 -> 1.0984131 | BZ8: =SUMPRODUCT(($G$8:$G$694=X8)*($I$8:$I$694^BY8))-Y8 -> 0.0017702246 | CA8: =IF(BZ8>0,BY8,BW8) -> 1.0984131 | CB8: =IF(BZ8>0,BX8,BY8) -> 1.0996094 | CC8: =(CA8+CB8)/2 -> 1.0990112 | CD8: =SUMPRODUCT(($G$8:$G$694=X8)*($I$8:$I$694^CC8))-Y8 -> 0.00044998762 | CE8: =IF(CD8>0,CC8,CA8) -> 1.0990112 | CF8: =IF(CD8>0,CB8,CC8) -> 1.0996094 | CG8: =(CE8+CF8)/2 -> 1.0993103 | CH8: =SUMPRODUCT(($G$8:$G$694=X8)*($I$8:$I$694^CG8))-Y8 -> -0.0002093066 | CI8: =IF(CH8>0,CG8,CE8) -> 1.0990112 | CJ8: =IF(CH8>0,CF8,CG8) -> 1.0993103 | CK8: =(CI8+CJ8)/2 -> 1.0991608 | CL8: =SUMPRODUCT(($G$8:$G$694=X8)*($I$8:$I$694^CK8))-Y8 -> 0.00012027187 | CM8: =IF(CL8>0,CK8,CI8) -> 1.0991608 | CN8: =IF(CL8>0,CJ8,CK8) -> 1.0993103 | CO8: =(CM8+CN8)/2 -> 1.0992355 | CP8: =SUMPRODUCT(($G$8:$G$694=X8)*($I$8:$I$694^CO8))-Y8 -> -4.4534519e-05 | CQ8: =IF(CP8>0,CO8,CM8) -> 1.0991608 | CR8: =IF(CP8>0,CN8,CO8) -> 1.0992355 | CS8: =(CQ8+CR8)/2 -> 1.0991982 | CT8: =SUMPRODUCT(($G$8:$G$694=X8)*($I$8:$I$694^CS8))-Y8 -> 3.7864388e-05 | CU8: =IF(CT8>0,CS8,CQ8) -> 1.0991982 | CV8: =IF(CT8>0,CR8,CS8) -> 1.0992355 | CW8: =(CU8+CV8)/2 -> 1.0992168 | CX8: =SUMPRODUCT(($G$8:$G$694=X8)*($I$8:$I$694^CW8))-Y8 -> -3.336138e-06 | CY8: =IF(CX8>0,CW8,CU8) -> 1.0991982 | CZ8: =IF(CX8>0,CV8,CW8) -> 1.0992168 | DA8: =(CY8+CZ8)/2 -> 1.0992075 | DB8: =SUMPRODUCT(($G$8:$G$694=X8)*($I$8:$I$694^DA8))-Y8 -> 1.7263857e-05 | DC8: =IF(DB8>0,DA8,CY8) -> 1.0992075 | DD8: =IF(DB8>0,CZ8,DA8) -> 1.0992168 | DE8: =(DC8+DD8)/2 -> 1.0992122 | DF8: =SUMPRODUCT(($G$8:$G$694=X8)*($I$8:$I$694^DE8))-Y8 -> 6.9637924e-06 | DG8: =IF(DF8>0,DE8,DC8) -> 1.0992122 | DH8: =IF(DF8>0,DD8,DE8) -> 1.0992168 | DI8: =(DG8+DH8)/2 -> 1.0992145 | DJ8: =SUMPRODUCT(($G$8:$G$694=X8)*($I$8:$I$694^DI8))-Y8 -> 1.8138105e-06 | DK8: =IF(DJ8>0,DI8,DG8) -> 1.0992145 | DL8: =IF(DJ8>0,DH8,DI8) -> 1.0992168 | DM8: =(DK8+DL8)/2 -> 1.0992157 | DN8: =SUMPRODUCT(($G$8:$G$694=X8)*($I$8:$I$694^DM8))-Y8 -> -7.6116794e-07 | DO8: =IF(DN8>0,DM8,DK8) -> 1.0992145 | DP8: =IF(DN8>0,DL8,DM8) -> 1.0992157 | DQ8: =(DO8+DP8)/2 -> 1.0992151 | DR8: =SUMPRODUCT(($G$8:$G$694=X8)*($I$8:$I$694^DQ8))-Y8 -> 5.2632022e-07 | DS8: =IF(DR8>0,DQ8,DO8) -> 1.0992151 | DT8: =IF(DR8>0,DP8,DQ8) -> 1.0992157 | DU8: =(DS8+DT8)/2 -> 1.0992154 | DV8: =SUMPRODUCT(($G$8:$G$694=X8)*($I$8:$I$694^DU8))-Y8 -> -1.1742412e-07 | DW8: =IF(DV8>0,DU8,DS8) -> 1.0992151 | DX8: =IF(DV8>0,DT8,DU8) -> 1.0992154 | DY8: =(DW8+DX8)/2 -> 1.0992152 | DZ8: =SUMPRODUCT(($G$8:$G$694=X8)*($I$8:$I$694^DY8))-Y8 -> 2.0444799e-07 | EA8: =IF(DZ8>0,DY8,DW8) -> 1.0992152 | EB8: =IF(DZ8>0,DX8,DY8) -> 1.0992154 | EC8: =(EA8+EB8)/2 -> 1.0992153 | ED8: =SUMPRODUCT(($G$8:$G$694=X8)*($I$8:$I$694^EC8))-Y8 -> 4.3511919e-08 | EE8: =IF(ED8>0,EC8,EA8) -> 1.0992153 | EF8: =IF(ED8>0,EB8,EC8) -> 1.0992154 | EG8: =(EE8+EF8)/2 -> 1.0992153 | EH8: =SUMPRODUCT(($G$8:$G$694=X8)*($I$8:$I$694^EG8))-Y8 -> -3.6956103e-08 | EI8: =IF(EH8>0,EG8,EE8) -> 1.0992153 | EJ8: =IF(EH8>0,EF8,EG8) -> 1.0992153 | EK8: =(EI8+EJ8)/2 -> 1.0992153 | EL8: =SUMPRODUCT(($G$8:$G$694=X8)*($I$8:$I$694^EK8))-Y8 -> 3.2779071e-09 | EM8: =IF(EL8>0,EK8,EI8) -> 1.0992153 | EN8: =IF(EL8>0,EJ8,EK8) -> 1.0992153 | EO8: =(EM8+EN8)/2 -> 1.0992153 | EP8: =SUMPRODUCT(($G$8:$G$694=X8)*($I$8:$I$694^EO8))-Y8 -> -1.6839098e-08 | EQ8: =IF(EP8>0,EO8,EM8) -> 1.0992153 | ER8: =IF(EP8>0,EN8,EO8) -> 1.0992153 | ES8: =(EQ8+ER8)/2 -> 1.0992153 | ET8: =SUMPRODUCT(($G$8:$G$694=X8)*($I$8:$I$694^ES8))-Y8 -> -6.7805958e-09 | EU8: =IF(ET8>0,ES8,EQ8) -> 1.0992153 | EV8: =IF(ET8>0,ER8,ES8) -> 1.0992153 | EW8: =(EU8+EV8)/2 -> 1.0992153 | EX8: =SUMPRODUCT(($G$8:$G$694=X8)*($I$8:$I$694^EW8))-Y8 -> -1.7513444e-09 | EY8: =IF(EX8>0,EW8,EU8) -> 1.0992153 | EZ8: =IF(EX8>0,EV8,EW8) -> 1.0992153 | FA8: 1e-06 | FB8: 0.9999 | FC8: =(FA8+FB8)/2 -> 0.4999505 | FD8: =(SUMPRODUCT(($G$8:$G$694=X8)*SQRT(FC8^2+4*(1-FC8)*$I$8:$I$694^2/Z8))-COUNTIF($G$8:$G$694,X8)*FC8)/(2*(1-FC8))-1 -> -0.70979199 | FE8: =IF(FD8>0,FC8,FA8) -> 1e-06 | FF8: =IF(FD8>0,FB8,FC8) -> 0.4999505 | FG8: =(FE8+FF8)/2 -> 0.24997575 | FH8: =(SUMPRODUCT(($G$8:$G$694=X8)*SQRT(FG8^2+4*(1-FG8)*$I$8:$I$694^2/Z8))-COUNTIF($G$8:$G$694,X8)*FG8)/(2*(1-FG8))-1 -> -0.54773389 | FI8: =IF(FH8>0,FG8,FE8) -> 1e-06 | FJ8: =IF(FH8>0,FF8,FG8) -> 0.24997575 | FK8: =(FI8+FJ8)/2 -> 0.12498837 | FL8: =(SUMPRODUCT(($G$8:$G$694=X8)*SQRT(FK8^2+4*(1-FK8)*$I$8:$I$694^2/Z8))-COUNTIF($G$8:$G$694,X8)*FK8)/(2*(1-FK8))-1 -> -0.39008224 | FM8: =IF(FL8>0,FK8,FI8) -> 1e-06 | FN8: =IF(FL8>0,FJ8,FK8) -> 0.12498837 | FO8: =(FM8+FN8)/2 -> 0.062494687 | FP8: =(SUMPRODUCT(($G$8:$G$694=X8)*SQRT(FO8^2+4*(1-FO8)*$I$8:$I$694^2/Z8))-COUNTIF($G$8:$G$694,X8)*FO8)/(2*(1-FO8))-1 -> -0.24780343 | FQ8: =IF(FP8>0,FO8,FM8) -> 1e-06 | FR8: =IF(FP8>0,FN8,FO8) -> 0.062494687 | FS8: =(FQ8+FR8)/2 -> 0.031247844 | FT8: =(SUMPRODUCT(($G$8:$G$694=X8)*SQRT(FS8^2+4*(1-FS8)*$I$8:$I$694^2/Z8))-COUNTIF($G$8:$G$694,X8)*FS8)/(2*(1-FS8))-1 -> -0.12712393 | FU8: =IF(FT8>0,FS8,FQ8) -> 1e-06 | FV8: =IF(FT8>0,FR8,FS8) -> 0.031247844 | FW8: =(FU8+FV8)/2 -> 0.015624422 | FX8: =(SUMPRODUCT(($G$8:$G$694=X8)*SQRT(FW8^2+4*(1-FW8)*$I$8:$I$694^2/Z8))-COUNTIF($G$8:$G$694,X8)*FW8)/(2*(1-FW8))-1 -> -0.034998898 | FY8: =IF(FX8>0,FW8,FU8) -> 1e-06 | FZ8: =IF(FX8>0,FV8,FW8) -> 0.015624422 | GA8: =(FY8+FZ8)/2 -> 0.0078127109 | GB8: =(SUMPRODUCT(($G$8:$G$694=X8)*SQRT(GA8^2+4*(1-GA8)*$I$8:$I$694^2/Z8))-COUNTIF($G$8:$G$694,X8)*GA8)/(2*(1-GA8))-1 -> 0.028479549 | GC8: =IF(GB8>0,GA8,FY8) -> 0.0078127109 | GD8: =IF(GB8>0,FZ8,GA8) -> 0.015624422 | GE8: =(GC8+GD8)/2 -> 0.011718566 | GF8: =(SUMPRODUCT(($G$8:$G$694=X8)*SQRT(GE8^2+4*(1-GE8)*$I$8:$I$694^2/Z8))-COUNTIF($G$8:$G$694,X8)*GE8)/(2*(1-GE8))-1 -> -0.0054378737 | GG8: =IF(GF8>0,GE8,GC8) -> 0.0078127109 | GH8: =IF(GF8>0,GD8,GE8) -> 0.011718566 | GI8: =(GG8+GH8)/2 -> 0.0097656387 | GJ8: =(SUMPRODUCT(($G$8:$G$694=X8)*SQRT(GI8^2+4*(1-GI8)*$I$8:$I$694^2/Z8))-COUNTIF($G$8:$G$694,X8)*GI8)/(2*(1-GI8))-1 -> 0.010874828 | GK8: =IF(GJ8>0,GI8,GG8) -> 0.0097656387 | GL8: =IF(GJ8>0,GH8,GI8) -> 0.011718566 | GM8: =(GK8+GL8)/2 -> 0.010742103 | GN8: =(SUMPRODUCT(($G$8:$G$694=X8)*SQRT(GM8^2+4*(1-GM8)*$I$8:$I$694^2/Z8))-COUNTIF($G$8:$G$694,X8)*GM8)/(2*(1-GM8))-1 -> 0.0025721335 | GO8: =IF(GN8>0,GM8,GK8) -> 0.010742103 | GP8: =IF(GN8>0,GL8,GM8) -> 0.011718566 | GQ8: =(GO8+GP8)/2 -> 0.011230334 | GR8: =(SUMPRODUCT(($G$8:$G$694=X8)*SQRT(GQ8^2+4*(1-GQ8)*$I$8:$I$694^2/Z8))-COUNTIF($G$8:$G$694,X8)*GQ8)/(2*(1-GQ8))-1 -> -0.0014678141 | GS8: =IF(GR8>0,GQ8,GO8) -> 0.010742103 | GT8: =IF(GR8>0,GP8,GQ8) -> 0.011230334 | GU8: =(GS8+GT8)/2 -> 0.010986219 | GV8: =(SUMPRODUCT(($G$8:$G$694=X8)*SQRT(GU8^2+4*(1-GU8)*$I$8:$I$694^2/Z8))-COUNTIF($G$8:$G$694,X8)*GU8)/(2*(1-GU8))-1 -> 0.00054322847 | GW8: =IF(GV8>0,GU8,GS8) -> 0.010986219 | GX8: =IF(GV8>0,GT8,GU8) -> 0.011230334 | GY8: =(GW8+GX8)/2 -> 0.011108276 | GZ8: =(SUMPRODUCT(($G$8:$G$694=X8)*SQRT(GY8^2+4*(1-GY8)*$I$8:$I$694^2/Z8))-COUNTIF($G$8:$G$694,X8)*GY8)/(2*(1-GY8))-1 -> -0.00046450061 | HA8: =IF(GZ8>0,GY8,GW8) -> 0.010986219 | HB8: =IF(GZ8>0,GX8,GY8) -> 0.011108276 | HC8: =(HA8+HB8)/2 -> 0.011047247 | HD8: =(SUMPRODUCT(($G$8:$G$694=X8)*SQRT(HC8^2+4*(1-HC8)*$I$8:$I$694^2/Z8))-COUNTIF($G$8:$G$694,X8)*HC8)/(2*(1-HC8))-1 -> 3.8808892e-05 | HE8: =IF(HD8>0,HC8,HA8) -> 0.011047247 | HF8: =IF(HD8>0,HB8,HC8) -> 0.011108276 | HG8: =(HE8+HF8)/2 -> 0.011077762 | HH8: =(SUMPRODUCT(($G$8:$G$694=X8)*SQRT(HG8^2+4*(1-HG8)*$I$8:$I$694^2/Z8))-COUNTIF($G$8:$G$694,X8)*HG8)/(2*(1-HG8))-1 -> -0.00021298423 | HI8: =IF(HH8>0,HG8,HE8) -> 0.011047247 | HJ8: =IF(HH8>0,HF8,HG8) -> 0.011077762 | HK8: =(HI8+HJ8)/2 -> 0.011062505 | HL8: =(SUMPRODUCT(($G$8:$G$694=X8)*SQRT(HK8^2+4*(1-HK8)*$I$8:$I$694^2/Z8))-COUNTIF($G$8:$G$694,X8)*HK8)/(2*(1-HK8))-1 -> -8.7122311e-05 | HM8: =IF(HL8>0,HK8,HI8) -> 0.011047247 | HN8: =IF(HL8>0,HJ8,HK8) -> 0.011062505 | HO8: =(HM8+HN8)/2 -> 0.011054876 | HP8: =(SUMPRODUCT(($G$8:$G$694=X8)*SQRT(HO8^2+4*(1-HO8)*$I$8:$I$694^2/Z8))-COUNTIF($G$8:$G$694,X8)*HO8)/(2*(1-HO8))-1 -> -2.4165376e-05 | HQ8: =IF(HP8>0,HO8,HM8) -> 0.011047247 | HR8: =IF(HP8>0,HN8,HO8) -> 0.011054876 | HS8: =(HQ8+HR8)/2 -> 0.011051062 | HT8: =(SUMPRODUCT(($G$8:$G$694=X8)*SQRT(HS8^2+4*(1-HS8)*$I$8:$I$694^2/Z8))-COUNTIF($G$8:$G$694,X8)*HS8)/(2*(1-HS8))-1 -> 7.3195904e-06 | HU8: =IF(HT8>0,HS8,HQ8) -> 0.011051062 | HV8: =IF(HT8>0,HR8,HS8) -> 0.011054876 | HW8: =(HU8+HV8)/2 -> 0.011052969 | HX8: =(SUMPRODUCT(($G$8:$G$694=X8)*SQRT(HW8^2+4*(1-HW8)*$I$8:$I$694^2/Z8))-COUNTIF($G$8:$G$694,X8)*HW8)/(2*(1-HW8))-1 -> -8.4234345e-06 | HY8: =IF(HX8>0,HW8,HU8) -> 0.011051062 | HZ8: =IF(HX8>0,HV8,HW8) -> 0.011052969 | IA8: =(HY8+HZ8)/2 -> 0.011052015 | IB8: =(SUMPRODUCT(($G$8:$G$694=X8)*SQRT(IA8^2+4*(1-IA8)*$I$8:$I$694^2/Z8))-COUNTIF($G$8:$G$694,X8)*IA8)/(2*(1-IA8))-1 -> -5.5205748e-07 | IC8: =IF(IB8>0,IA8,HY8) -> 0.011051062 | ID8: =IF(IB8>0,HZ8,IA8) -> 0.011052015 | IE8: =(IC8+ID8)/2 -> 0.011051539 | IF8: =(SUMPRODUCT(($G$8:$G$694=X8)*SQRT(IE8^2+4*(1-IE8)*$I$8:$I$694^2/Z8))-COUNTIF($G$8:$G$694,X8)*IE8)/(2*(1-IE8))-1 -> 3.3837326e-06 | IG8: =IF(IF8>0,IE8,IC8) -> 0.011051539 | IH8: =IF(IF8>0,ID8,IE8) -> 0.011052015 | II8: =(IG8+IH8)/2 -> 0.011051777 | IJ8: =(SUMPRODUCT(($G$8:$G$694=X8)*SQRT(II8^2+4*(1-II8)*$I$8:$I$694^2/Z8))-COUNTIF($G$8:$G$694,X8)*II8)/(2*(1-II8))-1 -> 1.4158291e-06 | IK8: =IF(IJ8>0,II8,IG8) -> 0.011051777 | IL8: =IF(IJ8>0,IH8,II8) -> 0.011052015 | IM8: =(IK8+IL8)/2 -> 0.011051896 | IN8: =(SUMPRODUCT(($G$8:$G$694=X8)*SQRT(IM8^2+4*(1-IM8)*$I$8:$I$694^2/Z8))-COUNTIF($G$8:$G$694,X8)*IM8)/(2*(1-IM8))-1 -> 4.318837e-07 | IO8: =IF(IN8>0,IM8,IK8) -> 0.011051896 | IP8: =IF(IN8>0,IL8,IM8) -> 0.011052015 | IQ8: =(IO8+IP8)/2 -> 0.011051956 | IR8: =(SUMPRODUCT(($G$8:$G$694=X8)*SQRT(IQ8^2+4*(1-IQ8)*$I$8:$I$694^2/Z8))-COUNTIF($G$8:$G$694,X8)*IQ8)/(2*(1-IQ8))-1 -> -6.0087419e-08 | IS8: =IF(IR8>0,IQ8,IO8) -> 0.011051896 | IT8: =IF(IR8>0,IP8,IQ8) -> 0.011051956 | IU8: =(IS8+IT8)/2 -> 0.011051926 | IV8: =(SUMPRODUCT(($G$8:$G$694=X8)*SQRT(IU8^2+4*(1-IU8)*$I$8:$I$694^2/Z8))-COUNTIF($G$8:$G$694,X8)*IU8)/(2*(1-IU8))-1 -> 1.8589801e-07 | IW8: =IF(IV8>0,IU8,IS8) -> 0.011051926 | IX8: =IF(IV8>0,IT8,IU8) -> 0.011051956 | IY8: =(IW8+IX8)/2 -> 0.011051941 | IZ8: =(SUMPRODUCT(($G$8:$G$694=X8)*SQRT(IY8^2+4*(1-IY8)*$I$8:$I$694^2/Z8))-COUNTIF($G$8:$G$694,X8)*IY8)/(2*(1-IY8))-1 -> 6.2905261e-08 | JA8: =IF(IZ8>0,IY8,IW8) -> 0.011051941 | JB8: =IF(IZ8>0,IX8,IY8) -> 0.011051956 | JC8: =(JA8+JB8)/2 -> 0.011051948 | JD8: =(SUMPRODUCT(($G$8:$G$694=X8)*SQRT(JC8^2+4*(1-JC8)*$I$8:$I$694^2/Z8))-COUNTIF($G$8:$G$694,X8)*JC8)/(2*(1-JC8))-1 -> 1.4089123e-09 | JE8: =IF(JD8>0,JC8,JA8) -> 0.011051948 | JF8: =IF(JD8>0,JB8,JC8) -> 0.011051956 | JG8: =(JE8+JF8)/2 -> 0.011051952 | JH8: =(SUMPRODUCT(($G$8:$G$694=X8)*SQRT(JG8^2+4*(1-JG8)*$I$8:$I$694^2/Z8))-COUNTIF($G$8:$G$694,X8)*JG8)/(2*(1-JG8))-1 -> -2.9339256e-08 | JI8: =IF(JH8>0,JG8,JE8) -> 0.011051948 | JJ8: =IF(JH8>0,JF8,JG8) -> 0.011051952 | JK8: =(JI8+JJ8)/2 -> 0.01105195 | JL8: =(SUMPRODUCT(($G$8:$G$694=X8)*SQRT(JK8^2+4*(1-JK8)*$I$8:$I$694^2/Z8))-COUNTIF($G$8:$G$694,X8)*JK8)/(2*(1-JK8))-1 -> -1.3965172e-08 | JM8: =IF(JL8>0,JK8,JI8) -> 0.011051948 | JN8: =IF(JL8>0,JJ8,JK8) -> 0.01105195 | JO8: =(JM8+JN8)/2 -> 0.011051949 | JP8: =(SUMPRODUCT(($G$8:$G$694=X8)*SQRT(JO8^2+4*(1-JO8)*$I$8:$I$694^2/Z8))-COUNTIF($G$8:$G$694,X8)*JO8)/(2*(1-JO8))-1 -> -6.2781301e-09 | JQ8: =IF(JP8>0,JO8,JM8) -> 0.011051948 | JR8: =IF(JP8>0,JN8,JO8) -> 0.011051949 | JS8: =(JQ8+JR8)/2 -> 0.011051949 | JT8: =(SUMPRODUCT(($G$8:$G$694=X8)*SQRT(JS8^2+4*(1-JS8)*$I$8:$I$694^2/Z8))-COUNTIF($G$8:$G$694,X8)*JS8)/(2*(1-JS8))-1 -> -2.4346092e-09 | JU8: =IF(JT8>0,JS8,JQ8) -> 0.011051948 | JV8: =IF(JT8>0,JR8,JS8) -> 0.011051949 | JW8: =(JU8+JV8)/2 -> 0.011051949 | JX8: =(SUMPRODUCT(($G$8:$G$694=X8)*SQRT(JW8^2+4*(1-JW8)*$I$8:$I$694^2/Z8))-COUNTIF($G$8:$G$694,X8)*JW8)/(2*(1-JW8))-1 -> -5.1284821e-10 | JY8: =IF(JX8>0,JW8,JU8) -> 0.011051948 | JZ8: =IF(JX8>0,JV8,JW8) -> 0.011051949 | KA8: =(EY8+EZ8)/2 -> 1.0992153 | KB8: =(JY8+JZ8)/2 -> 0.011051948
A9: =Odds_Input!A9 -> 1 | B9: =Odds_Input!B9 -> TITLE | C9: =Odds_Input!C9 -> Boston Celtics | D9: =Odds_Input!D9 -> YES | E9: =Odds_Input!E9 -> - | F9: =Odds_Input!F9 -> 1400 | G9: =IF(OR(B9="WINS",B9="PLAYOFFS"),B9&"|"&C9&IF(B9="WINS","|"&TEXT(E9,"0.0"),""),B9) -> TITLE | H9: =IF(F9>0,1+F9/100,1+100/ABS(F9)) -> 15 | I9: =1/H9 -> 0.066666667 | J9: =IF(LEFT(B9,6)="PLAYIN",A_playin_slots,1) -> 1 | K9: =COUNTIF($G$8:$G$694,G9) -> 30 | L9: =SUMIF($G$8:$G$694,G9,$I$8:$I$694) -> 1.2525652 | M9: =L9/J9-1 -> 0.25256519 | N9: =I9*J9/L9 -> 0.053224109 | O9: =I9^R9 -> 0.050959183 | P9: =IF(J9<>1,O9,IF(L9<=1,I9/L9,(SQRT(S9^2+4*(1-S9)*I9^2/L9)-S9)/(2*(1-S9)))) -> 0.054571644 | Q9: =IF(A_devig="Multiplicative",N9,IF(A_devig="Power",O9,P9)) -> 0.054571644 | R9: =INDEX($KA$8:$KA$96,MATCH(G9,$X$8:$X$96,0)) -> 1.0992153 | S9: =INDEX($KB$8:$KB$96,MATCH(G9,$X$8:$X$96,0)) -> 0.011051948 | X9: CONF_EAST | Y9: =IF(LEFT(X9,6)="PLAYIN",A_playin_slots,1) -> 1 | Z9: =SUMIF($G$8:$G$694,X9,$I$8:$I$694) -> 1.2088752 | AA9: 0.2 | AB9: 10 | AC9: =(AA9+AB9)/2 -> 5.1 | AD9: =SUMPRODUCT(($G$8:$G$694=X9)*($I$8:$I$694^AC9))-Y9 -> -0.99890686 | AE9: =IF(AD9>0,AC9,AA9) -> 0.2 | AF9: =IF(AD9>0,AB9,AC9) -> 5.1 | AG9: =(AE9+AF9)/2 -> 2.65 | AH9: =SUMPRODUCT(($G$8:$G$694=X9)*($I$8:$I$694^AG9))-Y9 -> -0.94506435 | AI9: =IF(AH9>0,AG9,AE9) -> 0.2 | AJ9: =IF(AH9>0,AF9,AG9) -> 2.65 | AK9: =(AI9+AJ9)/2 -> 1.425 | AL9: =SUMPRODUCT(($G$8:$G$694=X9)*($I$8:$I$694^AK9))-Y9 -> -0.49229824 | AM9: =IF(AL9>0,AK9,AI9) -> 0.2 | AN9: =IF(AL9>0,AJ9,AK9) -> 1.425 | AO9: =(AM9+AN9)/2 -> 0.8125 | AP9: =SUMPRODUCT(($G$8:$G$694=X9)*($I$8:$I$694^AO9))-Y9 -> 0.81849268 | AQ9: =IF(AP9>0,AO9,AM9) -> 0.8125 | AR9: =IF(AP9>0,AN9,AO9) -> 1.425 | AS9: =(AQ9+AR9)/2 -> 1.11875 | AT9: =SUMPRODUCT(($G$8:$G$694=X9)*($I$8:$I$694^AS9))-Y9 -> -0.058207618 | AU9: =IF(AT9>0,AS9,AQ9) -> 0.8125 | AV9: =IF(AT9>0,AR9,AS9) -> 1.11875 | AW9: =(AU9+AV9)/2 -> 0.965625 | AX9: =SUMPRODUCT(($G$8:$G$694=X9)*($I$8:$I$694^AW9))-Y9 -> 0.30106108 | AY9: =IF(AX9>0,AW9,AU9) -> 0.965625 | AZ9: =IF(AX9>0,AV9,AW9) -> 1.11875 | BA9: =(AY9+AZ9)/2 -> 1.0421875 | BB9: =SUMPRODUCT(($G$8:$G$694=X9)*($I$8:$I$694^BA9))-Y9 -> 0.10546614 | BC9: =IF(BB9>0,BA9,AY9) -> 1.0421875 | BD9: =IF(BB9>0,AZ9,BA9) -> 1.11875 | BE9: =(BC9+BD9)/2 -> 1.0804687 | BF9: =SUMPRODUCT(($G$8:$G$694=X9)*($I$8:$I$694^BE9))-Y9 -> 0.020025117 | BG9: =IF(BF9>0,BE9,BC9) -> 1.0804687 | BH9: =IF(BF9>0,BD9,BE9) -> 1.11875 | BI9: =(BG9+BH9)/2 -> 1.0996094 | BJ9: =SUMPRODUCT(($G$8:$G$694=X9)*($I$8:$I$694^BI9))-Y9 -> -0.019948631 | BK9: =IF(BJ9>0,BI9,BG9) -> 1.0804687 | BL9: =IF(BJ9>0,BH9,BI9) -> 1.0996094 | BM9: =(BK9+BL9)/2 -> 1.0900391 | BN9: =SUMPRODUCT(($G$8:$G$694=X9)*($I$8:$I$694^BM9))-Y9 -> -0.00018137125 | BO9: =IF(BN9>0,BM9,BK9) -> 1.0804687 | BP9: =IF(BN9>0,BL9,BM9) -> 1.0900391 | BQ9: =(BO9+BP9)/2 -> 1.0852539 | BR9: =SUMPRODUCT(($G$8:$G$694=X9)*($I$8:$I$694^BQ9))-Y9 -> 0.0098662946 | BS9: =IF(BR9>0,BQ9,BO9) -> 1.0852539 | BT9: =IF(BR9>0,BP9,BQ9) -> 1.0900391 | BU9: =(BS9+BT9)/2 -> 1.0876465 | BV9: =SUMPRODUCT(($G$8:$G$694=X9)*($I$8:$I$694^BU9))-Y9 -> 0.0048286522 | BW9: =IF(BV9>0,BU9,BS9) -> 1.0876465 | BX9: =IF(BV9>0,BT9,BU9) -> 1.0900391 | BY9: =(BW9+BX9)/2 -> 1.0888428 | BZ9: =SUMPRODUCT(($G$8:$G$694=X9)*($I$8:$I$694^BY9))-Y9 -> 0.0023201987 | CA9: =IF(BZ9>0,BY9,BW9) -> 1.0888428 | CB9: =IF(BZ9>0,BX9,BY9) -> 1.0900391 | CC9: =(CA9+CB9)/2 -> 1.0894409 | CD9: =SUMPRODUCT(($G$8:$G$694=X9)*($I$8:$I$694^CC9))-Y9 -> 0.0010685546 | CE9: =IF(CD9>0,CC9,CA9) -> 1.0894409 | CF9: =IF(CD9>0,CB9,CC9) -> 1.0900391 | CG9: =(CE9+CF9)/2 -> 1.08974 | CH9: =SUMPRODUCT(($G$8:$G$694=X9)*($I$8:$I$694^CG9))-Y9 -> 0.00044337705 | CI9: =IF(CH9>0,CG9,CE9) -> 1.08974 | CJ9: =IF(CH9>0,CF9,CG9) -> 1.0900391 | CK9: =(CI9+CJ9)/2 -> 1.0898895 | CL9: =SUMPRODUCT(($G$8:$G$694=X9)*($I$8:$I$694^CK9))-Y9 -> 0.00013094927 | CM9: =IF(CL9>0,CK9,CI9) -> 1.0898895 | CN9: =IF(CL9>0,CJ9,CK9) -> 1.0900391 | CO9: =(CM9+CN9)/2 -> 1.0899643 | CP9: =SUMPRODUCT(($G$8:$G$694=X9)*($I$8:$I$694^CO9))-Y9 -> -2.5224396e-05 | CQ9: =IF(CP9>0,CO9,CM9) -> 1.0898895 | CR9: =IF(CP9>0,CN9,CO9) -> 1.0899643 | CS9: =(CQ9+CR9)/2 -> 1.0899269 | CT9: =SUMPRODUCT(($G$8:$G$694=X9)*($I$8:$I$694^CS9))-Y9 -> 5.2859084e-05 | CU9: =IF(CT9>0,CS9,CQ9) -> 1.0899269 | CV9: =IF(CT9>0,CR9,CS9) -> 1.0899643 | CW9: =(CU9+CV9)/2 -> 1.0899456 | CX9: =SUMPRODUCT(($G$8:$G$694=X9)*($I$8:$I$694^CW9))-Y9 -> 1.3816506e-05 | CY9: =IF(CX9>0,CW9,CU9) -> 1.0899456 | CZ9: =IF(CX9>0,CV9,CW9) -> 1.0899643 | DA9: =(CY9+CZ9)/2 -> 1.0899549 | DB9: =SUMPRODUCT(($G$8:$G$694=X9)*($I$8:$I$694^DA9))-Y9 -> -5.7041543e-06 | DC9: =IF(DB9>0,DA9,CY9) -> 1.0899456 | DD9: =IF(DB9>0,CZ9,DA9) -> 1.0899549 | DE9: =(DC9+DD9)/2 -> 1.0899503 | DF9: =SUMPRODUCT(($G$8:$G$694=X9)*($I$8:$I$694^DE9))-Y9 -> 4.0561236e-06 | DG9: =IF(DF9>0,DE9,DC9) -> 1.0899503 | DH9: =IF(DF9>0,DD9,DE9) -> 1.0899549 | DI9: =(DG9+DH9)/2 -> 1.0899526 | DJ9: =SUMPRODUCT(($G$8:$G$694=X9)*($I$8:$I$694^DI9))-Y9 -> -8.2402844e-07 | DK9: =IF(DJ9>0,DI9,DG9) -> 1.0899503 | DL9: =IF(DJ9>0,DH9,DI9) -> 1.0899526 | DM9: =(DK9+DL9)/2 -> 1.0899514 | DN9: =SUMPRODUCT(($G$8:$G$694=X9)*($I$8:$I$694^DM9))-Y9 -> 1.6160443e-06 | DO9: =IF(DN9>0,DM9,DK9) -> 1.0899514 | DP9: =IF(DN9>0,DL9,DM9) -> 1.0899526 | DQ9: =(DO9+DP9)/2 -> 1.089952 | DR9: =SUMPRODUCT(($G$8:$G$694=X9)*($I$8:$I$694^DQ9))-Y9 -> 3.9600712e-07 | DS9: =IF(DR9>0,DQ9,DO9) -> 1.089952 | DT9: =IF(DR9>0,DP9,DQ9) -> 1.0899526 | DU9: =(DS9+DT9)/2 -> 1.0899523 | DV9: =SUMPRODUCT(($G$8:$G$694=X9)*($I$8:$I$694^DU9))-Y9 -> -2.1401086e-07 | DW9: =IF(DV9>0,DU9,DS9) -> 1.089952 | DX9: =IF(DV9>0,DT9,DU9) -> 1.0899523 | DY9: =(DW9+DX9)/2 -> 1.0899522 | DZ9: =SUMPRODUCT(($G$8:$G$694=X9)*($I$8:$I$694^DY9))-Y9 -> 9.0998077e-08 | EA9: =IF(DZ9>0,DY9,DW9) -> 1.0899522 | EB9: =IF(DZ9>0,DX9,DY9) -> 1.0899523 | EC9: =(EA9+EB9)/2 -> 1.0899522 | ED9: =SUMPRODUCT(($G$8:$G$694=X9)*($I$8:$I$694^EC9))-Y9 -> -6.1506407e-08 | EE9: =IF(ED9>0,EC9,EA9) -> 1.0899522 | EF9: =IF(ED9>0,EB9,EC9) -> 1.0899522 | EG9: =(EE9+EF9)/2 -> 1.0899522 | EH9: =SUMPRODUCT(($G$8:$G$694=X9)*($I$8:$I$694^EG9))-Y9 -> 1.4745832e-08 | EI9: =IF(EH9>0,EG9,EE9) -> 1.0899522 | EJ9: =IF(EH9>0,EF9,EG9) -> 1.0899522 | EK9: =(EI9+EJ9)/2 -> 1.0899522 | EL9: =SUMPRODUCT(($G$8:$G$694=X9)*($I$8:$I$694^EK9))-Y9 -> -2.3380288e-08 | EM9: =IF(EL9>0,EK9,EI9) -> 1.0899522 | EN9: =IF(EL9>0,EJ9,EK9) -> 1.0899522 | EO9: =(EM9+EN9)/2 -> 1.0899522 | EP9: =SUMPRODUCT(($G$8:$G$694=X9)*($I$8:$I$694^EO9))-Y9 -> -4.3172282e-09 | EQ9: =IF(EP9>0,EO9,EM9) -> 1.0899522 | ER9: =IF(EP9>0,EN9,EO9) -> 1.0899522 | ES9: =(EQ9+ER9)/2 -> 1.0899522 | ET9: =SUMPRODUCT(($G$8:$G$694=X9)*($I$8:$I$694^ES9))-Y9 -> 5.2143019e-09 | EU9: =IF(ET9>0,ES9,EQ9) -> 1.0899522 | EV9: =IF(ET9>0,ER9,ES9) -> 1.0899522 | EW9: =(EU9+EV9)/2 -> 1.0899522 | EX9: =SUMPRODUCT(($G$8:$G$694=X9)*($I$8:$I$694^EW9))-Y9 -> 4.4853699e-10 | EY9: =IF(EX9>0,EW9,EU9) -> 1.0899522 | EZ9: =IF(EX9>0,EV9,EW9) -> 1.0899522 | FA9: 1e-06 | FB9: 0.9999 | FC9: =(FA9+FB9)/2 -> 0.4999505 | FD9: =(SUMPRODUCT(($G$8:$G$694=X9)*SQRT(FC9^2+4*(1-FC9)*$I$8:$I$694^2/Z9))-COUNTIF($G$8:$G$694,X9)*FC9)/(2*(1-FC9))-1 -> -0.7301445 | FE9: =IF(FD9>0,FC9,FA9) -> 1e-06 | FF9: =IF(FD9>0,FB9,FC9) -> 0.4999505 | FG9: =(FE9+FF9)/2 -> 0.24997575 | FH9: =(SUMPRODUCT(($G$8:$G$694=X9)*SQRT(FG9^2+4*(1-FG9)*$I$8:$I$694^2/Z9))-COUNTIF($G$8:$G$694,X9)*FG9)/(2*(1-FG9))-1 -> -0.54469486 | FI9: =IF(FH9>0,FG9,FE9) -> 1e-06 | FJ9: =IF(FH9>0,FF9,FG9) -> 0.24997575 | FK9: =(FI9+FJ9)/2 -> 0.12498837 | FL9: =(SUMPRODUCT(($G$8:$G$694=X9)*SQRT(FK9^2+4*(1-FK9)*$I$8:$I$694^2/Z9))-COUNTIF($G$8:$G$694,X9)*FK9)/(2*(1-FK9))-1 -> -0.3446146 | FM9: =IF(FL9>0,FK9,FI9) -> 1e-06 | FN9: =IF(FL9>0,FJ9,FK9) -> 0.12498837 | FO9: =(FM9+FN9)/2 -> 0.062494687 | FP9: =(SUMPRODUCT(($G$8:$G$694=X9)*SQRT(FO9^2+4*(1-FO9)*$I$8:$I$694^2/Z9))-COUNTIF($G$8:$G$694,X9)*FO9)/(2*(1-FO9))-1 -> -0.17673886 | FQ9: =IF(FP9>0,FO9,FM9) -> 1e-06 | FR9: =IF(FP9>0,FN9,FO9) -> 0.062494687 | FS9: =(FQ9+FR9)/2 -> 0.031247844 | FT9: =(SUMPRODUCT(($G$8:$G$694=X9)*SQRT(FS9^2+4*(1-FS9)*$I$8:$I$694^2/Z9))-COUNTIF($G$8:$G$694,X9)*FS9)/(2*(1-FS9))-1 -> -0.060210912 | FU9: =IF(FT9>0,FS9,FQ9) -> 1e-06 | FV9: =IF(FT9>0,FR9,FS9) -> 0.031247844 | FW9: =(FU9+FV9)/2 -> 0.015624422 | FX9: =(SUMPRODUCT(($G$8:$G$694=X9)*SQRT(FW9^2+4*(1-FW9)*$I$8:$I$694^2/Z9))-COUNTIF($G$8:$G$694,X9)*FW9)/(2*(1-FW9))-1 -> 0.010915881 | FY9: =IF(FX9>0,FW9,FU9) -> 0.015624422 | FZ9: =IF(FX9>0,FV9,FW9) -> 0.031247844 | GA9: =(FY9+FZ9)/2 -> 0.023436133 | GB9: =(SUMPRODUCT(($G$8:$G$694=X9)*SQRT(GA9^2+4*(1-GA9)*$I$8:$I$694^2/Z9))-COUNTIF($G$8:$G$694,X9)*GA9)/(2*(1-GA9))-1 -> -0.025996703 | GC9: =IF(GB9>0,GA9,FY9) -> 0.015624422 | GD9: =IF(GB9>0,FZ9,GA9) -> 0.023436133 | GE9: =(GC9+GD9)/2 -> 0.019530277 | GF9: =(SUMPRODUCT(($G$8:$G$694=X9)*SQRT(GE9^2+4*(1-GE9)*$I$8:$I$694^2/Z9))-COUNTIF($G$8:$G$694,X9)*GE9)/(2*(1-GE9))-1 -> -0.007915688 | GG9: =IF(GF9>0,GE9,GC9) -> 0.015624422 | GH9: =IF(GF9>0,GD9,GE9) -> 0.019530277 | GI9: =(GG9+GH9)/2 -> 0.01757735 | GJ9: =(SUMPRODUCT(($G$8:$G$694=X9)*SQRT(GI9^2+4*(1-GI9)*$I$8:$I$694^2/Z9))-COUNTIF($G$8:$G$694,X9)*GI9)/(2*(1-GI9))-1 -> 0.0013995784 | GK9: =IF(GJ9>0,GI9,GG9) -> 0.01757735 | GL9: =IF(GJ9>0,GH9,GI9) -> 0.019530277 | GM9: =(GK9+GL9)/2 -> 0.018553813 | GN9: =(SUMPRODUCT(($G$8:$G$694=X9)*SQRT(GM9^2+4*(1-GM9)*$I$8:$I$694^2/Z9))-COUNTIF($G$8:$G$694,X9)*GM9)/(2*(1-GM9))-1 -> -0.0032822131 | GO9: =IF(GN9>0,GM9,GK9) -> 0.01757735 | GP9: =IF(GN9>0,GL9,GM9) -> 0.018553813 | GQ9: =(GO9+GP9)/2 -> 0.018065582 | GR9: =(SUMPRODUCT(($G$8:$G$694=X9)*SQRT(GQ9^2+4*(1-GQ9)*$I$8:$I$694^2/Z9))-COUNTIF($G$8:$G$694,X9)*GQ9)/(2*(1-GQ9))-1 -> -0.00094746802 | GS9: =IF(GR9>0,GQ9,GO9) -> 0.01757735 | GT9: =IF(GR9>0,GP9,GQ9) -> 0.018065582 | GU9: =(GS9+GT9)/2 -> 0.017821466 | GV9: =(SUMPRODUCT(($G$8:$G$694=X9)*SQRT(GU9^2+4*(1-GU9)*$I$8:$I$694^2/Z9))-COUNTIF($G$8:$G$694,X9)*GU9)/(2*(1-GU9))-1 -> 0.00022450282 | GW9: =IF(GV9>0,GU9,GS9) -> 0.017821466 | GX9: =IF(GV9>0,GT9,GU9) -> 0.018065582 | GY9: =(GW9+GX9)/2 -> 0.017943524 | GZ9: =(SUMPRODUCT(($G$8:$G$694=X9)*SQRT(GY9^2+4*(1-GY9)*$I$8:$I$694^2/Z9))-COUNTIF($G$8:$G$694,X9)*GY9)/(2*(1-GY9))-1 -> -0.00036186882 | HA9: =IF(GZ9>0,GY9,GW9) -> 0.017821466 | HB9: =IF(GZ9>0,GX9,GY9) -> 0.017943524 | HC9: =(HA9+HB9)/2 -> 0.017882495 | HD9: =(SUMPRODUCT(($G$8:$G$694=X9)*SQRT(HC9^2+4*(1-HC9)*$I$8:$I$694^2/Z9))-COUNTIF($G$8:$G$694,X9)*HC9)/(2*(1-HC9))-1 -> -6.8779786e-05 | HE9: =IF(HD9>0,HC9,HA9) -> 0.017821466 | HF9: =IF(HD9>0,HB9,HC9) -> 0.017882495 | HG9: =(HE9+HF9)/2 -> 0.01785198 | HH9: =(SUMPRODUCT(($G$8:$G$694=X9)*SQRT(HG9^2+4*(1-HG9)*$I$8:$I$694^2/Z9))-COUNTIF($G$8:$G$694,X9)*HG9)/(2*(1-HG9))-1 -> 7.783729e-05 | HI9: =IF(HH9>0,HG9,HE9) -> 0.01785198 | HJ9: =IF(HH9>0,HF9,HG9) -> 0.017882495 | HK9: =(HI9+HJ9)/2 -> 0.017867237 | HL9: =(SUMPRODUCT(($G$8:$G$694=X9)*SQRT(HK9^2+4*(1-HK9)*$I$8:$I$694^2/Z9))-COUNTIF($G$8:$G$694,X9)*HK9)/(2*(1-HK9))-1 -> 4.5226994e-06 | HM9: =IF(HL9>0,HK9,HI9) -> 0.017867237 | HN9: =IF(HL9>0,HJ9,HK9) -> 0.017882495 | HO9: =(HM9+HN9)/2 -> 0.017874866 | HP9: =(SUMPRODUCT(($G$8:$G$694=X9)*SQRT(HO9^2+4*(1-HO9)*$I$8:$I$694^2/Z9))-COUNTIF($G$8:$G$694,X9)*HO9)/(2*(1-HO9))-1 -> -3.2130056e-05 | HQ9: =IF(HP9>0,HO9,HM9) -> 0.017867237 | HR9: =IF(HP9>0,HN9,HO9) -> 0.017874866 | HS9: =(HQ9+HR9)/2 -> 0.017871052 | HT9: =(SUMPRODUCT(($G$8:$G$694=X9)*SQRT(HS9^2+4*(1-HS9)*$I$8:$I$694^2/Z9))-COUNTIF($G$8:$G$694,X9)*HS9)/(2*(1-HS9))-1 -> -1.3804057e-05 | HU9: =IF(HT9>0,HS9,HQ9) -> 0.017867237 | HV9: =IF(HT9>0,HR9,HS9) -> 0.017871052 | HW9: =(HU9+HV9)/2 -> 0.017869144 | HX9: =(SUMPRODUCT(($G$8:$G$694=X9)*SQRT(HW9^2+4*(1-HW9)*$I$8:$I$694^2/Z9))-COUNTIF($G$8:$G$694,X9)*HW9)/(2*(1-HW9))-1 -> -4.6407732e-06 | HY9: =IF(HX9>0,HW9,HU9) -> 0.017867237 | HZ9: =IF(HX9>0,HV9,HW9) -> 0.017869144 | IA9: =(HY9+HZ9)/2 -> 0.017868191 | IB9: =(SUMPRODUCT(($G$8:$G$694=X9)*SQRT(IA9^2+4*(1-IA9)*$I$8:$I$694^2/Z9))-COUNTIF($G$8:$G$694,X9)*IA9)/(2*(1-IA9))-1 -> -5.9060543e-08 | IC9: =IF(IB9>0,IA9,HY9) -> 0.017867237 | ID9: =IF(IB9>0,HZ9,IA9) -> 0.017868191 | IE9: =(IC9+ID9)/2 -> 0.017867714 | IF9: =(SUMPRODUCT(($G$8:$G$694=X9)*SQRT(IE9^2+4*(1-IE9)*$I$8:$I$694^2/Z9))-COUNTIF($G$8:$G$694,X9)*IE9)/(2*(1-IE9))-1 -> 2.2318135e-06 | IG9: =IF(IF9>0,IE9,IC9) -> 0.017867714 | IH9: =IF(IF9>0,ID9,IE9) -> 0.017868191 | II9: =(IG9+IH9)/2 -> 0.017867953 | IJ9: =(SUMPRODUCT(($G$8:$G$694=X9)*SQRT(II9^2+4*(1-II9)*$I$8:$I$694^2/Z9))-COUNTIF($G$8:$G$694,X9)*II9)/(2*(1-II9))-1 -> 1.086375e-06 | IK9: =IF(IJ9>0,II9,IG9) -> 0.017867953 | IL9: =IF(IJ9>0,IH9,II9) -> 0.017868191 | IM9: =(IK9+IL9)/2 -> 0.017868072 | IN9: =(SUMPRODUCT(($G$8:$G$694=X9)*SQRT(IM9^2+4*(1-IM9)*$I$8:$I$694^2/Z9))-COUNTIF($G$8:$G$694,X9)*IM9)/(2*(1-IM9))-1 -> 5.1365686e-07 | IO9: =IF(IN9>0,IM9,IK9) -> 0.017868072 | IP9: =IF(IN9>0,IL9,IM9) -> 0.017868191 | IQ9: =(IO9+IP9)/2 -> 0.017868131 | IR9: =(SUMPRODUCT(($G$8:$G$694=X9)*SQRT(IQ9^2+4*(1-IQ9)*$I$8:$I$694^2/Z9))-COUNTIF($G$8:$G$694,X9)*IQ9)/(2*(1-IQ9))-1 -> 2.2729807e-07 | IS9: =IF(IR9>0,IQ9,IO9) -> 0.017868131 | IT9: =IF(IR9>0,IP9,IQ9) -> 0.017868191 | IU9: =(IS9+IT9)/2 -> 0.017868161 | IV9: =(SUMPRODUCT(($G$8:$G$694=X9)*SQRT(IU9^2+4*(1-IU9)*$I$8:$I$694^2/Z9))-COUNTIF($G$8:$G$694,X9)*IU9)/(2*(1-IU9))-1 -> 8.4118739e-08 | IW9: =IF(IV9>0,IU9,IS9) -> 0.017868161 | IX9: =IF(IV9>0,IT9,IU9) -> 0.017868191 | IY9: =(IW9+IX9)/2 -> 0.017868176 | IZ9: =(SUMPRODUCT(($G$8:$G$694=X9)*SQRT(IY9^2+4*(1-IY9)*$I$8:$I$694^2/Z9))-COUNTIF($G$8:$G$694,X9)*IY9)/(2*(1-IY9))-1 -> 1.2529092e-08 | JA9: =IF(IZ9>0,IY9,IW9) -> 0.017868176 | JB9: =IF(IZ9>0,IX9,IY9) -> 0.017868191 | JC9: =(JA9+JB9)/2 -> 0.017868183 | JD9: =(SUMPRODUCT(($G$8:$G$694=X9)*SQRT(JC9^2+4*(1-JC9)*$I$8:$I$694^2/Z9))-COUNTIF($G$8:$G$694,X9)*JC9)/(2*(1-JC9))-1 -> -2.3265727e-08 | JE9: =IF(JD9>0,JC9,JA9) -> 0.017868176 | JF9: =IF(JD9>0,JB9,JC9) -> 0.017868183 | JG9: =(JE9+JF9)/2 -> 0.01786818 | JH9: =(SUMPRODUCT(($G$8:$G$694=X9)*SQRT(JG9^2+4*(1-JG9)*$I$8:$I$694^2/Z9))-COUNTIF($G$8:$G$694,X9)*JG9)/(2*(1-JG9))-1 -> -5.3683172e-09 | JI9: =IF(JH9>0,JG9,JE9) -> 0.017868176 | JJ9: =IF(JH9>0,JF9,JG9) -> 0.01786818 | JK9: =(JI9+JJ9)/2 -> 0.017868178 | JL9: =(SUMPRODUCT(($G$8:$G$694=X9)*SQRT(JK9^2+4*(1-JK9)*$I$8:$I$694^2/Z9))-COUNTIF($G$8:$G$694,X9)*JK9)/(2*(1-JK9))-1 -> 3.5803875e-09 | JM9: =IF(JL9>0,JK9,JI9) -> 0.017868178 | JN9: =IF(JL9>0,JJ9,JK9) -> 0.01786818 | JO9: =(JM9+JN9)/2 -> 0.017868179 | JP9: =(SUMPRODUCT(($G$8:$G$694=X9)*SQRT(JO9^2+4*(1-JO9)*$I$8:$I$694^2/Z9))-COUNTIF($G$8:$G$694,X9)*JO9)/(2*(1-JO9))-1 -> -8.9396512e-10 | JQ9: =IF(JP9>0,JO9,JM9) -> 0.017868178 | JR9: =IF(JP9>0,JN9,JO9) -> 0.017868179 | JS9: =(JQ9+JR9)/2 -> 0.017868178 | JT9: =(SUMPRODUCT(($G$8:$G$694=X9)*SQRT(JS9^2+4*(1-JS9)*$I$8:$I$694^2/Z9))-COUNTIF($G$8:$G$694,X9)*JS9)/(2*(1-JS9))-1 -> 1.3432111e-09 | JU9: =IF(JT9>0,JS9,JQ9) -> 0.017868178 | JV9: =IF(JT9>0,JR9,JS9) -> 0.017868179 | JW9: =(JU9+JV9)/2 -> 0.017868179 | JX9: =(SUMPRODUCT(($G$8:$G$694=X9)*SQRT(JW9^2+4*(1-JW9)*$I$8:$I$694^2/Z9))-COUNTIF($G$8:$G$694,X9)*JW9)/(2*(1-JW9))-1 -> 2.2462321e-10 | JY9: =IF(JX9>0,JW9,JU9) -> 0.017868179 | JZ9: =IF(JX9>0,JV9,JW9) -> 0.017868179 | KA9: =(EY9+EZ9)/2 -> 1.0899522 | KB9: =(JY9+JZ9)/2 -> 0.017868179
A10: =Odds_Input!A10 -> 2 | B10: =Odds_Input!B10 -> TITLE | C10: =Odds_Input!C10 -> Brooklyn Nets | D10: =Odds_Input!D10 -> YES | E10: =Odds_Input!E10 -> - | F10: =Odds_Input!F10 -> 25000 | G10: =IF(OR(B10="WINS",B10="PLAYOFFS"),B10&"|"&C10&IF(B10="WINS","|"&TEXT(E10,"0.0"),""),B10) -> TITLE | H10: =IF(F10>0,1+F10/100,1+100/ABS(F10)) -> 251 | I10: =1/H10 -> 0.0039840637 | J10: =IF(LEFT(B10,6)="PLAYIN",A_playin_slots,1) -> 1 | K10: =COUNTIF($G$8:$G$694,G10) -> 30 | L10: =SUMIF($G$8:$G$694,G10,$I$8:$I$694) -> 1.2525652 | M10: =L10/J10-1 -> 0.25256519 | N10: =I10*J10/L10 -> 0.0031807237 | O10: =I10^R10 -> 0.0023027239 | P10: =IF(J10<>1,O10,IF(L10<=1,I10/L10,(SQRT(S10^2+4*(1-S10)*I10^2/L10)-S10)/(2*(1-S10)))) -> 0.0010482742 | Q10: =IF(A_devig="Multiplicative",N10,IF(A_devig="Power",O10,P10)) -> 0.0010482742 | R10: =INDEX($KA$8:$KA$96,MATCH(G10,$X$8:$X$96,0)) -> 1.0992153 | S10: =INDEX($KB$8:$KB$96,MATCH(G10,$X$8:$X$96,0)) -> 0.011051948 | X10: CONF_WEST | Y10: =IF(LEFT(X10,6)="PLAYIN",A_playin_slots,1) -> 1 | Z10: =SUMIF($G$8:$G$694,X10,$I$8:$I$694) -> 1.1953442 | AA10: 0.2 | AB10: 10 | AC10: =(AA10+AB10)/2 -> 5.1 | AD10: =SUMPRODUCT(($G$8:$G$694=X10)*($I$8:$I$694^AC10))-Y10 -> -0.97466254 | AE10: =IF(AD10>0,AC10,AA10) -> 0.2 | AF10: =IF(AD10>0,AB10,AC10) -> 5.1 | AG10: =(AE10+AF10)/2 -> 2.65 | AH10: =SUMPRODUCT(($G$8:$G$694=X10)*($I$8:$I$694^AG10))-Y10 -> -0.79248432 | AI10: =IF(AH10>0,AG10,AE10) -> 0.2 | AJ10: =IF(AH10>0,AF10,AG10) -> 2.65 | AK10: =(AI10+AJ10)/2 -> 1.425 | AL10: =SUMPRODUCT(($G$8:$G$694=X10)*($I$8:$I$694^AK10))-Y10 -> -0.32042075 | AM10: =IF(AL10>0,AK10,AI10) -> 0.2 | AN10: =IF(AL10>0,AJ10,AK10) -> 1.425 | AO10: =(AM10+AN10)/2 -> 0.8125 | AP10: =SUMPRODUCT(($G$8:$G$694=X10)*($I$8:$I$694^AO10))-Y10 -> 0.63946769 | AQ10: =IF(AP10>0,AO10,AM10) -> 0.8125 | AR10: =IF(AP10>0,AN10,AO10) -> 1.425 | AS10: =(AQ10+AR10)/2 -> 1.11875 | AT10: =SUMPRODUCT(($G$8:$G$694=X10)*($I$8:$I$694^AS10))-Y10 -> 0.0030769075 | AU10: =IF(AT10>0,AS10,AQ10) -> 1.11875 | AV10: =IF(AT10>0,AR10,AS10) -> 1.425 | AW10: =(AU10+AV10)/2 -> 1.271875 | AX10: =SUMPRODUCT(($G$8:$G$694=X10)*($I$8:$I$694^AW10))-Y10 -> -0.18221091 | AY10: =IF(AX10>0,AW10,AU10) -> 1.11875 | AZ10: =IF(AX10>0,AV10,AW10) -> 1.271875 | BA10: =(AY10+AZ10)/2 -> 1.1953125 | BB10: =SUMPRODUCT(($G$8:$G$694=X10)*($I$8:$I$694^BA10))-Y10 -> -0.096769242 | BC10: =IF(BB10>0,BA10,AY10) -> 1.11875 | BD10: =IF(BB10>0,AZ10,BA10) -> 1.1953125 | BE10: =(BC10+BD10)/2 -> 1.1570312 | BF10: =SUMPRODUCT(($G$8:$G$694=X10)*($I$8:$I$694^BE10))-Y10 -> -0.048851727 | BG10: =IF(BF10>0,BE10,BC10) -> 1.11875 | BH10: =IF(BF10>0,BD10,BE10) -> 1.1570312 | BI10: =(BG10+BH10)/2 -> 1.1378906 | BJ10: =SUMPRODUCT(($G$8:$G$694=X10)*($I$8:$I$694^BI10))-Y10 -> -0.023417535 | BK10: =IF(BJ10>0,BI10,BG10) -> 1.11875 | BL10: =IF(BJ10>0,BH10,BI10) -> 1.1378906 | BM10: =(BK10+BL10)/2 -> 1.1283203 | BN10: =SUMPRODUCT(($G$8:$G$694=X10)*($I$8:$I$694^BM10))-Y10 -> -0.010306654 | BO10: =IF(BN10>0,BM10,BK10) -> 1.11875 | BP10: =IF(BN10>0,BL10,BM10) -> 1.1283203 | BQ10: =(BO10+BP10)/2 -> 1.1235352 | BR10: =SUMPRODUCT(($G$8:$G$694=X10)*($I$8:$I$694^BQ10))-Y10 -> -0.0036494486 | BS10: =IF(BR10>0,BQ10,BO10) -> 1.11875 | BT10: =IF(BR10>0,BP10,BQ10) -> 1.1235352 | BU10: =(BS10+BT10)/2 -> 1.1211426 | BV10: =SUMPRODUCT(($G$8:$G$694=X10)*($I$8:$I$694^BU10))-Y10 -> -0.00029497662 | BW10: =IF(BV10>0,BU10,BS10) -> 1.11875 | BX10: =IF(BV10>0,BT10,BU10) -> 1.1211426 | BY10: =(BW10+BX10)/2 -> 1.1199463 | BZ10: =SUMPRODUCT(($G$8:$G$694=X10)*($I$8:$I$694^BY10))-Y10 -> 0.0013887811 | CA10: =IF(BZ10>0,BY10,BW10) -> 1.1199463 | CB10: =IF(BZ10>0,BX10,BY10) -> 1.1211426 | CC10: =(CA10+CB10)/2 -> 1.1205444 | CD10: =SUMPRODUCT(($G$8:$G$694=X10)*($I$8:$I$694^CC10))-Y10 -> 0.00054635712 | CE10: =IF(CD10>0,CC10,CA10) -> 1.1205444 | CF10: =IF(CD10>0,CB10,CC10) -> 1.1211426 | CG10: =(CE10+CF10)/2 -> 1.1208435 | CH10: =SUMPRODUCT(($G$8:$G$694=X10)*($I$8:$I$694^CG10))-Y10 -> 0.0001255541 | CI10: =IF(CH10>0,CG10,CE10) -> 1.1208435 | CJ10: =IF(CH10>0,CF10,CG10) -> 1.1211426 | CK10: =(CI10+CJ10)/2 -> 1.120993 | CL10: =SUMPRODUCT(($G$8:$G$694=X10)*($I$8:$I$694^CK10))-Y10 -> -8.4745284e-05 | CM10: =IF(CL10>0,CK10,CI10) -> 1.1208435 | CN10: =IF(CL10>0,CJ10,CK10) -> 1.120993 | CO10: =(CM10+CN10)/2 -> 1.1209183 | CP10: =SUMPRODUCT(($G$8:$G$694=X10)*($I$8:$I$694^CO10))-Y10 -> 2.0395899e-05 | CQ10: =IF(CP10>0,CO10,CM10) -> 1.1209183 | CR10: =IF(CP10>0,CN10,CO10) -> 1.120993 | CS10: =(CQ10+CR10)/2 -> 1.1209557 | CT10: =SUMPRODUCT(($G$8:$G$694=X10)*($I$8:$I$694^CS10))-Y10 -> -3.2176819e-05 | CU10: =IF(CT10>0,CS10,CQ10) -> 1.1209183 | CV10: =IF(CT10>0,CR10,CS10) -> 1.1209557 | CW10: =(CU10+CV10)/2 -> 1.120937 | CX10: =SUMPRODUCT(($G$8:$G$694=X10)*($I$8:$I$694^CW10))-Y10 -> -5.8909918e-06 | CY10: =IF(CX10>0,CW10,CU10) -> 1.1209183 | CZ10: =IF(CX10>0,CV10,CW10) -> 1.120937 | DA10: =(CY10+CZ10)/2 -> 1.1209276 | DB10: =SUMPRODUCT(($G$8:$G$694=X10)*($I$8:$I$694^DA10))-Y10 -> 7.2523207e-06 | DC10: =IF(DB10>0,DA10,CY10) -> 1.1209276 | DD10: =IF(DB10>0,CZ10,DA10) -> 1.120937 | DE10: =(DC10+DD10)/2 -> 1.1209323 | DF10: =SUMPRODUCT(($G$8:$G$694=X10)*($I$8:$I$694^DE10))-Y10 -> 6.8063123e-07 | DG10: =IF(DF10>0,DE10,DC10) -> 1.1209323 | DH10: =IF(DF10>0,DD10,DE10) -> 1.120937 | DI10: =(DG10+DH10)/2 -> 1.1209346 | DJ10: =SUMPRODUCT(($G$8:$G$694=X10)*($I$8:$I$694^DI10))-Y10 -> -2.6051886e-06 | DK10: =IF(DJ10>0,DI10,DG10) -> 1.1209323 | DL10: =IF(DJ10>0,DH10,DI10) -> 1.1209346 | DM10: =(DK10+DL10)/2 -> 1.1209335 | DN10: =SUMPRODUCT(($G$8:$G$694=X10)*($I$8:$I$694^DM10))-Y10 -> -9.6228075e-07 | DO10: =IF(DN10>0,DM10,DK10) -> 1.1209323 | DP10: =IF(DN10>0,DL10,DM10) -> 1.1209335 | DQ10: =(DO10+DP10)/2 -> 1.1209329 | DR10: =SUMPRODUCT(($G$8:$G$694=X10)*($I$8:$I$694^DQ10))-Y10 -> -1.4082528e-07 | DS10: =IF(DR10>0,DQ10,DO10) -> 1.1209323 | DT10: =IF(DR10>0,DP10,DQ10) -> 1.1209329 | DU10: =(DS10+DT10)/2 -> 1.1209326 | DV10: =SUMPRODUCT(($G$8:$G$694=X10)*($I$8:$I$694^DU10))-Y10 -> 2.6990285e-07 | DW10: =IF(DV10>0,DU10,DS10) -> 1.1209326 | DX10: =IF(DV10>0,DT10,DU10) -> 1.1209329 | DY10: =(DW10+DX10)/2 -> 1.1209327 | DZ10: =SUMPRODUCT(($G$8:$G$694=X10)*($I$8:$I$694^DY10))-Y10 -> 6.4538755e-08 | EA10: =IF(DZ10>0,DY10,DW10) -> 1.1209327 | EB10: =IF(DZ10>0,DX10,DY10) -> 1.1209329 | EC10: =(EA10+EB10)/2 -> 1.1209328 | ED10: =SUMPRODUCT(($G$8:$G$694=X10)*($I$8:$I$694^EC10))-Y10 -> -3.8143269e-08 | EE10: =IF(ED10>0,EC10,EA10) -> 1.1209327 | EF10: =IF(ED10>0,EB10,EC10) -> 1.1209328 | EG10: =(EE10+EF10)/2 -> 1.1209328 | EH10: =SUMPRODUCT(($G$8:$G$694=X10)*($I$8:$I$694^EG10))-Y10 -> 1.3197741e-08 | EI10: =IF(EH10>0,EG10,EE10) -> 1.1209328 | EJ10: =IF(EH10>0,EF10,EG10) -> 1.1209328 | EK10: =(EI10+EJ10)/2 -> 1.1209328 | EL10: =SUMPRODUCT(($G$8:$G$694=X10)*($I$8:$I$694^EK10))-Y10 -> -1.2472765e-08 | EM10: =IF(EL10>0,EK10,EI10) -> 1.1209328 | EN10: =IF(EL10>0,EJ10,EK10) -> 1.1209328 | EO10: =(EM10+EN10)/2 -> 1.1209328 | EP10: =SUMPRODUCT(($G$8:$G$694=X10)*($I$8:$I$694^EO10))-Y10 -> 3.6248826e-10 | EQ10: =IF(EP10>0,EO10,EM10) -> 1.1209328 | ER10: =IF(EP10>0,EN10,EO10) -> 1.1209328 | ES10: =(EQ10+ER10)/2 -> 1.1209328 | ET10: =SUMPRODUCT(($G$8:$G$694=X10)*($I$8:$I$694^ES10))-Y10 -> -6.0551383e-09 | EU10: =IF(ET10>0,ES10,EQ10) -> 1.1209328 | EV10: =IF(ET10>0,ER10,ES10) -> 1.1209328 | EW10: =(EU10+EV10)/2 -> 1.1209328 | EX10: =SUMPRODUCT(($G$8:$G$694=X10)*($I$8:$I$694^EW10))-Y10 -> -2.846325e-09 | EY10: =IF(EX10>0,EW10,EU10) -> 1.1209328 | EZ10: =IF(EX10>0,EV10,EW10) -> 1.1209328 | FA10: 1e-06 | FB10: 0.9999 | FC10: =(FA10+FB10)/2 -> 0.4999505 | FD10: =(SUMPRODUCT(($G$8:$G$694=X10)*SQRT(FC10^2+4*(1-FC10)*$I$8:$I$694^2/Z10))-COUNTIF($G$8:$G$694,X10)*FC10)/(2*(1-FC10))-1 -> -0.4899148 | FE10: =IF(FD10>0,FC10,FA10) -> 1e-06 | FF10: =IF(FD10>0,FB10,FC10) -> 0.4999505 | FG10: =(FE10+FF10)/2 -> 0.24997575 | FH10: =(SUMPRODUCT(($G$8:$G$694=X10)*SQRT(FG10^2+4*(1-FG10)*$I$8:$I$694^2/Z10))-COUNTIF($G$8:$G$694,X10)*FG10)/(2*(1-FG10))-1 -> -0.3254379 | FI10: =IF(FH10>0,FG10,FE10) -> 1e-06 | FJ10: =IF(FH10>0,FF10,FG10) -> 0.24997575 | FK10: =(FI10+FJ10)/2 -> 0.12498837 | FL10: =(SUMPRODUCT(($G$8:$G$694=X10)*SQRT(FK10^2+4*(1-FK10)*$I$8:$I$694^2/Z10))-COUNTIF($G$8:$G$694,X10)*FK10)/(2*(1-FK10))-1 -> -0.20435596 | FM10: =IF(FL10>0,FK10,FI10) -> 1e-06 | FN10: =IF(FL10>0,FJ10,FK10) -> 0.12498837 | FO10: =(FM10+FN10)/2 -> 0.062494687 | FP10: =(SUMPRODUCT(($G$8:$G$694=X10)*SQRT(FO10^2+4*(1-FO10)*$I$8:$I$694^2/Z10))-COUNTIF($G$8:$G$694,X10)*FO10)/(2*(1-FO10))-1 -> -0.10855846 | FQ10: =IF(FP10>0,FO10,FM10) -> 1e-06 | FR10: =IF(FP10>0,FN10,FO10) -> 0.062494687 | FS10: =(FQ10+FR10)/2 -> 0.031247844 | FT10: =(SUMPRODUCT(($G$8:$G$694=X10)*SQRT(FS10^2+4*(1-FS10)*$I$8:$I$694^2/Z10))-COUNTIF($G$8:$G$694,X10)*FS10)/(2*(1-FS10))-1 -> -0.03545759 | FU10: =IF(FT10>0,FS10,FQ10) -> 1e-06 | FV10: =IF(FT10>0,FR10,FS10) -> 0.031247844 | FW10: =(FU10+FV10)/2 -> 0.015624422 | FX10: =(SUMPRODUCT(($G$8:$G$694=X10)*SQRT(FW10^2+4*(1-FW10)*$I$8:$I$694^2/Z10))-COUNTIF($G$8:$G$694,X10)*FW10)/(2*(1-FW10))-1 -> 0.015500565 | FY10: =IF(FX10>0,FW10,FU10) -> 0.015624422 | FZ10: =IF(FX10>0,FV10,FW10) -> 0.031247844 | GA10: =(FY10+FZ10)/2 -> 0.023436133 | GB10: =(SUMPRODUCT(($G$8:$G$694=X10)*SQRT(GA10^2+4*(1-GA10)*$I$8:$I$694^2/Z10))-COUNTIF($G$8:$G$694,X10)*GA10)/(2*(1-GA10))-1 -> -0.011814836 | GC10: =IF(GB10>0,GA10,FY10) -> 0.015624422 | GD10: =IF(GB10>0,FZ10,GA10) -> 0.023436133 | GE10: =(GC10+GD10)/2 -> 0.019530277 | GF10: =(SUMPRODUCT(($G$8:$G$694=X10)*SQRT(GE10^2+4*(1-GE10)*$I$8:$I$694^2/Z10))-COUNTIF($G$8:$G$694,X10)*GE10)/(2*(1-GE10))-1 -> 0.0012927044 | GG10: =IF(GF10>0,GE10,GC10) -> 0.019530277 | GH10: =IF(GF10>0,GD10,GE10) -> 0.023436133 | GI10: =(GG10+GH10)/2 -> 0.021483205 | GJ10: =(SUMPRODUCT(($G$8:$G$694=X10)*SQRT(GI10^2+4*(1-GI10)*$I$8:$I$694^2/Z10))-COUNTIF($G$8:$G$694,X10)*GI10)/(2*(1-GI10))-1 -> -0.0053847605 | GK10: =IF(GJ10>0,GI10,GG10) -> 0.019530277 | GL10: =IF(GJ10>0,GH10,GI10) -> 0.021483205 | GM10: =(GK10+GL10)/2 -> 0.020506741 | GN10: =(SUMPRODUCT(($G$8:$G$694=X10)*SQRT(GM10^2+4*(1-GM10)*$I$8:$I$694^2/Z10))-COUNTIF($G$8:$G$694,X10)*GM10)/(2*(1-GM10))-1 -> -0.002078484 | GO10: =IF(GN10>0,GM10,GK10) -> 0.019530277 | GP10: =IF(GN10>0,GL10,GM10) -> 0.020506741 | GQ10: =(GO10+GP10)/2 -> 0.020018509 | GR10: =(SUMPRODUCT(($G$8:$G$694=X10)*SQRT(GQ10^2+4*(1-GQ10)*$I$8:$I$694^2/Z10))-COUNTIF($G$8:$G$694,X10)*GQ10)/(2*(1-GQ10))-1 -> -0.00040121052 | GS10: =IF(GR10>0,GQ10,GO10) -> 0.019530277 | GT10: =IF(GR10>0,GP10,GQ10) -> 0.020018509 | GU10: =(GS10+GT10)/2 -> 0.019774393 | GV10: =(SUMPRODUCT(($G$8:$G$694=X10)*SQRT(GU10^2+4*(1-GU10)*$I$8:$I$694^2/Z10))-COUNTIF($G$8:$G$694,X10)*GU10)/(2*(1-GU10))-1 -> 0.00044363986 | GW10: =IF(GV10>0,GU10,GS10) -> 0.019774393 | GX10: =IF(GV10>0,GT10,GU10) -> 0.020018509 | GY10: =(GW10+GX10)/2 -> 0.019896451 | GZ10: =(SUMPRODUCT(($G$8:$G$694=X10)*SQRT(GY10^2+4*(1-GY10)*$I$8:$I$694^2/Z10))-COUNTIF($G$8:$G$694,X10)*GY10)/(2*(1-GY10))-1 -> 2.0691319e-05 | HA10: =IF(GZ10>0,GY10,GW10) -> 0.019896451 | HB10: =IF(GZ10>0,GX10,GY10) -> 0.020018509 | HC10: =(HA10+HB10)/2 -> 0.01995748 | HD10: =(SUMPRODUCT(($G$8:$G$694=X10)*SQRT(HC10^2+4*(1-HC10)*$I$8:$I$694^2/Z10))-COUNTIF($G$8:$G$694,X10)*HC10)/(2*(1-HC10))-1 -> -0.00019039002 | HE10: =IF(HD10>0,HC10,HA10) -> 0.019896451 | HF10: =IF(HD10>0,HB10,HC10) -> 0.01995748 | HG10: =(HE10+HF10)/2 -> 0.019926966 | HH10: =(SUMPRODUCT(($G$8:$G$694=X10)*SQRT(HG10^2+4*(1-HG10)*$I$8:$I$694^2/Z10))-COUNTIF($G$8:$G$694,X10)*HG10)/(2*(1-HG10))-1 -> -8.4882005e-05 | HI10: =IF(HH10>0,HG10,HE10) -> 0.019896451 | HJ10: =IF(HH10>0,HF10,HG10) -> 0.019926966 | HK10: =(HI10+HJ10)/2 -> 0.019911709 | HL10: =(SUMPRODUCT(($G$8:$G$694=X10)*SQRT(HK10^2+4*(1-HK10)*$I$8:$I$694^2/Z10))-COUNTIF($G$8:$G$694,X10)*HK10)/(2*(1-HK10))-1 -> -3.2103514e-05 | HM10: =IF(HL10>0,HK10,HI10) -> 0.019896451 | HN10: =IF(HL10>0,HJ10,HK10) -> 0.019911709 | HO10: =(HM10+HN10)/2 -> 0.01990408 | HP10: =(SUMPRODUCT(($G$8:$G$694=X10)*SQRT(HO10^2+4*(1-HO10)*$I$8:$I$694^2/Z10))-COUNTIF($G$8:$G$694,X10)*HO10)/(2*(1-HO10))-1 -> -5.7081413e-06 | HQ10: =IF(HP10>0,HO10,HM10) -> 0.019896451 | HR10: =IF(HP10>0,HN10,HO10) -> 0.01990408 | HS10: =(HQ10+HR10)/2 -> 0.019900266 | HT10: =(SUMPRODUCT(($G$8:$G$694=X10)*SQRT(HS10^2+4*(1-HS10)*$I$8:$I$694^2/Z10))-COUNTIF($G$8:$G$694,X10)*HS10)/(2*(1-HS10))-1 -> 7.4910777e-06 | HU10: =IF(HT10>0,HS10,HQ10) -> 0.019900266 | HV10: =IF(HT10>0,HR10,HS10) -> 0.01990408 | HW10: =(HU10+HV10)/2 -> 0.019902173 | HX10: =(SUMPRODUCT(($G$8:$G$694=X10)*SQRT(HW10^2+4*(1-HW10)*$I$8:$I$694^2/Z10))-COUNTIF($G$8:$G$694,X10)*HW10)/(2*(1-HW10))-1 -> 8.9134048e-07 | HY10: =IF(HX10>0,HW10,HU10) -> 0.019902173 | HZ10: =IF(HX10>0,HV10,HW10) -> 0.01990408 | IA10: =(HY10+HZ10)/2 -> 0.019903126 | IB10: =(SUMPRODUCT(($G$8:$G$694=X10)*SQRT(IA10^2+4*(1-IA10)*$I$8:$I$694^2/Z10))-COUNTIF($G$8:$G$694,X10)*IA10)/(2*(1-IA10))-1 -> -2.4084323e-06 | IC10: =IF(IB10>0,IA10,HY10) -> 0.019902173 | ID10: =IF(IB10>0,HZ10,IA10) -> 0.019903126 | IE10: =(IC10+ID10)/2 -> 0.01990265 | IF10: =(SUMPRODUCT(($G$8:$G$694=X10)*SQRT(IE10^2+4*(1-IE10)*$I$8:$I$694^2/Z10))-COUNTIF($G$8:$G$694,X10)*IE10)/(2*(1-IE10))-1 -> -7.5855391e-07 | IG10: =IF(IF10>0,IE10,IC10) -> 0.019902173 | IH10: =IF(IF10>0,ID10,IE10) -> 0.01990265 | II10: =(IG10+IH10)/2 -> 0.019902411 | IJ10: =(SUMPRODUCT(($G$8:$G$694=X10)*SQRT(II10^2+4*(1-II10)*$I$8:$I$694^2/Z10))-COUNTIF($G$8:$G$694,X10)*II10)/(2*(1-II10))-1 -> 6.6391292e-08 | IK10: =IF(IJ10>0,II10,IG10) -> 0.019902411 | IL10: =IF(IJ10>0,IH10,II10) -> 0.01990265 | IM10: =(IK10+IL10)/2 -> 0.01990253 | IN10: =(SUMPRODUCT(($G$8:$G$694=X10)*SQRT(IM10^2+4*(1-IM10)*$I$8:$I$694^2/Z10))-COUNTIF($G$8:$G$694,X10)*IM10)/(2*(1-IM10))-1 -> -3.4608181e-07 | IO10: =IF(IN10>0,IM10,IK10) -> 0.019902411 | IP10: =IF(IN10>0,IL10,IM10) -> 0.01990253 | IQ10: =(IO10+IP10)/2 -> 0.019902471 | IR10: =(SUMPRODUCT(($G$8:$G$694=X10)*SQRT(IQ10^2+4*(1-IQ10)*$I$8:$I$694^2/Z10))-COUNTIF($G$8:$G$694,X10)*IQ10)/(2*(1-IQ10))-1 -> -1.3984538e-07 | IS10: =IF(IR10>0,IQ10,IO10) -> 0.019902411 | IT10: =IF(IR10>0,IP10,IQ10) -> 0.019902471 | IU10: =(IS10+IT10)/2 -> 0.019902441 | IV10: =(SUMPRODUCT(($G$8:$G$694=X10)*SQRT(IU10^2+4*(1-IU10)*$I$8:$I$694^2/Z10))-COUNTIF($G$8:$G$694,X10)*IU10)/(2*(1-IU10))-1 -> -3.6727077e-08 | IW10: =IF(IV10>0,IU10,IS10) -> 0.019902411 | IX10: =IF(IV10>0,IT10,IU10) -> 0.019902441 | IY10: =(IW10+IX10)/2 -> 0.019902426 | IZ10: =(SUMPRODUCT(($G$8:$G$694=X10)*SQRT(IY10^2+4*(1-IY10)*$I$8:$I$694^2/Z10))-COUNTIF($G$8:$G$694,X10)*IY10)/(2*(1-IY10))-1 -> 1.48321e-08 | JA10: =IF(IZ10>0,IY10,IW10) -> 0.019902426 | JB10: =IF(IZ10>0,IX10,IY10) -> 0.019902441 | JC10: =(JA10+JB10)/2 -> 0.019902434 | JD10: =(SUMPRODUCT(($G$8:$G$694=X10)*SQRT(JC10^2+4*(1-JC10)*$I$8:$I$694^2/Z10))-COUNTIF($G$8:$G$694,X10)*JC10)/(2*(1-JC10))-1 -> -1.094749e-08 | JE10: =IF(JD10>0,JC10,JA10) -> 0.019902426 | JF10: =IF(JD10>0,JB10,JC10) -> 0.019902434 | JG10: =(JE10+JF10)/2 -> 0.01990243 | JH10: =(SUMPRODUCT(($G$8:$G$694=X10)*SQRT(JG10^2+4*(1-JG10)*$I$8:$I$694^2/Z10))-COUNTIF($G$8:$G$694,X10)*JG10)/(2*(1-JG10))-1 -> 1.9423041e-09 | JI10: =IF(JH10>0,JG10,JE10) -> 0.01990243 | JJ10: =IF(JH10>0,JF10,JG10) -> 0.019902434 | JK10: =(JI10+JJ10)/2 -> 0.019902432 | JL10: =(SUMPRODUCT(($G$8:$G$694=X10)*SQRT(JK10^2+4*(1-JK10)*$I$8:$I$694^2/Z10))-COUNTIF($G$8:$G$694,X10)*JK10)/(2*(1-JK10))-1 -> -4.5025933e-09 | JM10: =IF(JL10>0,JK10,JI10) -> 0.01990243 | JN10: =IF(JL10>0,JJ10,JK10) -> 0.019902432 | JO10: =(JM10+JN10)/2 -> 0.019902431 | JP10: =(SUMPRODUCT(($G$8:$G$694=X10)*SQRT(JO10^2+4*(1-JO10)*$I$8:$I$694^2/Z10))-COUNTIF($G$8:$G$694,X10)*JO10)/(2*(1-JO10))-1 -> -1.2801445e-09 | JQ10: =IF(JP10>0,JO10,JM10) -> 0.01990243 | JR10: =IF(JP10>0,JN10,JO10) -> 0.019902431 | JS10: =(JQ10+JR10)/2 -> 0.01990243 | JT10: =(SUMPRODUCT(($G$8:$G$694=X10)*SQRT(JS10^2+4*(1-JS10)*$I$8:$I$694^2/Z10))-COUNTIF($G$8:$G$694,X10)*JS10)/(2*(1-JS10))-1 -> 3.3107983e-10 | JU10: =IF(JT10>0,JS10,JQ10) -> 0.01990243 | JV10: =IF(JT10>0,JR10,JS10) -> 0.019902431 | JW10: =(JU10+JV10)/2 -> 0.01990243 | JX10: =(SUMPRODUCT(($G$8:$G$694=X10)*SQRT(JW10^2+4*(1-JW10)*$I$8:$I$694^2/Z10))-COUNTIF($G$8:$G$694,X10)*JW10)/(2*(1-JW10))-1 -> -4.7453241e-10 | JY10: =IF(JX10>0,JW10,JU10) -> 0.01990243 | JZ10: =IF(JX10>0,JV10,JW10) -> 0.01990243 | KA10: =(EY10+EZ10)/2 -> 1.1209328 | KB10: =(JY10+JZ10)/2 -> 0.01990243
A11: =Odds_Input!A11 -> 3 | B11: =Odds_Input!B11 -> TITLE | C11: =Odds_Input!C11 -> Charlotte Hornets | D11: =Odds_Input!D11 -> YES | E11: =Odds_Input!E11 -> - | F11: =Odds_Input!F11 -> 8600 | G11: =IF(OR(B11="WINS",B11="PLAYOFFS"),B11&"|"&C11&IF(B11="WINS","|"&TEXT(E11,"0.0"),""),B11) -> TITLE | H11: =IF(F11>0,1+F11/100,1+100/ABS(F11)) -> 87 | I11: =1/H11 -> 0.011494253 | J11: =IF(LEFT(B11,6)="PLAYIN",A_playin_slots,1) -> 1 | K11: =COUNTIF($G$8:$G$694,G11) -> 30 | L11: =SUMIF($G$8:$G$694,G11,$I$8:$I$694) -> 1.2525652 | M11: =L11/J11-1 -> 0.25256519 | N11: =I11*J11/L11 -> 0.0091765706 | O11: =I11^R11 -> 0.0073799039 | P11: =IF(J11<>1,O11,IF(L11<=1,I11/L11,(SQRT(S11^2+4*(1-S11)*I11^2/L11)-S11)/(2*(1-S11)))) -> 0.0061544724 | Q11: =IF(A_devig="Multiplicative",N11,IF(A_devig="Power",O11,P11)) -> 0.0061544724 | R11: =INDEX($KA$8:$KA$96,MATCH(G11,$X$8:$X$96,0)) -> 1.0992153 | S11: =INDEX($KB$8:$KB$96,MATCH(G11,$X$8:$X$96,0)) -> 0.011051948 | X11: DIV_ATLANTIC | Y11: =IF(LEFT(X11,6)="PLAYIN",A_playin_slots,1) -> 1 | Z11: =SUMIF($G$8:$G$694,X11,$I$8:$I$694) -> 1.1462829 | AA11: 0.2 | AB11: 10 | AC11: =(AA11+AB11)/2 -> 5.1 | AD11: =SUMPRODUCT(($G$8:$G$694=X11)*($I$8:$I$694^AC11))-Y11 -> -0.9879552 | AE11: =IF(AD11>0,AC11,AA11) -> 0.2 | AF11: =IF(AD11>0,AB11,AC11) -> 5.1 | AG11: =(AE11+AF11)/2 -> 2.65 | AH11: =SUMPRODUCT(($G$8:$G$694=X11)*($I$8:$I$694^AG11))-Y11 -> -0.82681144 | AI11: =IF(AH11>0,AG11,AE11) -> 0.2 | AJ11: =IF(AH11>0,AF11,AG11) -> 2.65 | AK11: =(AI11+AJ11)/2 -> 1.425 | AL11: =SUMPRODUCT(($G$8:$G$694=X11)*($I$8:$I$694^AK11))-Y11 -> -0.30736844 | AM11: =IF(AL11>0,AK11,AI11) -> 0.2 | AN11: =IF(AL11>0,AJ11,AK11) -> 1.425 | AO11: =(AM11+AN11)/2 -> 0.8125 | AP11: =SUMPRODUCT(($G$8:$G$694=X11)*($I$8:$I$694^AO11))-Y11 -> 0.44313063 | AQ11: =IF(AP11>0,AO11,AM11) -> 0.8125 | AR11: =IF(AP11>0,AN11,AO11) -> 1.425 | AS11: =(AQ11+AR11)/2 -> 1.11875 | AT11: =SUMPRODUCT(($G$8:$G$694=X11)*($I$8:$I$694^AS11))-Y11 -> -0.0062712776 | AU11: =IF(AT11>0,AS11,AQ11) -> 0.8125 | AV11: =IF(AT11>0,AR11,AS11) -> 1.11875 | AW11: =(AU11+AV11)/2 -> 0.965625 | AX11: =SUMPRODUCT(($G$8:$G$694=X11)*($I$8:$I$694^AW11))-Y11 -> 0.19512969 | AY11: =IF(AX11>0,AW11,AU11) -> 0.965625 | AZ11: =IF(AX11>0,AV11,AW11) -> 1.11875 | BA11: =(AY11+AZ11)/2 -> 1.0421875 | BB11: =SUMPRODUCT(($G$8:$G$694=X11)*($I$8:$I$694^BA11))-Y11 -> 0.089328253 | BC11: =IF(BB11>0,BA11,AY11) -> 1.0421875 | BD11: =IF(BB11>0,AZ11,BA11) -> 1.11875 | BE11: =(BC11+BD11)/2 -> 1.0804687 | BF11: =SUMPRODUCT(($G$8:$G$694=X11)*($I$8:$I$694^BE11))-Y11 -> 0.040329901 | BG11: =IF(BF11>0,BE11,BC11) -> 1.0804687 | BH11: =IF(BF11>0,BD11,BE11) -> 1.11875 | BI11: =(BG11+BH11)/2 -> 1.0996094 | BJ11: =SUMPRODUCT(($G$8:$G$694=X11)*($I$8:$I$694^BI11))-Y11 -> 0.016738547 | BK11: =IF(BJ11>0,BI11,BG11) -> 1.0996094 | BL11: =IF(BJ11>0,BH11,BI11) -> 1.11875 | BM11: =(BK11+BL11)/2 -> 1.1091797 | BN11: =SUMPRODUCT(($G$8:$G$694=X11)*($I$8:$I$694^BM11))-Y11 -> 0.0051620141 | BO11: =IF(BN11>0,BM11,BK11) -> 1.1091797 | BP11: =IF(BN11>0,BL11,BM11) -> 1.11875 | BQ11: =(BO11+BP11)/2 -> 1.1139648 | BR11: =SUMPRODUCT(($G$8:$G$694=X11)*($I$8:$I$694^BQ11))-Y11 -> -0.0005724054 | BS11: =IF(BR11>0,BQ11,BO11) -> 1.1091797 | BT11: =IF(BR11>0,BP11,BQ11) -> 1.1139648 | BU11: =(BS11+BT11)/2 -> 1.1115723 | BV11: =SUMPRODUCT(($G$8:$G$694=X11)*($I$8:$I$694^BU11))-Y11 -> 0.0022903446 | BW11: =IF(BV11>0,BU11,BS11) -> 1.1115723 | BX11: =IF(BV11>0,BT11,BU11) -> 1.1139648 | BY11: =(BW11+BX11)/2 -> 1.1127686 | BZ11: =SUMPRODUCT(($G$8:$G$694=X11)*($I$8:$I$694^BY11))-Y11 -> 0.00085785672 | CA11: =IF(BZ11>0,BY11,BW11) -> 1.1127686 | CB11: =IF(BZ11>0,BX11,BY11) -> 1.1139648 | CC11: =(CA11+CB11)/2 -> 1.1133667 | CD11: =SUMPRODUCT(($G$8:$G$694=X11)*($I$8:$I$694^CC11))-Y11 -> 0.0001424477 | CE11: =IF(CD11>0,CC11,CA11) -> 1.1133667 | CF11: =IF(CD11>0,CB11,CC11) -> 1.1139648 | CG11: =(CE11+CF11)/2 -> 1.1136658 | CH11: =SUMPRODUCT(($G$8:$G$694=X11)*($I$8:$I$694^CG11))-Y11 -> -0.00021504831 | CI11: =IF(CH11>0,CG11,CE11) -> 1.1133667 | CJ11: =IF(CH11>0,CF11,CG11) -> 1.1136658 | CK11: =(CI11+CJ11)/2 -> 1.1135162 | CL11: =SUMPRODUCT(($G$8:$G$694=X11)*($I$8:$I$694^CK11))-Y11 -> -3.6317676e-05 | CM11: =IF(CL11>0,CK11,CI11) -> 1.1133667 | CN11: =IF(CL11>0,CJ11,CK11) -> 1.1135162 | CO11: =(CM11+CN11)/2 -> 1.1134415 | CP11: =SUMPRODUCT(($G$8:$G$694=X11)*($I$8:$I$694^CO11))-Y11 -> 5.3060667e-05 | CQ11: =IF(CP11>0,CO11,CM11) -> 1.1134415 | CR11: =IF(CP11>0,CN11,CO11) -> 1.1135162 | CS11: =(CQ11+CR11)/2 -> 1.1134789 | CT11: =SUMPRODUCT(($G$8:$G$694=X11)*($I$8:$I$694^CS11))-Y11 -> 8.3704101e-06 | CU11: =IF(CT11>0,CS11,CQ11) -> 1.1134789 | CV11: =IF(CT11>0,CR11,CS11) -> 1.1135162 | CW11: =(CU11+CV11)/2 -> 1.1134975 | CX11: =SUMPRODUCT(($G$8:$G$694=X11)*($I$8:$I$694^CW11))-Y11 -> -1.3973904e-05 | CY11: =IF(CX11>0,CW11,CU11) -> 1.1134789 | CZ11: =IF(CX11>0,CV11,CW11) -> 1.1134975 | DA11: =(CY11+CZ11)/2 -> 1.1134882 | DB11: =SUMPRODUCT(($G$8:$G$694=X11)*($I$8:$I$694^DA11))-Y11 -> -2.801815e-06 | DC11: =IF(DB11>0,DA11,CY11) -> 1.1134789 | DD11: =IF(DB11>0,CZ11,DA11) -> 1.1134882 | DE11: =(DC11+DD11)/2 -> 1.1134835 | DF11: =SUMPRODUCT(($G$8:$G$694=X11)*($I$8:$I$694^DE11))-Y11 -> 2.7842806e-06 | DG11: =IF(DF11>0,DE11,DC11) -> 1.1134835 | DH11: =IF(DF11>0,DD11,DE11) -> 1.1134882 | DI11: =(DG11+DH11)/2 -> 1.1134859 | DJ11: =SUMPRODUCT(($G$8:$G$694=X11)*($I$8:$I$694^DI11))-Y11 -> -8.7714386e-09 | DK11: =IF(DJ11>0,DI11,DG11) -> 1.1134835 | DL11: =IF(DJ11>0,DH11,DI11) -> 1.1134859 | DM11: =(DK11+DL11)/2 -> 1.1134847 | DN11: =SUMPRODUCT(($G$8:$G$694=X11)*($I$8:$I$694^DM11))-Y11 -> 1.3877535e-06 | DO11: =IF(DN11>0,DM11,DK11) -> 1.1134847 | DP11: =IF(DN11>0,DL11,DM11) -> 1.1134859 | DQ11: =(DO11+DP11)/2 -> 1.1134853 | DR11: =SUMPRODUCT(($G$8:$G$694=X11)*($I$8:$I$694^DQ11))-Y11 -> 6.8949077e-07 | DS11: =IF(DR11>0,DQ11,DO11) -> 1.1134853 | DT11: =IF(DR11>0,DP11,DQ11) -> 1.1134859 | DU11: =(DS11+DT11)/2 -> 1.1134856 | DV11: =SUMPRODUCT(($G$8:$G$694=X11)*($I$8:$I$694^DU11))-Y11 -> 3.403596e-07 | DW11: =IF(DV11>0,DU11,DS11) -> 1.1134856 | DX11: =IF(DV11>0,DT11,DU11) -> 1.1134859 | DY11: =(DW11+DX11)/2 -> 1.1134857 | DZ11: =SUMPRODUCT(($G$8:$G$694=X11)*($I$8:$I$694^DY11))-Y11 -> 1.6579406e-07 | EA11: =IF(DZ11>0,DY11,DW11) -> 1.1134857 | EB11: =IF(DZ11>0,DX11,DY11) -> 1.1134859 | EC11: =(EA11+EB11)/2 -> 1.1134858 | ED11: =SUMPRODUCT(($G$8:$G$694=X11)*($I$8:$I$694^EC11))-Y11 -> 7.8511309e-08 | EE11: =IF(ED11>0,EC11,EA11) -> 1.1134858 | EF11: =IF(ED11>0,EB11,EC11) -> 1.1134859 | EG11: =(EE11+EF11)/2 -> 1.1134858 | EH11: =SUMPRODUCT(($G$8:$G$694=X11)*($I$8:$I$694^EG11))-Y11 -> 3.4869934e-08 | EI11: =IF(EH11>0,EG11,EE11) -> 1.1134858 | EJ11: =IF(EH11>0,EF11,EG11) -> 1.1134859 | EK11: =(EI11+EJ11)/2 -> 1.1134858 | EL11: =SUMPRODUCT(($G$8:$G$694=X11)*($I$8:$I$694^EK11))-Y11 -> 1.3049248e-08 | EM11: =IF(EL11>0,EK11,EI11) -> 1.1134858 | EN11: =IF(EL11>0,EJ11,EK11) -> 1.1134859 | EO11: =(EM11+EN11)/2 -> 1.1134859 | EP11: =SUMPRODUCT(($G$8:$G$694=X11)*($I$8:$I$694^EO11))-Y11 -> 2.1389046e-09 | EQ11: =IF(EP11>0,EO11,EM11) -> 1.1134859 | ER11: =IF(EP11>0,EN11,EO11) -> 1.1134859 | ES11: =(EQ11+ER11)/2 -> 1.1134859 | ET11: =SUMPRODUCT(($G$8:$G$694=X11)*($I$8:$I$694^ES11))-Y11 -> -3.3162669e-09 | EU11: =IF(ET11>0,ES11,EQ11) -> 1.1134859 | EV11: =IF(ET11>0,ER11,ES11) -> 1.1134859 | EW11: =(EU11+EV11)/2 -> 1.1134859 | EX11: =SUMPRODUCT(($G$8:$G$694=X11)*($I$8:$I$694^EW11))-Y11 -> -5.8868133e-10 | EY11: =IF(EX11>0,EW11,EU11) -> 1.1134859 | EZ11: =IF(EX11>0,EV11,EW11) -> 1.1134859 | FA11: 1e-06 | FB11: 0.9999 | FC11: =(FA11+FB11)/2 -> 0.4999505 | FD11: =(SUMPRODUCT(($G$8:$G$694=X11)*SQRT(FC11^2+4*(1-FC11)*$I$8:$I$694^2/Z11))-COUNTIF($G$8:$G$694,X11)*FC11)/(2*(1-FC11))-1 -> -0.4624455 | FE11: =IF(FD11>0,FC11,FA11) -> 1e-06 | FF11: =IF(FD11>0,FB11,FC11) -> 0.4999505 | FG11: =(FE11+FF11)/2 -> 0.24997575 | FH11: =(SUMPRODUCT(($G$8:$G$694=X11)*SQRT(FG11^2+4*(1-FG11)*$I$8:$I$694^2/Z11))-COUNTIF($G$8:$G$694,X11)*FG11)/(2*(1-FG11))-1 -> -0.2486148 | FI11: =IF(FH11>0,FG11,FE11) -> 1e-06 | FJ11: =IF(FH11>0,FF11,FG11) -> 0.24997575 | FK11: =(FI11+FJ11)/2 -> 0.12498837 | FL11: =(SUMPRODUCT(($G$8:$G$694=X11)*SQRT(FK11^2+4*(1-FK11)*$I$8:$I$694^2/Z11))-COUNTIF($G$8:$G$694,X11)*FK11)/(2*(1-FK11))-1 -> -0.10443824 | FM11: =IF(FL11>0,FK11,FI11) -> 1e-06 | FN11: =IF(FL11>0,FJ11,FK11) -> 0.12498837 | FO11: =(FM11+FN11)/2 -> 0.062494687 | FP11: =(SUMPRODUCT(($G$8:$G$694=X11)*SQRT(FO11^2+4*(1-FO11)*$I$8:$I$694^2/Z11))-COUNTIF($G$8:$G$694,X11)*FO11)/(2*(1-FO11))-1 -> -0.021800058 | FQ11: =IF(FP11>0,FO11,FM11) -> 1e-06 | FR11: =IF(FP11>0,FN11,FO11) -> 0.062494687 | FS11: =(FQ11+FR11)/2 -> 0.031247844 | FT11: =(SUMPRODUCT(($G$8:$G$694=X11)*SQRT(FS11^2+4*(1-FS11)*$I$8:$I$694^2/Z11))-COUNTIF($G$8:$G$694,X11)*FS11)/(2*(1-FS11))-1 -> 0.022170738 | FU11: =IF(FT11>0,FS11,FQ11) -> 0.031247844 | FV11: =IF(FT11>0,FR11,FS11) -> 0.062494687 | FW11: =(FU11+FV11)/2 -> 0.046871266 | FX11: =(SUMPRODUCT(($G$8:$G$694=X11)*SQRT(FW11^2+4*(1-FW11)*$I$8:$I$694^2/Z11))-COUNTIF($G$8:$G$694,X11)*FW11)/(2*(1-FW11))-1 -> -4.3197327e-05 | FY11: =IF(FX11>0,FW11,FU11) -> 0.031247844 | FZ11: =IF(FX11>0,FV11,FW11) -> 0.046871266 | GA11: =(FY11+FZ11)/2 -> 0.039059555 | GB11: =(SUMPRODUCT(($G$8:$G$694=X11)*SQRT(GA11^2+4*(1-GA11)*$I$8:$I$694^2/Z11))-COUNTIF($G$8:$G$694,X11)*GA11)/(2*(1-GA11))-1 -> 0.011003026 | GC11: =IF(GB11>0,GA11,FY11) -> 0.039059555 | GD11: =IF(GB11>0,FZ11,GA11) -> 0.046871266 | GE11: =(GC11+GD11)/2 -> 0.04296541 | GF11: =(SUMPRODUCT(($G$8:$G$694=X11)*SQRT(GE11^2+4*(1-GE11)*$I$8:$I$694^2/Z11))-COUNTIF($G$8:$G$694,X11)*GE11)/(2*(1-GE11))-1 -> 0.0054654476 | GG11: =IF(GF11>0,GE11,GC11) -> 0.04296541 | GH11: =IF(GF11>0,GD11,GE11) -> 0.046871266 | GI11: =(GG11+GH11)/2 -> 0.044918338 | GJ11: =(SUMPRODUCT(($G$8:$G$694=X11)*SQRT(GI11^2+4*(1-GI11)*$I$8:$I$694^2/Z11))-COUNTIF($G$8:$G$694,X11)*GI11)/(2*(1-GI11))-1 -> 0.0027075657 | GK11: =IF(GJ11>0,GI11,GG11) -> 0.044918338 | GL11: =IF(GJ11>0,GH11,GI11) -> 0.046871266 | GM11: =(GK11+GL11)/2 -> 0.045894802 | GN11: =(SUMPRODUCT(($G$8:$G$694=X11)*SQRT(GM11^2+4*(1-GM11)*$I$8:$I$694^2/Z11))-COUNTIF($G$8:$G$694,X11)*GM11)/(2*(1-GM11))-1 -> 0.0013313001 | GO11: =IF(GN11>0,GM11,GK11) -> 0.045894802 | GP11: =IF(GN11>0,GL11,GM11) -> 0.046871266 | GQ11: =(GO11+GP11)/2 -> 0.046383034 | GR11: =(SUMPRODUCT(($G$8:$G$694=X11)*SQRT(GQ11^2+4*(1-GQ11)*$I$8:$I$694^2/Z11))-COUNTIF($G$8:$G$694,X11)*GQ11)/(2*(1-GQ11))-1 -> 0.000643831 | GS11: =IF(GR11>0,GQ11,GO11) -> 0.046383034 | GT11: =IF(GR11>0,GP11,GQ11) -> 0.046871266 | GU11: =(GS11+GT11)/2 -> 0.04662715 | GV11: =(SUMPRODUCT(($G$8:$G$694=X11)*SQRT(GU11^2+4*(1-GU11)*$I$8:$I$694^2/Z11))-COUNTIF($G$8:$G$694,X11)*GU11)/(2*(1-GU11))-1 -> 0.00030026182 | GW11: =IF(GV11>0,GU11,GS11) -> 0.04662715 | GX11: =IF(GV11>0,GT11,GU11) -> 0.046871266 | GY11: =(GW11+GX11)/2 -> 0.046749208 | GZ11: =(SUMPRODUCT(($G$8:$G$694=X11)*SQRT(GY11^2+4*(1-GY11)*$I$8:$I$694^2/Z11))-COUNTIF($G$8:$G$694,X11)*GY11)/(2*(1-GY11))-1 -> 0.0001285185 | HA11: =IF(GZ11>0,GY11,GW11) -> 0.046749208 | HB11: =IF(GZ11>0,GX11,GY11) -> 0.046871266 | HC11: =(HA11+HB11)/2 -> 0.046810237 | HD11: =(SUMPRODUCT(($G$8:$G$694=X11)*SQRT(HC11^2+4*(1-HC11)*$I$8:$I$694^2/Z11))-COUNTIF($G$8:$G$694,X11)*HC11)/(2*(1-HC11))-1 -> 4.2657151e-05 | HE11: =IF(HD11>0,HC11,HA11) -> 0.046810237 | HF11: =IF(HD11>0,HB11,HC11) -> 0.046871266 | HG11: =(HE11+HF11)/2 -> 0.046840751 | HH11: =(SUMPRODUCT(($G$8:$G$694=X11)*SQRT(HG11^2+4*(1-HG11)*$I$8:$I$694^2/Z11))-COUNTIF($G$8:$G$694,X11)*HG11)/(2*(1-HG11))-1 -> -2.7094679e-07 | HI11: =IF(HH11>0,HG11,HE11) -> 0.046810237 | HJ11: =IF(HH11>0,HF11,HG11) -> 0.046840751 | HK11: =(HI11+HJ11)/2 -> 0.046825494 | HL11: =(SUMPRODUCT(($G$8:$G$694=X11)*SQRT(HK11^2+4*(1-HK11)*$I$8:$I$694^2/Z11))-COUNTIF($G$8:$G$694,X11)*HK11)/(2*(1-HK11))-1 -> 2.1192887e-05 | HM11: =IF(HL11>0,HK11,HI11) -> 0.046825494 | HN11: =IF(HL11>0,HJ11,HK11) -> 0.046840751 | HO11: =(HM11+HN11)/2 -> 0.046833123 | HP11: =(SUMPRODUCT(($G$8:$G$694=X11)*SQRT(HO11^2+4*(1-HO11)*$I$8:$I$694^2/Z11))-COUNTIF($G$8:$G$694,X11)*HO11)/(2*(1-HO11))-1 -> 1.0460917e-05 | HQ11: =IF(HP11>0,HO11,HM11) -> 0.046833123 | HR11: =IF(HP11>0,HN11,HO11) -> 0.046840751 | HS11: =(HQ11+HR11)/2 -> 0.046836937 | HT11: =(SUMPRODUCT(($G$8:$G$694=X11)*SQRT(HS11^2+4*(1-HS11)*$I$8:$I$694^2/Z11))-COUNTIF($G$8:$G$694,X11)*HS11)/(2*(1-HS11))-1 -> 5.0949715e-06 | HU11: =IF(HT11>0,HS11,HQ11) -> 0.046836937 | HV11: =IF(HT11>0,HR11,HS11) -> 0.046840751 | HW11: =(HU11+HV11)/2 -> 0.046838844 | HX11: =(SUMPRODUCT(($G$8:$G$694=X11)*SQRT(HW11^2+4*(1-HW11)*$I$8:$I$694^2/Z11))-COUNTIF($G$8:$G$694,X11)*HW11)/(2*(1-HW11))-1 -> 2.412009e-06 | HY11: =IF(HX11>0,HW11,HU11) -> 0.046838844 | HZ11: =IF(HX11>0,HV11,HW11) -> 0.046840751 | IA11: =(HY11+HZ11)/2 -> 0.046839798 | IB11: =(SUMPRODUCT(($G$8:$G$694=X11)*SQRT(IA11^2+4*(1-IA11)*$I$8:$I$694^2/Z11))-COUNTIF($G$8:$G$694,X11)*IA11)/(2*(1-IA11))-1 -> 1.0705303e-06 | IC11: =IF(IB11>0,IA11,HY11) -> 0.046839798 | ID11: =IF(IB11>0,HZ11,IA11) -> 0.046840751 | IE11: =(IC11+ID11)/2 -> 0.046840274 | IF11: =(SUMPRODUCT(($G$8:$G$694=X11)*SQRT(IE11^2+4*(1-IE11)*$I$8:$I$694^2/Z11))-COUNTIF($G$8:$G$694,X11)*IE11)/(2*(1-IE11))-1 -> 3.9979153e-07 | IG11: =IF(IF11>0,IE11,IC11) -> 0.046840274 | IH11: =IF(IF11>0,ID11,IE11) -> 0.046840751 | II11: =(IG11+IH11)/2 -> 0.046840513 | IJ11: =(SUMPRODUCT(($G$8:$G$694=X11)*SQRT(II11^2+4*(1-II11)*$I$8:$I$694^2/Z11))-COUNTIF($G$8:$G$694,X11)*II11)/(2*(1-II11))-1 -> 6.4422321e-08 | IK11: =IF(IJ11>0,II11,IG11) -> 0.046840513 | IL11: =IF(IJ11>0,IH11,II11) -> 0.046840751 | IM11: =(IK11+IL11)/2 -> 0.046840632 | IN11: =(SUMPRODUCT(($G$8:$G$694=X11)*SQRT(IM11^2+4*(1-IM11)*$I$8:$I$694^2/Z11))-COUNTIF($G$8:$G$694,X11)*IM11)/(2*(1-IM11))-1 -> -1.0326224e-07 | IO11: =IF(IN11>0,IM11,IK11) -> 0.046840513 | IP11: =IF(IN11>0,IL11,IM11) -> 0.046840632 | IQ11: =(IO11+IP11)/2 -> 0.046840572 | IR11: =(SUMPRODUCT(($G$8:$G$694=X11)*SQRT(IQ11^2+4*(1-IQ11)*$I$8:$I$694^2/Z11))-COUNTIF($G$8:$G$694,X11)*IQ11)/(2*(1-IQ11))-1 -> -1.9419965e-08 | IS11: =IF(IR11>0,IQ11,IO11) -> 0.046840513 | IT11: =IF(IR11>0,IP11,IQ11) -> 0.046840572 | IU11: =(IS11+IT11)/2 -> 0.046840543 | IV11: =(SUMPRODUCT(($G$8:$G$694=X11)*SQRT(IU11^2+4*(1-IU11)*$I$8:$I$694^2/Z11))-COUNTIF($G$8:$G$694,X11)*IU11)/(2*(1-IU11))-1 -> 2.2501177e-08 | IW11: =IF(IV11>0,IU11,IS11) -> 0.046840543 | IX11: =IF(IV11>0,IT11,IU11) -> 0.046840572 | IY11: =(IW11+IX11)/2 -> 0.046840557 | IZ11: =(SUMPRODUCT(($G$8:$G$694=X11)*SQRT(IY11^2+4*(1-IY11)*$I$8:$I$694^2/Z11))-COUNTIF($G$8:$G$694,X11)*IY11)/(2*(1-IY11))-1 -> 1.5406059e-09 | JA11: =IF(IZ11>0,IY11,IW11) -> 0.046840557 | JB11: =IF(IZ11>0,IX11,IY11) -> 0.046840572 | JC11: =(JA11+JB11)/2 -> 0.046840565 | JD11: =(SUMPRODUCT(($G$8:$G$694=X11)*SQRT(JC11^2+4*(1-JC11)*$I$8:$I$694^2/Z11))-COUNTIF($G$8:$G$694,X11)*JC11)/(2*(1-JC11))-1 -> -8.9396798e-09 | JE11: =IF(JD11>0,JC11,JA11) -> 0.046840557 | JF11: =IF(JD11>0,JB11,JC11) -> 0.046840565 | JG11: =(JE11+JF11)/2 -> 0.046840561 | JH11: =(SUMPRODUCT(($G$8:$G$694=X11)*SQRT(JG11^2+4*(1-JG11)*$I$8:$I$694^2/Z11))-COUNTIF($G$8:$G$694,X11)*JG11)/(2*(1-JG11))-1 -> -3.699537e-09 | JI11: =IF(JH11>0,JG11,JE11) -> 0.046840557 | JJ11: =IF(JH11>0,JF11,JG11) -> 0.046840561 | JK11: =(JI11+JJ11)/2 -> 0.046840559 | JL11: =(SUMPRODUCT(($G$8:$G$694=X11)*SQRT(JK11^2+4*(1-JK11)*$I$8:$I$694^2/Z11))-COUNTIF($G$8:$G$694,X11)*JK11)/(2*(1-JK11))-1 -> -1.0794656e-09 | JM11: =IF(JL11>0,JK11,JI11) -> 0.046840557 | JN11: =IF(JL11>0,JJ11,JK11) -> 0.046840559 | JO11: =(JM11+JN11)/2 -> 0.046840558 | JP11: =(SUMPRODUCT(($G$8:$G$694=X11)*SQRT(JO11^2+4*(1-JO11)*$I$8:$I$694^2/Z11))-COUNTIF($G$8:$G$694,X11)*JO11)/(2*(1-JO11))-1 -> 2.3056979e-10 | JQ11: =IF(JP11>0,JO11,JM11) -> 0.046840558 | JR11: =IF(JP11>0,JN11,JO11) -> 0.046840559 | JS11: =(JQ11+JR11)/2 -> 0.046840559 | JT11: =(SUMPRODUCT(($G$8:$G$694=X11)*SQRT(JS11^2+4*(1-JS11)*$I$8:$I$694^2/Z11))-COUNTIF($G$8:$G$694,X11)*JS11)/(2*(1-JS11))-1 -> -4.2444792e-10 | JU11: =IF(JT11>0,JS11,JQ11) -> 0.046840558 | JV11: =IF(JT11>0,JR11,JS11) -> 0.046840559 | JW11: =(JU11+JV11)/2 -> 0.046840559 | JX11: =(SUMPRODUCT(($G$8:$G$694=X11)*SQRT(JW11^2+4*(1-JW11)*$I$8:$I$694^2/Z11))-COUNTIF($G$8:$G$694,X11)*JW11)/(2*(1-JW11))-1 -> -9.6938901e-11 | JY11: =IF(JX11>0,JW11,JU11) -> 0.046840558 | JZ11: =IF(JX11>0,JV11,JW11) -> 0.046840559 | KA11: =(EY11+EZ11)/2 -> 1.1134859 | KB11: =(JY11+JZ11)/2 -> 0.046840558
A12: =Odds_Input!A12 -> 4 | B12: =Odds_Input!B12 -> TITLE | C12: =Odds_Input!C12 -> Chicago Bulls | D12: =Odds_Input!D12 -> YES | E12: =Odds_Input!E12 -> - | F12: =Odds_Input!F12 -> 25000 | G12: =IF(OR(B12="WINS",B12="PLAYOFFS"),B12&"|"&C12&IF(B12="WINS","|"&TEXT(E12,"0.0"),""),B12) -> TITLE | H12: =IF(F12>0,1+F12/100,1+100/ABS(F12)) -> 251 | I12: =1/H12 -> 0.0039840637 | J12: =IF(LEFT(B12,6)="PLAYIN",A_playin_slots,1) -> 1 | K12: =COUNTIF($G$8:$G$694,G12) -> 30 | L12: =SUMIF($G$8:$G$694,G12,$I$8:$I$694) -> 1.2525652 | M12: =L12/J12-1 -> 0.25256519 | N12: =I12*J12/L12 -> 0.0031807237 | O12: =I12^R12 -> 0.0023027239 | P12: =IF(J12<>1,O12,IF(L12<=1,I12/L12,(SQRT(S12^2+4*(1-S12)*I12^2/L12)-S12)/(2*(1-S12)))) -> 0.0010482742 | Q12: =IF(A_devig="Multiplicative",N12,IF(A_devig="Power",O12,P12)) -> 0.0010482742 | R12: =INDEX($KA$8:$KA$96,MATCH(G12,$X$8:$X$96,0)) -> 1.0992153 | S12: =INDEX($KB$8:$KB$96,MATCH(G12,$X$8:$X$96,0)) -> 0.011051948 | X12: DIV_CENTRAL | Y12: =IF(LEFT(X12,6)="PLAYIN",A_playin_slots,1) -> 1 | Z12: =SUMIF($G$8:$G$694,X12,$I$8:$I$694) -> 1.122466 | AA12: 0.2 | AB12: 10 | AC12: =(AA12+AB12)/2 -> 5.1 | AD12: =SUMPRODUCT(($G$8:$G$694=X12)*($I$8:$I$694^AC12))-Y12 -> -0.97064485 | AE12: =IF(AD12>0,AC12,AA12) -> 0.2 | AF12: =IF(AD12>0,AB12,AC12) -> 5.1 | AG12: =(AE12+AF12)/2 -> 2.65 | AH12: =SUMPRODUCT(($G$8:$G$694=X12)*($I$8:$I$694^AG12))-Y12 -> -0.75913844 | AI12: =IF(AH12>0,AG12,AE12) -> 0.2 | AJ12: =IF(AH12>0,AF12,AG12) -> 2.65 | AK12: =(AI12+AJ12)/2 -> 1.425 | AL12: =SUMPRODUCT(($G$8:$G$694=X12)*($I$8:$I$694^AK12))-Y12 -> -0.26252323 | AM12: =IF(AL12>0,AK12,AI12) -> 0.2 | AN12: =IF(AL12>0,AJ12,AK12) -> 1.425 | AO12: =(AM12+AN12)/2 -> 0.8125 | AP12: =SUMPRODUCT(($G$8:$G$694=X12)*($I$8:$I$694^AO12))-Y12 -> 0.37128639 | AQ12: =IF(AP12>0,AO12,AM12) -> 0.8125 | AR12: =IF(AP12>0,AN12,AO12) -> 1.425 | AS12: =(AQ12+AR12)/2 -> 1.11875 | AT12: =SUMPRODUCT(($G$8:$G$694=X12)*($I$8:$I$694^AS12))-Y12 -> -0.0053660778 | AU12: =IF(AT12>0,AS12,AQ12) -> 0.8125 | AV12: =IF(AT12>0,AR12,AS12) -> 1.11875 | AW12: =(AU12+AV12)/2 -> 0.965625 | AX12: =SUMPRODUCT(($G$8:$G$694=X12)*($I$8:$I$694^AW12))-Y12 -> 0.16330303 | AY12: =IF(AX12>0,AW12,AU12) -> 0.965625 | AZ12: =IF(AX12>0,AV12,AW12) -> 1.11875 | BA12: =(AY12+AZ12)/2 -> 1.0421875 | BB12: =SUMPRODUCT(($G$8:$G$694=X12)*($I$8:$I$694^BA12))-Y12 -> 0.074819168 | BC12: =IF(BB12>0,BA12,AY12) -> 1.0421875 | BD12: =IF(BB12>0,AZ12,BA12) -> 1.11875 | BE12: =(BC12+BD12)/2 -> 1.0804687 | BF12: =SUMPRODUCT(($G$8:$G$694=X12)*($I$8:$I$694^BE12))-Y12 -> 0.033765406 | BG12: =IF(BF12>0,BE12,BC12) -> 1.0804687 | BH12: =IF(BF12>0,BD12,BE12) -> 1.11875 | BI12: =(BG12+BH12)/2 -> 1.0996094 | BJ12: =SUMPRODUCT(($G$8:$G$694=X12)*($I$8:$I$694^BI12))-Y12 -> 0.013967953 | BK12: =IF(BJ12>0,BI12,BG12) -> 1.0996094 | BL12: =IF(BJ12>0,BH12,BI12) -> 1.11875 | BM12: =(BK12+BL12)/2 -> 1.1091797 | BN12: =SUMPRODUCT(($G$8:$G$694=X12)*($I$8:$I$694^BM12))-Y12 -> 0.0042440289 | BO12: =IF(BN12>0,BM12,BK12) -> 1.1091797 | BP12: =IF(BN12>0,BL12,BM12) -> 1.11875 | BQ12: =(BO12+BP12)/2 -> 1.1139648 | BR12: =SUMPRODUCT(($G$8:$G$694=X12)*($I$8:$I$694^BQ12))-Y12 -> -0.00057512742 | BS12: =IF(BR12>0,BQ12,BO12) -> 1.1091797 | BT12: =IF(BR12>0,BP12,BQ12) -> 1.1139648 | BU12: =(BS12+BT12)/2 -> 1.1115723 | BV12: =SUMPRODUCT(($G$8:$G$694=X12)*($I$8:$I$694^BU12))-Y12 -> 0.0018309096 | BW12: =IF(BV12>0,BU12,BS12) -> 1.1115723 | BX12: =IF(BV12>0,BT12,BU12) -> 1.1139648 | BY12: =(BW12+BX12)/2 -> 1.1127686 | BZ12: =SUMPRODUCT(($G$8:$G$694=X12)*($I$8:$I$694^BY12))-Y12 -> 0.00062700774 | CA12: =IF(BZ12>0,BY12,BW12) -> 1.1127686 | CB12: =IF(BZ12>0,BX12,BY12) -> 1.1139648 | CC12: =(CA12+CB12)/2 -> 1.1133667 | CD12: =SUMPRODUCT(($G$8:$G$694=X12)*($I$8:$I$694^CC12))-Y12 -> 2.5719567e-05 | CE12: =IF(CD12>0,CC12,CA12) -> 1.1133667 | CF12: =IF(CD12>0,CB12,CC12) -> 1.1139648 | CG12: =(CE12+CF12)/2 -> 1.1136658 | CH12: =SUMPRODUCT(($G$8:$G$694=X12)*($I$8:$I$694^CG12))-Y12 -> -0.00027475904 | CI12: =IF(CH12>0,CG12,CE12) -> 1.1133667 | CJ12: =IF(CH12>0,CF12,CG12) -> 1.1136658 | CK12: =(CI12+CJ12)/2 -> 1.1135162 | CL12: =SUMPRODUCT(($G$8:$G$694=X12)*($I$8:$I$694^CK12))-Y12 -> -0.00012453352 | CM12: =IF(CL12>0,CK12,CI12) -> 1.1133667 | CN12: =IF(CL12>0,CJ12,CK12) -> 1.1135162 | CO12: =(CM12+CN12)/2 -> 1.1134415 | CP12: =SUMPRODUCT(($G$8:$G$694=X12)*($I$8:$I$694^CO12))-Y12 -> -4.9410424e-05 | CQ12: =IF(CP12>0,CO12,CM12) -> 1.1133667 | CR12: =IF(CP12>0,CN12,CO12) -> 1.1134415 | CS12: =(CQ12+CR12)/2 -> 1.1134041 | CT12: =SUMPRODUCT(($G$8:$G$694=X12)*($I$8:$I$694^CS12))-Y12 -> -1.184629e-05 | CU12: =IF(CT12>0,CS12,CQ12) -> 1.1133667 | CV12: =IF(CT12>0,CR12,CS12) -> 1.1134041 | CW12: =(CU12+CV12)/2 -> 1.1133854 | CX12: =SUMPRODUCT(($G$8:$G$694=X12)*($I$8:$I$694^CW12))-Y12 -> 6.9364231e-06 | CY12: =IF(CX12>0,CW12,CU12) -> 1.1133854 | CZ12: =IF(CX12>0,CV12,CW12) -> 1.1134041 | DA12: =(CY12+CZ12)/2 -> 1.1133947 | DB12: =SUMPRODUCT(($G$8:$G$694=X12)*($I$8:$I$694^DA12))-Y12 -> -2.4549873e-06 | DC12: =IF(DB12>0,DA12,CY12) -> 1.1133854 | DD12: =IF(DB12>0,CZ12,DA12) -> 1.1133947 | DE12: =(DC12+DD12)/2 -> 1.1133901 | DF12: =SUMPRODUCT(($G$8:$G$694=X12)*($I$8:$I$694^DE12))-Y12 -> 2.2407045e-06 | DG12: =IF(DF12>0,DE12,DC12) -> 1.1133901 | DH12: =IF(DF12>0,DD12,DE12) -> 1.1133947 | DI12: =(DG12+DH12)/2 -> 1.1133924 | DJ12: =SUMPRODUCT(($G$8:$G$694=X12)*($I$8:$I$694^DI12))-Y12 -> -1.0714476e-07 | DK12: =IF(DJ12>0,DI12,DG12) -> 1.1133901 | DL12: =IF(DJ12>0,DH12,DI12) -> 1.1133924 | DM12: =(DK12+DL12)/2 -> 1.1133912 | DN12: =SUMPRODUCT(($G$8:$G$694=X12)*($I$8:$I$694^DM12))-Y12 -> 1.066779e-06 | DO12: =IF(DN12>0,DM12,DK12) -> 1.1133912 | DP12: =IF(DN12>0,DL12,DM12) -> 1.1133924 | DQ12: =(DO12+DP12)/2 -> 1.1133918 | DR12: =SUMPRODUCT(($G$8:$G$694=X12)*($I$8:$I$694^DQ12))-Y12 -> 4.7981691e-07 | DS12: =IF(DR12>0,DQ12,DO12) -> 1.1133918 | DT12: =IF(DR12>0,DP12,DQ12) -> 1.1133924 | DU12: =(DS12+DT12)/2 -> 1.1133921 | DV12: =SUMPRODUCT(($G$8:$G$694=X12)*($I$8:$I$694^DU12))-Y12 -> 1.8633602e-07 | DW12: =IF(DV12>0,DU12,DS12) -> 1.1133921 | DX12: =IF(DV12>0,DT12,DU12) -> 1.1133924 | DY12: =(DW12+DX12)/2 -> 1.1133923 | DZ12: =SUMPRODUCT(($G$8:$G$694=X12)*($I$8:$I$694^DY12))-Y12 -> 3.9595616e-08 | EA12: =IF(DZ12>0,DY12,DW12) -> 1.1133923 | EB12: =IF(DZ12>0,DX12,DY12) -> 1.1133924 | EC12: =(EA12+EB12)/2 -> 1.1133923 | ED12: =SUMPRODUCT(($G$8:$G$694=X12)*($I$8:$I$694^EC12))-Y12 -> -3.3774578e-08 | EE12: =IF(ED12>0,EC12,EA12) -> 1.1133923 | EF12: =IF(ED12>0,EB12,EC12) -> 1.1133923 | EG12: =(EE12+EF12)/2 -> 1.1133923 | EH12: =SUMPRODUCT(($G$8:$G$694=X12)*($I$8:$I$694^EG12))-Y12 -> 2.910518e-09 | EI12: =IF(EH12>0,EG12,EE12) -> 1.1133923 | EJ12: =IF(EH12>0,EF12,EG12) -> 1.1133923 | EK12: =(EI12+EJ12)/2 -> 1.1133923 | EL12: =SUMPRODUCT(($G$8:$G$694=X12)*($I$8:$I$694^EK12))-Y12 -> -1.543203e-08 | EM12: =IF(EL12>0,EK12,EI12) -> 1.1133923 | EN12: =IF(EL12>0,EJ12,EK12) -> 1.1133923 | EO12: =(EM12+EN12)/2 -> 1.1133923 | EP12: =SUMPRODUCT(($G$8:$G$694=X12)*($I$8:$I$694^EO12))-Y12 -> -6.260756e-09 | EQ12: =IF(EP12>0,EO12,EM12) -> 1.1133923 | ER12: =IF(EP12>0,EN12,EO12) -> 1.1133923 | ES12: =(EQ12+ER12)/2 -> 1.1133923 | ET12: =SUMPRODUCT(($G$8:$G$694=X12)*($I$8:$I$694^ES12))-Y12 -> -1.6751192e-09 | EU12: =IF(ET12>0,ES12,EQ12) -> 1.1133923 | EV12: =IF(ET12>0,ER12,ES12) -> 1.1133923 | EW12: =(EU12+EV12)/2 -> 1.1133923 | EX12: =SUMPRODUCT(($G$8:$G$694=X12)*($I$8:$I$694^EW12))-Y12 -> 6.1769945e-10 | EY12: =IF(EX12>0,EW12,EU12) -> 1.1133923 | EZ12: =IF(EX12>0,EV12,EW12) -> 1.1133923 | FA12: 1e-06 | FB12: 0.9999 | FC12: =(FA12+FB12)/2 -> 0.4999505 | FD12: =(SUMPRODUCT(($G$8:$G$694=X12)*SQRT(FC12^2+4*(1-FC12)*$I$8:$I$694^2/Z12))-COUNTIF($G$8:$G$694,X12)*FC12)/(2*(1-FC12))-1 -> -0.38017578 | FE12: =IF(FD12>0,FC12,FA12) -> 1e-06 | FF12: =IF(FD12>0,FB12,FC12) -> 0.4999505 | FG12: =(FE12+FF12)/2 -> 0.24997575 | FH12: =(SUMPRODUCT(($G$8:$G$694=X12)*SQRT(FG12^2+4*(1-FG12)*$I$8:$I$694^2/Z12))-COUNTIF($G$8:$G$694,X12)*FG12)/(2*(1-FG12))-1 -> -0.19287951 | FI12: =IF(FH12>0,FG12,FE12) -> 1e-06 | FJ12: =IF(FH12>0,FF12,FG12) -> 0.24997575 | FK12: =(FI12+FJ12)/2 -> 0.12498837 | FL12: =(SUMPRODUCT(($G$8:$G$694=X12)*SQRT(FK12^2+4*(1-FK12)*$I$8:$I$694^2/Z12))-COUNTIF($G$8:$G$694,X12)*FK12)/(2*(1-FK12))-1 -> -0.080001319 | FM12: =IF(FL12>0,FK12,FI12) -> 1e-06 | FN12: =IF(FL12>0,FJ12,FK12) -> 0.12498837 | FO12: =(FM12+FN12)/2 -> 0.062494687 | FP12: =(SUMPRODUCT(($G$8:$G$694=X12)*SQRT(FO12^2+4*(1-FO12)*$I$8:$I$694^2/Z12))-COUNTIF($G$8:$G$694,X12)*FO12)/(2*(1-FO12))-1 -> -0.018558157 | FQ12: =IF(FP12>0,FO12,FM12) -> 1e-06 | FR12: =IF(FP12>0,FN12,FO12) -> 0.062494687 | FS12: =(FQ12+FR12)/2 -> 0.031247844 | FT12: =(SUMPRODUCT(($G$8:$G$694=X12)*SQRT(FS12^2+4*(1-FS12)*$I$8:$I$694^2/Z12))-COUNTIF($G$8:$G$694,X12)*FS12)/(2*(1-FS12))-1 -> 0.015027349 | FU12: =IF(FT12>0,FS12,FQ12) -> 0.031247844 | FV12: =IF(FT12>0,FR12,FS12) -> 0.062494687 | FW12: =(FU12+FV12)/2 -> 0.046871266 | FX12: =(SUMPRODUCT(($G$8:$G$694=X12)*SQRT(FW12^2+4*(1-FW12)*$I$8:$I$694^2/Z12))-COUNTIF($G$8:$G$694,X12)*FW12)/(2*(1-FW12))-1 -> -0.0022347787 | FY12: =IF(FX12>0,FW12,FU12) -> 0.031247844 | FZ12: =IF(FX12>0,FV12,FW12) -> 0.046871266 | GA12: =(FY12+FZ12)/2 -> 0.039059555 | GB12: =(SUMPRODUCT(($G$8:$G$694=X12)*SQRT(GA12^2+4*(1-GA12)*$I$8:$I$694^2/Z12))-COUNTIF($G$8:$G$694,X12)*GA12)/(2*(1-GA12))-1 -> 0.0062351832 | GC12: =IF(GB12>0,GA12,FY12) -> 0.039059555 | GD12: =IF(GB12>0,FZ12,GA12) -> 0.046871266 | GE12: =(GC12+GD12)/2 -> 0.04296541 | GF12: =(SUMPRODUCT(($G$8:$G$694=X12)*SQRT(GE12^2+4*(1-GE12)*$I$8:$I$694^2/Z12))-COUNTIF($G$8:$G$694,X12)*GE12)/(2*(1-GE12))-1 -> 0.0019670595 | GG12: =IF(GF12>0,GE12,GC12) -> 0.04296541 | GH12: =IF(GF12>0,GD12,GE12) -> 0.046871266 | GI12: =(GG12+GH12)/2 -> 0.044918338 | GJ12: =(SUMPRODUCT(($G$8:$G$694=X12)*SQRT(GI12^2+4*(1-GI12)*$I$8:$I$694^2/Z12))-COUNTIF($G$8:$G$694,X12)*GI12)/(2*(1-GI12))-1 -> -0.00014143455 | GK12: =IF(GJ12>0,GI12,GG12) -> 0.04296541 | GL12: =IF(GJ12>0,GH12,GI12) -> 0.044918338 | GM12: =(GK12+GL12)/2 -> 0.043941874 | GN12: =(SUMPRODUCT(($G$8:$G$694=X12)*SQRT(GM12^2+4*(1-GM12)*$I$8:$I$694^2/Z12))-COUNTIF($G$8:$G$694,X12)*GM12)/(2*(1-GM12))-1 -> 0.00091083656 | GO12: =IF(GN12>0,GM12,GK12) -> 0.043941874 | GP12: =IF(GN12>0,GL12,GM12) -> 0.044918338 | GQ12: =(GO12+GP12)/2 -> 0.044430106 | GR12: =(SUMPRODUCT(($G$8:$G$694=X12)*SQRT(GQ12^2+4*(1-GQ12)*$I$8:$I$694^2/Z12))-COUNTIF($G$8:$G$694,X12)*GQ12)/(2*(1-GQ12))-1 -> 0.00038421768 | GS12: =IF(GR12>0,GQ12,GO12) -> 0.044430106 | GT12: =IF(GR12>0,GP12,GQ12) -> 0.044918338 | GU12: =(GS12+GT12)/2 -> 0.044674222 | GV12: =(SUMPRODUCT(($G$8:$G$694=X12)*SQRT(GU12^2+4*(1-GU12)*$I$8:$I$694^2/Z12))-COUNTIF($G$8:$G$694,X12)*GU12)/(2*(1-GU12))-1 -> 0.00012127203 | GW12: =IF(GV12>0,GU12,GS12) -> 0.044674222 | GX12: =IF(GV12>0,GT12,GU12) -> 0.044918338 | GY12: =(GW12+GX12)/2 -> 0.04479628 | GZ12: =(SUMPRODUCT(($G$8:$G$694=X12)*SQRT(GY12^2+4*(1-GY12)*$I$8:$I$694^2/Z12))-COUNTIF($G$8:$G$694,X12)*GY12)/(2*(1-GY12))-1 -> -1.0110985e-05 | HA12: =IF(GZ12>0,GY12,GW12) -> 0.044674222 | HB12: =IF(GZ12>0,GX12,GY12) -> 0.04479628 | HC12: =(HA12+HB12)/2 -> 0.044735251 | HD12: =(SUMPRODUCT(($G$8:$G$694=X12)*SQRT(HC12^2+4*(1-HC12)*$I$8:$I$694^2/Z12))-COUNTIF($G$8:$G$694,X12)*HC12)/(2*(1-HC12))-1 -> 5.5573072e-05 | HE12: =IF(HD12>0,HC12,HA12) -> 0.044735251 | HF12: =IF(HD12>0,HB12,HC12) -> 0.04479628 | HG12: =(HE12+HF12)/2 -> 0.044765765 | HH12: =(SUMPRODUCT(($G$8:$G$694=X12)*SQRT(HG12^2+4*(1-HG12)*$I$8:$I$694^2/Z12))-COUNTIF($G$8:$G$694,X12)*HG12)/(2*(1-HG12))-1 -> 2.2729183e-05 | HI12: =IF(HH12>0,HG12,HE12) -> 0.044765765 | HJ12: =IF(HH12>0,HF12,HG12) -> 0.04479628 | HK12: =(HI12+HJ12)/2 -> 0.044781023 | HL12: =(SUMPRODUCT(($G$8:$G$694=X12)*SQRT(HK12^2+4*(1-HK12)*$I$8:$I$694^2/Z12))-COUNTIF($G$8:$G$694,X12)*HK12)/(2*(1-HK12))-1 -> 6.3086346e-06 | HM12: =IF(HL12>0,HK12,HI12) -> 0.044781023 | HN12: =IF(HL12>0,HJ12,HK12) -> 0.04479628 | HO12: =(HM12+HN12)/2 -> 0.044788651 | HP12: =(SUMPRODUCT(($G$8:$G$694=X12)*SQRT(HO12^2+4*(1-HO12)*$I$8:$I$694^2/Z12))-COUNTIF($G$8:$G$694,X12)*HO12)/(2*(1-HO12))-1 -> -1.9012912e-06 | HQ12: =IF(HP12>0,HO12,HM12) -> 0.044781023 | HR12: =IF(HP12>0,HN12,HO12) -> 0.044788651 | HS12: =(HQ12+HR12)/2 -> 0.044784837 | HT12: =(SUMPRODUCT(($G$8:$G$694=X12)*SQRT(HS12^2+4*(1-HS12)*$I$8:$I$694^2/Z12))-COUNTIF($G$8:$G$694,X12)*HS12)/(2*(1-HS12))-1 -> 2.2036426e-06 | HU12: =IF(HT12>0,HS12,HQ12) -> 0.044784837 | HV12: =IF(HT12>0,HR12,HS12) -> 0.044788651 | HW12: =(HU12+HV12)/2 -> 0.044786744 | HX12: =(SUMPRODUCT(($G$8:$G$694=X12)*SQRT(HW12^2+4*(1-HW12)*$I$8:$I$694^2/Z12))-COUNTIF($G$8:$G$694,X12)*HW12)/(2*(1-HW12))-1 -> 1.5116845e-07 | HY12: =IF(HX12>0,HW12,HU12) -> 0.044786744 | HZ12: =IF(HX12>0,HV12,HW12) -> 0.044788651 | IA12: =(HY12+HZ12)/2 -> 0.044787698 | IB12: =(SUMPRODUCT(($G$8:$G$694=X12)*SQRT(IA12^2+4*(1-IA12)*$I$8:$I$694^2/Z12))-COUNTIF($G$8:$G$694,X12)*IA12)/(2*(1-IA12))-1 -> -8.750632e-07 | IC12: =IF(IB12>0,IA12,HY12) -> 0.044786744 | ID12: =IF(IB12>0,HZ12,IA12) -> 0.044787698 | IE12: =(IC12+ID12)/2 -> 0.044787221 | IF12: =(SUMPRODUCT(($G$8:$G$694=X12)*SQRT(IE12^2+4*(1-IE12)*$I$8:$I$694^2/Z12))-COUNTIF($G$8:$G$694,X12)*IE12)/(2*(1-IE12))-1 -> -3.6194783e-07 | IG12: =IF(IF12>0,IE12,IC12) -> 0.044786744 | IH12: =IF(IF12>0,ID12,IE12) -> 0.044787221 | II12: =(IG12+IH12)/2 -> 0.044786983 | IJ12: =(SUMPRODUCT(($G$8:$G$694=X12)*SQRT(II12^2+4*(1-II12)*$I$8:$I$694^2/Z12))-COUNTIF($G$8:$G$694,X12)*II12)/(2*(1-II12))-1 -> -1.053898e-07 | IK12: =IF(IJ12>0,II12,IG12) -> 0.044786744 | IL12: =IF(IJ12>0,IH12,II12) -> 0.044786983 | IM12: =(IK12+IL12)/2 -> 0.044786863 | IN12: =(SUMPRODUCT(($G$8:$G$694=X12)*SQRT(IM12^2+4*(1-IM12)*$I$8:$I$694^2/Z12))-COUNTIF($G$8:$G$694,X12)*IM12)/(2*(1-IM12))-1 -> 2.2889294e-08 | IO12: =IF(IN12>0,IM12,IK12) -> 0.044786863 | IP12: =IF(IN12>0,IL12,IM12) -> 0.044786983 | IQ12: =(IO12+IP12)/2 -> 0.044786923 | IR12: =(SUMPRODUCT(($G$8:$G$694=X12)*SQRT(IQ12^2+4*(1-IQ12)*$I$8:$I$694^2/Z12))-COUNTIF($G$8:$G$694,X12)*IQ12)/(2*(1-IQ12))-1 -> -4.1250262e-08 | IS12: =IF(IR12>0,IQ12,IO12) -> 0.044786863 | IT12: =IF(IR12>0,IP12,IQ12) -> 0.044786923 | IU12: =(IS12+IT12)/2 -> 0.044786893 | IV12: =(SUMPRODUCT(($G$8:$G$694=X12)*SQRT(IU12^2+4*(1-IU12)*$I$8:$I$694^2/Z12))-COUNTIF($G$8:$G$694,X12)*IU12)/(2*(1-IU12))-1 -> -9.1804855e-09 | IW12: =IF(IV12>0,IU12,IS12) -> 0.044786863 | IX12: =IF(IV12>0,IT12,IU12) -> 0.044786893 | IY12: =(IW12+IX12)/2 -> 0.044786878 | IZ12: =(SUMPRODUCT(($G$8:$G$694=X12)*SQRT(IY12^2+4*(1-IY12)*$I$8:$I$694^2/Z12))-COUNTIF($G$8:$G$694,X12)*IY12)/(2*(1-IY12))-1 -> 6.8544042e-09 | JA12: =IF(IZ12>0,IY12,IW12) -> 0.044786878 | JB12: =IF(IZ12>0,IX12,IY12) -> 0.044786893 | JC12: =(JA12+JB12)/2 -> 0.044786886 | JD12: =(SUMPRODUCT(($G$8:$G$694=X12)*SQRT(JC12^2+4*(1-JC12)*$I$8:$I$694^2/Z12))-COUNTIF($G$8:$G$694,X12)*JC12)/(2*(1-JC12))-1 -> -1.1630408e-09 | JE12: =IF(JD12>0,JC12,JA12) -> 0.044786878 | JF12: =IF(JD12>0,JB12,JC12) -> 0.044786886 | JG12: =(JE12+JF12)/2 -> 0.044786882 | JH12: =(SUMPRODUCT(($G$8:$G$694=X12)*SQRT(JG12^2+4*(1-JG12)*$I$8:$I$694^2/Z12))-COUNTIF($G$8:$G$694,X12)*JG12)/(2*(1-JG12))-1 -> 2.8456817e-09 | JI12: =IF(JH12>0,JG12,JE12) -> 0.044786882 | JJ12: =IF(JH12>0,JF12,JG12) -> 0.044786886 | JK12: =(JI12+JJ12)/2 -> 0.044786884 | JL12: =(SUMPRODUCT(($G$8:$G$694=X12)*SQRT(JK12^2+4*(1-JK12)*$I$8:$I$694^2/Z12))-COUNTIF($G$8:$G$694,X12)*JK12)/(2*(1-JK12))-1 -> 8.4132035e-10 | JM12: =IF(JL12>0,JK12,JI12) -> 0.044786884 | JN12: =IF(JL12>0,JJ12,JK12) -> 0.044786886 | JO12: =(JM12+JN12)/2 -> 0.044786885 | JP12: =(SUMPRODUCT(($G$8:$G$694=X12)*SQRT(JO12^2+4*(1-JO12)*$I$8:$I$694^2/Z12))-COUNTIF($G$8:$G$694,X12)*JO12)/(2*(1-JO12))-1 -> -1.6086033e-10 | JQ12: =IF(JP12>0,JO12,JM12) -> 0.044786884 | JR12: =IF(JP12>0,JN12,JO12) -> 0.044786885 | JS12: =(JQ12+JR12)/2 -> 0.044786884 | JT12: =(SUMPRODUCT(($G$8:$G$694=X12)*SQRT(JS12^2+4*(1-JS12)*$I$8:$I$694^2/Z12))-COUNTIF($G$8:$G$694,X12)*JS12)/(2*(1-JS12))-1 -> 3.4023029e-10 | JU12: =IF(JT12>0,JS12,JQ12) -> 0.044786884 | JV12: =IF(JT12>0,JR12,JS12) -> 0.044786885 | JW12: =(JU12+JV12)/2 -> 0.044786885 | JX12: =(SUMPRODUCT(($G$8:$G$694=X12)*SQRT(JW12^2+4*(1-JW12)*$I$8:$I$694^2/Z12))-COUNTIF($G$8:$G$694,X12)*JW12)/(2*(1-JW12))-1 -> 8.9684926e-11 | JY12: =IF(JX12>0,JW12,JU12) -> 0.044786885 | JZ12: =IF(JX12>0,JV12,JW12) -> 0.044786885 | KA12: =(EY12+EZ12)/2 -> 1.1133923 | KB12: =(JY12+JZ12)/2 -> 0.044786885
A13: =Odds_Input!A13 -> 5 | B13: =Odds_Input!B13 -> TITLE | C13: =Odds_Input!C13 -> Cleveland Cavaliers | D13: =Odds_Input!D13 -> YES | E13: =Odds_Input!E13 -> - | F13: =Odds_Input!F13 -> 2400 | G13: =IF(OR(B13="WINS",B13="PLAYOFFS"),B13&"|"&C13&IF(B13="WINS","|"&TEXT(E13,"0.0"),""),B13) -> TITLE | H13: =IF(F13>0,1+F13/100,1+100/ABS(F13)) -> 25 | I13: =1/H13 -> 0.04 | J13: =IF(LEFT(B13,6)="PLAYIN",A_playin_slots,1) -> 1 | K13: =COUNTIF($G$8:$G$694,G13) -> 30 | L13: =SUMIF($G$8:$G$694,G13,$I$8:$I$694) -> 1.2525652 | M13: =L13/J13-1 -> 0.25256519 | N13: =I13*J13/L13 -> 0.031934466 | O13: =I13^R13 -> 0.029064504 | P13: =IF(J13<>1,O13,IF(L13<=1,I13/L13,(SQRT(S13^2+4*(1-S13)*I13^2/L13)-S13)/(2*(1-S13)))) -> 0.030783642 | Q13: =IF(A_devig="Multiplicative",N13,IF(A_devig="Power",O13,P13)) -> 0.030783642 | R13: =INDEX($KA$8:$KA$96,MATCH(G13,$X$8:$X$96,0)) -> 1.0992153 | S13: =INDEX($KB$8:$KB$96,MATCH(G13,$X$8:$X$96,0)) -> 0.011051948 | X13: DIV_SOUTHEAST | Y13: =IF(LEFT(X13,6)="PLAYIN",A_playin_slots,1) -> 1 | Z13: =SUMIF($G$8:$G$694,X13,$I$8:$I$694) -> 1.1184505 | AA13: 0.2 | AB13: 10 | AC13: =(AA13+AB13)/2 -> 5.1 | AD13: =SUMPRODUCT(($G$8:$G$694=X13)*($I$8:$I$694^AC13))-Y13 -> -0.99149822 | AE13: =IF(AD13>0,AC13,AA13) -> 0.2 | AF13: =IF(AD13>0,AB13,AC13) -> 5.1 | AG13: =(AE13+AF13)/2 -> 2.65 | AH13: =SUMPRODUCT(($G$8:$G$694=X13)*($I$8:$I$694^AG13))-Y13 -> -0.86107276 | AI13: =IF(AH13>0,AG13,AE13) -> 0.2 | AJ13: =IF(AH13>0,AF13,AG13) -> 2.65 | AK13: =(AI13+AJ13)/2 -> 1.425 | AL13: =SUMPRODUCT(($G$8:$G$694=X13)*($I$8:$I$694^AK13))-Y13 -> -0.36650913 | AM13: =IF(AL13>0,AK13,AI13) -> 0.2 | AN13: =IF(AL13>0,AJ13,AK13) -> 1.425 | AO13: =(AM13+AN13)/2 -> 0.8125 | AP13: =SUMPRODUCT(($G$8:$G$694=X13)*($I$8:$I$694^AO13))-Y13 -> 0.45251686 | AQ13: =IF(AP13>0,AO13,AM13) -> 0.8125 | AR13: =IF(AP13>0,AN13,AO13) -> 1.425 | AS13: =(AQ13+AR13)/2 -> 1.11875 | AT13: =SUMPRODUCT(($G$8:$G$694=X13)*($I$8:$I$694^AS13))-Y13 -> -0.048757261 | AU13: =IF(AT13>0,AS13,AQ13) -> 0.8125 | AV13: =IF(AT13>0,AR13,AS13) -> 1.11875 | AW13: =(AU13+AV13)/2 -> 0.965625 | AX13: =SUMPRODUCT(($G$8:$G$694=X13)*($I$8:$I$694^AW13))-Y13 -> 0.17271296 | AY13: =IF(AX13>0,AW13,AU13) -> 0.965625 | AZ13: =IF(AX13>0,AV13,AW13) -> 1.11875 | BA13: =(AY13+AZ13)/2 -> 1.0421875 | BB13: =SUMPRODUCT(($G$8:$G$694=X13)*($I$8:$I$694^BA13))-Y13 -> 0.055605616 | BC13: =IF(BB13>0,BA13,AY13) -> 1.0421875 | BD13: =IF(BB13>0,AZ13,BA13) -> 1.11875 | BE13: =(BC13+BD13)/2 -> 1.0804687 | BF13: =SUMPRODUCT(($G$8:$G$694=X13)*($I$8:$I$694^BE13))-Y13 -> 0.0019319495 | BG13: =IF(BF13>0,BE13,BC13) -> 1.0804687 | BH13: =IF(BF13>0,BD13,BE13) -> 1.11875 | BI13: =(BG13+BH13)/2 -> 1.0996094 | BJ13: =SUMPRODUCT(($G$8:$G$694=X13)*($I$8:$I$694^BI13))-Y13 -> -0.023773888 | BK13: =IF(BJ13>0,BI13,BG13) -> 1.0804687 | BL13: =IF(BJ13>0,BH13,BI13) -> 1.0996094 | BM13: =(BK13+BL13)/2 -> 1.0900391 | BN13: =SUMPRODUCT(($G$8:$G$694=X13)*($I$8:$I$694^BM13))-Y13 -> -0.011012723 | BO13: =IF(BN13>0,BM13,BK13) -> 1.0804687 | BP13: =IF(BN13>0,BL13,BM13) -> 1.0900391 | BQ13: =(BO13+BP13)/2 -> 1.0852539 | BR13: =SUMPRODUCT(($G$8:$G$694=X13)*($I$8:$I$694^BQ13))-Y13 -> -0.0045635083 | BS13: =IF(BR13>0,BQ13,BO13) -> 1.0804687 | BT13: =IF(BR13>0,BP13,BQ13) -> 1.0852539 | BU13: =(BS13+BT13)/2 -> 1.0828613 | BV13: =SUMPRODUCT(($G$8:$G$694=X13)*($I$8:$I$694^BU13))-Y13 -> -0.0013215829 | BW13: =IF(BV13>0,BU13,BS13) -> 1.0804687 | BX13: =IF(BV13>0,BT13,BU13) -> 1.0828613 | BY13: =(BW13+BX13)/2 -> 1.081665 | BZ13: =SUMPRODUCT(($G$8:$G$694=X13)*($I$8:$I$694^BY13))-Y13 -> 0.00030372948 | CA13: =IF(BZ13>0,BY13,BW13) -> 1.081665 | CB13: =IF(BZ13>0,BX13,BY13) -> 1.0828613 | CC13: =(CA13+CB13)/2 -> 1.0822632 | CD13: =SUMPRODUCT(($G$8:$G$694=X13)*($I$8:$I$694^CC13))-Y13 -> -0.00050928981 | CE13: =IF(CD13>0,CC13,CA13) -> 1.081665 | CF13: =IF(CD13>0,CB13,CC13) -> 1.0822632 | CG13: =(CE13+CF13)/2 -> 1.0819641 | CH13: =SUMPRODUCT(($G$8:$G$694=X13)*($I$8:$I$694^CG13))-Y13 -> -0.00010287098 | CI13: =IF(CH13>0,CG13,CE13) -> 1.081665 | CJ13: =IF(CH13>0,CF13,CG13) -> 1.0819641 | CK13: =(CI13+CJ13)/2 -> 1.0818146 | CL13: =SUMPRODUCT(($G$8:$G$694=X13)*($I$8:$I$694^CK13))-Y13 -> 0.00010040654 | CM13: =IF(CL13>0,CK13,CI13) -> 1.0818146 | CN13: =IF(CL13>0,CJ13,CK13) -> 1.0819641 | CO13: =(CM13+CN13)/2 -> 1.0818893 | CP13: =SUMPRODUCT(($G$8:$G$694=X13)*($I$8:$I$694^CO13))-Y13 -> -1.2378965e-06 | CQ13: =IF(CP13>0,CO13,CM13) -> 1.0818146 | CR13: =IF(CP13>0,CN13,CO13) -> 1.0818893 | CS13: =(CQ13+CR13)/2 -> 1.081852 | CT13: =SUMPRODUCT(($G$8:$G$694=X13)*($I$8:$I$694^CS13))-Y13 -> 4.9582903e-05 | CU13: =IF(CT13>0,CS13,CQ13) -> 1.081852 | CV13: =IF(CT13>0,CR13,CS13) -> 1.0818893 | CW13: =(CU13+CV13)/2 -> 1.0818707 | CX13: =SUMPRODUCT(($G$8:$G$694=X13)*($I$8:$I$694^CW13))-Y13 -> 2.4172149e-05 | CY13: =IF(CX13>0,CW13,CU13) -> 1.0818707 | CZ13: =IF(CX13>0,CV13,CW13) -> 1.0818893 | DA13: =(CY13+CZ13)/2 -> 1.08188 | DB13: =SUMPRODUCT(($G$8:$G$694=X13)*($I$8:$I$694^DA13))-Y13 -> 1.1467037e-05 | DC13: =IF(DB13>0,DA13,CY13) -> 1.08188 | DD13: =IF(DB13>0,CZ13,DA13) -> 1.0818893 | DE13: =(DC13+DD13)/2 -> 1.0818847 | DF13: =SUMPRODUCT(($G$8:$G$694=X13)*($I$8:$I$694^DE13))-Y13 -> 5.1145482e-06 | DG13: =IF(DF13>0,DE13,DC13) -> 1.0818847 | DH13: =IF(DF13>0,DD13,DE13) -> 1.0818893 | DI13: =(DG13+DH13)/2 -> 1.081887 | DJ13: =SUMPRODUCT(($G$8:$G$694=X13)*($I$8:$I$694^DI13))-Y13 -> 1.9383203e-06 | DK13: =IF(DJ13>0,DI13,DG13) -> 1.081887 | DL13: =IF(DJ13>0,DH13,DI13) -> 1.0818893 | DM13: =(DK13+DL13)/2 -> 1.0818882 | DN13: =SUMPRODUCT(($G$8:$G$694=X13)*($I$8:$I$694^DM13))-Y13 -> 3.5021049e-07 | DO13: =IF(DN13>0,DM13,DK13) -> 1.0818882 | DP13: =IF(DN13>0,DL13,DM13) -> 1.0818893 | DQ13: =(DO13+DP13)/2 -> 1.0818888 | DR13: =SUMPRODUCT(($G$8:$G$694=X13)*($I$8:$I$694^DQ13))-Y13 -> -4.4384337e-07 | DS13: =IF(DR13>0,DQ13,DO13) -> 1.0818882 | DT13: =IF(DR13>0,DP13,DQ13) -> 1.0818888 | DU13: =(DS13+DT13)/2 -> 1.0818885 | DV13: =SUMPRODUCT(($G$8:$G$694=X13)*($I$8:$I$694^DU13))-Y13 -> -4.6816524e-08 | DW13: =IF(DV13>0,DU13,DS13) -> 1.0818882 | DX13: =IF(DV13>0,DT13,DU13) -> 1.0818885 | DY13: =(DW13+DX13)/2 -> 1.0818883 | DZ13: =SUMPRODUCT(($G$8:$G$694=X13)*($I$8:$I$694^DY13))-Y13 -> 1.5169696e-07 | EA13: =IF(DZ13>0,DY13,DW13) -> 1.0818883 | EB13: =IF(DZ13>0,DX13,DY13) -> 1.0818885 | EC13: =(EA13+EB13)/2 -> 1.0818884 | ED13: =SUMPRODUCT(($G$8:$G$694=X13)*($I$8:$I$694^EC13))-Y13 -> 5.2440214e-08 | EE13: =IF(ED13>0,EC13,EA13) -> 1.0818884 | EF13: =IF(ED13>0,EB13,EC13) -> 1.0818885 | EG13: =(EE13+EF13)/2 -> 1.0818884 | EH13: =SUMPRODUCT(($G$8:$G$694=X13)*($I$8:$I$694^EG13))-Y13 -> 2.8118434e-09 | EI13: =IF(EH13>0,EG13,EE13) -> 1.0818884 | EJ13: =IF(EH13>0,EF13,EG13) -> 1.0818885 | EK13: =(EI13+EJ13)/2 -> 1.0818884 | EL13: =SUMPRODUCT(($G$8:$G$694=X13)*($I$8:$I$694^EK13))-Y13 -> -2.2002341e-08 | EM13: =IF(EL13>0,EK13,EI13) -> 1.0818884 | EN13: =IF(EL13>0,EJ13,EK13) -> 1.0818884 | EO13: =(EM13+EN13)/2 -> 1.0818884 | EP13: =SUMPRODUCT(($G$8:$G$694=X13)*($I$8:$I$694^EO13))-Y13 -> -9.5952488e-09 | EQ13: =IF(EP13>0,EO13,EM13) -> 1.0818884 | ER13: =IF(EP13>0,EN13,EO13) -> 1.0818884 | ES13: =(EQ13+ER13)/2 -> 1.0818884 | ET13: =SUMPRODUCT(($G$8:$G$694=X13)*($I$8:$I$694^ES13))-Y13 -> -3.3917027e-09 | EU13: =IF(ET13>0,ES13,EQ13) -> 1.0818884 | EV13: =IF(ET13>0,ER13,ES13) -> 1.0818884 | EW13: =(EU13+EV13)/2 -> 1.0818884 | EX13: =SUMPRODUCT(($G$8:$G$694=X13)*($I$8:$I$694^EW13))-Y13 -> -2.8992975e-10 | EY13: =IF(EX13>0,EW13,EU13) -> 1.0818884 | EZ13: =IF(EX13>0,EV13,EW13) -> 1.0818884 | FA13: 1e-06 | FB13: 0.9999 | FC13: =(FA13+FB13)/2 -> 0.4999505 | FD13: =(SUMPRODUCT(($G$8:$G$694=X13)*SQRT(FC13^2+4*(1-FC13)*$I$8:$I$694^2/Z13))-COUNTIF($G$8:$G$694,X13)*FC13)/(2*(1-FC13))-1 -> -0.52246076 | FE13: =IF(FD13>0,FC13,FA13) -> 1e-06 | FF13: =IF(FD13>0,FB13,FC13) -> 0.4999505 | FG13: =(FE13+FF13)/2 -> 0.24997575 | FH13: =(SUMPRODUCT(($G$8:$G$694=X13)*SQRT(FG13^2+4*(1-FG13)*$I$8:$I$694^2/Z13))-COUNTIF($G$8:$G$694,X13)*FG13)/(2*(1-FG13))-1 -> -0.31143899 | FI13: =IF(FH13>0,FG13,FE13) -> 1e-06 | FJ13: =IF(FH13>0,FF13,FG13) -> 0.24997575 | FK13: =(FI13+FJ13)/2 -> 0.12498837 | FL13: =(SUMPRODUCT(($G$8:$G$694=X13)*SQRT(FK13^2+4*(1-FK13)*$I$8:$I$694^2/Z13))-COUNTIF($G$8:$G$694,X13)*FK13)/(2*(1-FK13))-1 -> -0.15482553 | FM13: =IF(FL13>0,FK13,FI13) -> 1e-06 | FN13: =IF(FL13>0,FJ13,FK13) -> 0.12498837 | FO13: =(FM13+FN13)/2 -> 0.062494687 | FP13: =(SUMPRODUCT(($G$8:$G$694=X13)*SQRT(FO13^2+4*(1-FO13)*$I$8:$I$694^2/Z13))-COUNTIF($G$8:$G$694,X13)*FO13)/(2*(1-FO13))-1 -> -0.057061785 | FQ13: =IF(FP13>0,FO13,FM13) -> 1e-06 | FR13: =IF(FP13>0,FN13,FO13) -> 0.062494687 | FS13: =(FQ13+FR13)/2 -> 0.031247844 | FT13: =(SUMPRODUCT(($G$8:$G$694=X13)*SQRT(FS13^2+4*(1-FS13)*$I$8:$I$694^2/Z13))-COUNTIF($G$8:$G$694,X13)*FS13)/(2*(1-FS13))-1 -> -0.0019364544 | FU13: =IF(FT13>0,FS13,FQ13) -> 1e-06 | FV13: =IF(FT13>0,FR13,FS13) -> 0.031247844 | FW13: =(FU13+FV13)/2 -> 0.015624422 | FX13: =(SUMPRODUCT(($G$8:$G$694=X13)*SQRT(FW13^2+4*(1-FW13)*$I$8:$I$694^2/Z13))-COUNTIF($G$8:$G$694,X13)*FW13)/(2*(1-FW13))-1 -> 0.027281263 | FY13: =IF(FX13>0,FW13,FU13) -> 0.015624422 | FZ13: =IF(FX13>0,FV13,FW13) -> 0.031247844 | GA13: =(FY13+FZ13)/2 -> 0.023436133 | GB13: =(SUMPRODUCT(($G$8:$G$694=X13)*SQRT(GA13^2+4*(1-GA13)*$I$8:$I$694^2/Z13))-COUNTIF($G$8:$G$694,X13)*GA13)/(2*(1-GA13))-1 -> 0.012535866 | GC13: =IF(GB13>0,GA13,FY13) -> 0.023436133 | GD13: =IF(GB13>0,FZ13,GA13) -> 0.031247844 | GE13: =(GC13+GD13)/2 -> 0.027341988 | GF13: =(SUMPRODUCT(($G$8:$G$694=X13)*SQRT(GE13^2+4*(1-GE13)*$I$8:$I$694^2/Z13))-COUNTIF($G$8:$G$694,X13)*GE13)/(2*(1-GE13))-1 -> 0.0052653119 | GG13: =IF(GF13>0,GE13,GC13) -> 0.027341988 | GH13: =IF(GF13>0,GD13,GE13) -> 0.031247844 | GI13: =(GG13+GH13)/2 -> 0.029294916 | GJ13: =(SUMPRODUCT(($G$8:$G$694=X13)*SQRT(GI13^2+4*(1-GI13)*$I$8:$I$694^2/Z13))-COUNTIF($G$8:$G$694,X13)*GI13)/(2*(1-GI13))-1 -> 0.001655806 | GK13: =IF(GJ13>0,GI13,GG13) -> 0.029294916 | GL13: =IF(GJ13>0,GH13,GI13) -> 0.031247844 | GM13: =(GK13+GL13)/2 -> 0.03027138 | GN13: =(SUMPRODUCT(($G$8:$G$694=X13)*SQRT(GM13^2+4*(1-GM13)*$I$8:$I$694^2/Z13))-COUNTIF($G$8:$G$694,X13)*GM13)/(2*(1-GM13))-1 -> -0.0001424824 | GO13: =IF(GN13>0,GM13,GK13) -> 0.029294916 | GP13: =IF(GN13>0,GL13,GM13) -> 0.03027138 | GQ13: =(GO13+GP13)/2 -> 0.029783148 | GR13: =(SUMPRODUCT(($G$8:$G$694=X13)*SQRT(GQ13^2+4*(1-GQ13)*$I$8:$I$694^2/Z13))-COUNTIF($G$8:$G$694,X13)*GQ13)/(2*(1-GQ13))-1 -> 0.00075612255 | GS13: =IF(GR13>0,GQ13,GO13) -> 0.029783148 | GT13: =IF(GR13>0,GP13,GQ13) -> 0.03027138 | GU13: =(GS13+GT13)/2 -> 0.030027264 | GV13: =(SUMPRODUCT(($G$8:$G$694=X13)*SQRT(GU13^2+4*(1-GU13)*$I$8:$I$694^2/Z13))-COUNTIF($G$8:$G$694,X13)*GU13)/(2*(1-GU13))-1 -> 0.00030668522 | GW13: =IF(GV13>0,GU13,GS13) -> 0.030027264 | GX13: =IF(GV13>0,GT13,GU13) -> 0.03027138 | GY13: =(GW13+GX13)/2 -> 0.030149322 | GZ13: =(SUMPRODUCT(($G$8:$G$694=X13)*SQRT(GY13^2+4*(1-GY13)*$I$8:$I$694^2/Z13))-COUNTIF($G$8:$G$694,X13)*GY13)/(2*(1-GY13))-1 -> 8.2067691e-05 | HA13: =IF(GZ13>0,GY13,GW13) -> 0.030149322 | HB13: =IF(GZ13>0,GX13,GY13) -> 0.03027138 | HC13: =(HA13+HB13)/2 -> 0.030210351 | HD13: =(SUMPRODUCT(($G$8:$G$694=X13)*SQRT(HC13^2+4*(1-HC13)*$I$8:$I$694^2/Z13))-COUNTIF($G$8:$G$694,X13)*HC13)/(2*(1-HC13))-1 -> -3.0215786e-05 | HE13: =IF(HD13>0,HC13,HA13) -> 0.030149322 | HF13: =IF(HD13>0,HB13,HC13) -> 0.030210351 | HG13: =(HE13+HF13)/2 -> 0.030179836 | HH13: =(SUMPRODUCT(($G$8:$G$694=X13)*SQRT(HG13^2+4*(1-HG13)*$I$8:$I$694^2/Z13))-COUNTIF($G$8:$G$694,X13)*HG13)/(2*(1-HG13))-1 -> 2.5923845e-05 | HI13: =IF(HH13>0,HG13,HE13) -> 0.030179836 | HJ13: =IF(HH13>0,HF13,HG13) -> 0.030210351 | HK13: =(HI13+HJ13)/2 -> 0.030195094 | HL13: =(SUMPRODUCT(($G$8:$G$694=X13)*SQRT(HK13^2+4*(1-HK13)*$I$8:$I$694^2/Z13))-COUNTIF($G$8:$G$694,X13)*HK13)/(2*(1-HK13))-1 -> -2.1464972e-06 | HM13: =IF(HL13>0,HK13,HI13) -> 0.030179836 | HN13: =IF(HL13>0,HJ13,HK13) -> 0.030195094 | HO13: =(HM13+HN13)/2 -> 0.030187465 | HP13: =(SUMPRODUCT(($G$8:$G$694=X13)*SQRT(HO13^2+4*(1-HO13)*$I$8:$I$694^2/Z13))-COUNTIF($G$8:$G$694,X13)*HO13)/(2*(1-HO13))-1 -> 1.1888542e-05 | HQ13: =IF(HP13>0,HO13,HM13) -> 0.030187465 | HR13: =IF(HP13>0,HN13,HO13) -> 0.030195094 | HS13: =(HQ13+HR13)/2 -> 0.030191279 | HT13: =(SUMPRODUCT(($G$8:$G$694=X13)*SQRT(HS13^2+4*(1-HS13)*$I$8:$I$694^2/Z13))-COUNTIF($G$8:$G$694,X13)*HS13)/(2*(1-HS13))-1 -> 4.8709896e-06 | HU13: =IF(HT13>0,HS13,HQ13) -> 0.030191279 | HV13: =IF(HT13>0,HR13,HS13) -> 0.030195094 | HW13: =(HU13+HV13)/2 -> 0.030193186 | HX13: =(SUMPRODUCT(($G$8:$G$694=X13)*SQRT(HW13^2+4*(1-HW13)*$I$8:$I$694^2/Z13))-COUNTIF($G$8:$G$694,X13)*HW13)/(2*(1-HW13))-1 -> 1.362238e-06 | HY13: =IF(HX13>0,HW13,HU13) -> 0.030193186 | HZ13: =IF(HX13>0,HV13,HW13) -> 0.030195094 | IA13: =(HY13+HZ13)/2 -> 0.03019414 | IB13: =(SUMPRODUCT(($G$8:$G$694=X13)*SQRT(IA13^2+4*(1-IA13)*$I$8:$I$694^2/Z13))-COUNTIF($G$8:$G$694,X13)*IA13)/(2*(1-IA13))-1 -> -3.9213169e-07 | IC13: =IF(IB13>0,IA13,HY13) -> 0.030193186 | ID13: =IF(IB13>0,HZ13,IA13) -> 0.03019414 | IE13: =(IC13+ID13)/2 -> 0.030193663 | IF13: =(SUMPRODUCT(($G$8:$G$694=X13)*SQRT(IE13^2+4*(1-IE13)*$I$8:$I$694^2/Z13))-COUNTIF($G$8:$G$694,X13)*IE13)/(2*(1-IE13))-1 -> 4.8505261e-07 | IG13: =IF(IF13>0,IE13,IC13) -> 0.030193663 | IH13: =IF(IF13>0,ID13,IE13) -> 0.03019414 | II13: =(IG13+IH13)/2 -> 0.030193902 | IJ13: =(SUMPRODUCT(($G$8:$G$694=X13)*SQRT(II13^2+4*(1-II13)*$I$8:$I$694^2/Z13))-COUNTIF($G$8:$G$694,X13)*II13)/(2*(1-II13))-1 -> 4.6460332e-08 | IK13: =IF(IJ13>0,II13,IG13) -> 0.030193902 | IL13: =IF(IJ13>0,IH13,II13) -> 0.03019414 | IM13: =(IK13+IL13)/2 -> 0.030194021 | IN13: =(SUMPRODUCT(($G$8:$G$694=X13)*SQRT(IM13^2+4*(1-IM13)*$I$8:$I$694^2/Z13))-COUNTIF($G$8:$G$694,X13)*IM13)/(2*(1-IM13))-1 -> -1.7283571e-07 | IO13: =IF(IN13>0,IM13,IK13) -> 0.030193902 | IP13: =IF(IN13>0,IL13,IM13) -> 0.030194021 | IQ13: =(IO13+IP13)/2 -> 0.030193961 | IR13: =(SUMPRODUCT(($G$8:$G$694=X13)*SQRT(IQ13^2+4*(1-IQ13)*$I$8:$I$694^2/Z13))-COUNTIF($G$8:$G$694,X13)*IQ13)/(2*(1-IQ13))-1 -> -6.3187699e-08 | IS13: =IF(IR13>0,IQ13,IO13) -> 0.030193902 | IT13: =IF(IR13>0,IP13,IQ13) -> 0.030193961 | IU13: =(IS13+IT13)/2 -> 0.030193931 | IV13: =(SUMPRODUCT(($G$8:$G$694=X13)*SQRT(IU13^2+4*(1-IU13)*$I$8:$I$694^2/Z13))-COUNTIF($G$8:$G$694,X13)*IU13)/(2*(1-IU13))-1 -> -8.3636855e-09 | IW13: =IF(IV13>0,IU13,IS13) -> 0.030193902 | IX13: =IF(IV13>0,IT13,IU13) -> 0.030193931 | IY13: =(IW13+IX13)/2 -> 0.030193917 | IZ13: =(SUMPRODUCT(($G$8:$G$694=X13)*SQRT(IY13^2+4*(1-IY13)*$I$8:$I$694^2/Z13))-COUNTIF($G$8:$G$694,X13)*IY13)/(2*(1-IY13))-1 -> 1.9048322e-08 | JA13: =IF(IZ13>0,IY13,IW13) -> 0.030193917 | JB13: =IF(IZ13>0,IX13,IY13) -> 0.030193931 | JC13: =(JA13+JB13)/2 -> 0.030193924 | JD13: =(SUMPRODUCT(($G$8:$G$694=X13)*SQRT(JC13^2+4*(1-JC13)*$I$8:$I$694^2/Z13))-COUNTIF($G$8:$G$694,X13)*JC13)/(2*(1-JC13))-1 -> 5.3423186e-09 | JE13: =IF(JD13>0,JC13,JA13) -> 0.030193924 | JF13: =IF(JD13>0,JB13,JC13) -> 0.030193931 | JG13: =(JE13+JF13)/2 -> 0.030193928 | JH13: =(SUMPRODUCT(($G$8:$G$694=X13)*SQRT(JG13^2+4*(1-JG13)*$I$8:$I$694^2/Z13))-COUNTIF($G$8:$G$694,X13)*JG13)/(2*(1-JG13))-1 -> -1.5106837e-09 | JI13: =IF(JH13>0,JG13,JE13) -> 0.030193924 | JJ13: =IF(JH13>0,JF13,JG13) -> 0.030193928 | JK13: =(JI13+JJ13)/2 -> 0.030193926 | JL13: =(SUMPRODUCT(($G$8:$G$694=X13)*SQRT(JK13^2+4*(1-JK13)*$I$8:$I$694^2/Z13))-COUNTIF($G$8:$G$694,X13)*JK13)/(2*(1-JK13))-1 -> 1.9158175e-09 | JM13: =IF(JL13>0,JK13,JI13) -> 0.030193926 | JN13: =IF(JL13>0,JJ13,JK13) -> 0.030193928 | JO13: =(JM13+JN13)/2 -> 0.030193927 | JP13: =(SUMPRODUCT(($G$8:$G$694=X13)*SQRT(JO13^2+4*(1-JO13)*$I$8:$I$694^2/Z13))-COUNTIF($G$8:$G$694,X13)*JO13)/(2*(1-JO13))-1 -> 2.0256685e-10 | JQ13: =IF(JP13>0,JO13,JM13) -> 0.030193927 | JR13: =IF(JP13>0,JN13,JO13) -> 0.030193928 | JS13: =(JQ13+JR13)/2 -> 0.030193927 | JT13: =(SUMPRODUCT(($G$8:$G$694=X13)*SQRT(JS13^2+4*(1-JS13)*$I$8:$I$694^2/Z13))-COUNTIF($G$8:$G$694,X13)*JS13)/(2*(1-JS13))-1 -> -6.5405859e-10 | JU13: =IF(JT13>0,JS13,JQ13) -> 0.030193927 | JV13: =IF(JT13>0,JR13,JS13) -> 0.030193927 | JW13: =(JU13+JV13)/2 -> 0.030193927 | JX13: =(SUMPRODUCT(($G$8:$G$694=X13)*SQRT(JW13^2+4*(1-JW13)*$I$8:$I$694^2/Z13))-COUNTIF($G$8:$G$694,X13)*JW13)/(2*(1-JW13))-1 -> -2.2574576e-10 | JY13: =IF(JX13>0,JW13,JU13) -> 0.030193927 | JZ13: =IF(JX13>0,JV13,JW13) -> 0.030193927 | KA13: =(EY13+EZ13)/2 -> 1.0818884 | KB13: =(JY13+JZ13)/2 -> 0.030193927
A14: =Odds_Input!A14 -> 6 | B14: =Odds_Input!B14 -> TITLE | C14: =Odds_Input!C14 -> Dallas Mavericks | D14: =Odds_Input!D14 -> YES | E14: =Odds_Input!E14 -> - | F14: =Odds_Input!F14 -> 16000 | G14: =IF(OR(B14="WINS",B14="PLAYOFFS"),B14&"|"&C14&IF(B14="WINS","|"&TEXT(E14,"0.0"),""),B14) -> TITLE | H14: =IF(F14>0,1+F14/100,1+100/ABS(F14)) -> 161 | I14: =1/H14 -> 0.0062111801 | J14: =IF(LEFT(B14,6)="PLAYIN",A_playin_slots,1) -> 1 | K14: =COUNTIF($G$8:$G$694,G14) -> 30 | L14: =SUMIF($G$8:$G$694,G14,$I$8:$I$694) -> 1.2525652 | M14: =L14/J14-1 -> 0.25256519 | N14: =I14*J14/L14 -> 0.0049587679 | O14: =I14^R14 -> 0.0037516574 | P14: =IF(J14<>1,O14,IF(L14<=1,I14/L14,(SQRT(S14^2+4*(1-S14)*I14^2/L14)-S14)/(2*(1-S14)))) -> 0.002309531 | Q14: =IF(A_devig="Multiplicative",N14,IF(A_devig="Power",O14,P14)) -> 0.002309531 | R14: =INDEX($KA$8:$KA$96,MATCH(G14,$X$8:$X$96,0)) -> 1.0992153 | S14: =INDEX($KB$8:$KB$96,MATCH(G14,$X$8:$X$96,0)) -> 0.011051948 | X14: DIV_NORTHWEST | Y14: =IF(LEFT(X14,6)="PLAYIN",A_playin_slots,1) -> 1 | Z14: =SUMIF($G$8:$G$694,X14,$I$8:$I$694) -> 1.1129211 | AA14: 0.2 | AB14: 10 | AC14: =(AA14+AB14)/2 -> 5.1 | AD14: =SUMPRODUCT(($G$8:$G$694=X14)*($I$8:$I$694^AC14))-Y14 -> -0.51798546 | AE14: =IF(AD14>0,AC14,AA14) -> 0.2 | AF14: =IF(AD14>0,AB14,AC14) -> 5.1 | AG14: =(AE14+AF14)/2 -> 2.65 | AH14: =SUMPRODUCT(($G$8:$G$694=X14)*($I$8:$I$694^AG14))-Y14 -> -0.31101962 | AI14: =IF(AH14>0,AG14,AE14) -> 0.2 | AJ14: =IF(AH14>0,AF14,AG14) -> 2.65 | AK14: =(AI14+AJ14)/2 -> 1.425 | AL14: =SUMPRODUCT(($G$8:$G$694=X14)*($I$8:$I$694^AK14))-Y14 -> -0.099918724 | AM14: =IF(AL14>0,AK14,AI14) -> 0.2 | AN14: =IF(AL14>0,AJ14,AK14) -> 1.425 | AO14: =(AM14+AN14)/2 -> 0.8125 | AP14: =SUMPRODUCT(($G$8:$G$694=X14)*($I$8:$I$694^AO14))-Y14 -> 0.2918633 | AQ14: =IF(AP14>0,AO14,AM14) -> 0.8125 | AR14: =IF(AP14>0,AN14,AO14) -> 1.425 | AS14: =(AQ14+AR14)/2 -> 1.11875 | AT14: =SUMPRODUCT(($G$8:$G$694=X14)*($I$8:$I$694^AS14))-Y14 -> 0.033819103 | AU14: =IF(AT14>0,AS14,AQ14) -> 1.11875 | AV14: =IF(AT14>0,AR14,AS14) -> 1.425 | AW14: =(AU14+AV14)/2 -> 1.271875 | AX14: =SUMPRODUCT(($G$8:$G$694=X14)*($I$8:$I$694^AW14))-Y14 -> -0.042800202 | AY14: =IF(AX14>0,AW14,AU14) -> 1.11875 | AZ14: =IF(AX14>0,AV14,AW14) -> 1.271875 | BA14: =(AY14+AZ14)/2 -> 1.1953125 | BB14: =SUMPRODUCT(($G$8:$G$694=X14)*($I$8:$I$694^BA14))-Y14 -> -0.0074543924 | BC14: =IF(BB14>0,BA14,AY14) -> 1.11875 | BD14: =IF(BB14>0,AZ14,BA14) -> 1.1953125 | BE14: =(BC14+BD14)/2 -> 1.1570312 | BF14: =SUMPRODUCT(($G$8:$G$694=X14)*($I$8:$I$694^BE14))-Y14 -> 0.012362066 | BG14: =IF(BF14>0,BE14,BC14) -> 1.1570312 | BH14: =IF(BF14>0,BD14,BE14) -> 1.1953125 | BI14: =(BG14+BH14)/2 -> 1.1761719 | BJ14: =SUMPRODUCT(($G$8:$G$694=X14)*($I$8:$I$694^BI14))-Y14 -> 0.0022593812 | BK14: =IF(BJ14>0,BI14,BG14) -> 1.1761719 | BL14: =IF(BJ14>0,BH14,BI14) -> 1.1953125 | BM14: =(BK14+BL14)/2 -> 1.1857422 | BN14: =SUMPRODUCT(($G$8:$G$694=X14)*($I$8:$I$694^BM14))-Y14 -> -0.002644857 | BO14: =IF(BN14>0,BM14,BK14) -> 1.1761719 | BP14: =IF(BN14>0,BL14,BM14) -> 1.1857422 | BQ14: =(BO14+BP14)/2 -> 1.180957 | BR14: =SUMPRODUCT(($G$8:$G$694=X14)*($I$8:$I$694^BQ14))-Y14 -> -0.00020473074 | BS14: =IF(BR14>0,BQ14,BO14) -> 1.1761719 | BT14: =IF(BR14>0,BP14,BQ14) -> 1.180957 | BU14: =(BS14+BT14)/2 -> 1.1785645 | BV14: =SUMPRODUCT(($G$8:$G$694=X14)*($I$8:$I$694^BU14))-Y14 -> 0.0010243074 | BW14: =IF(BV14>0,BU14,BS14) -> 1.1785645 | BX14: =IF(BV14>0,BT14,BU14) -> 1.180957 | BY14: =(BW14+BX14)/2 -> 1.1797607 | BZ14: =SUMPRODUCT(($G$8:$G$694=X14)*($I$8:$I$694^BY14))-Y14 -> 0.00040903634 | CA14: =IF(BZ14>0,BY14,BW14) -> 1.1797607 | CB14: =IF(BZ14>0,BX14,BY14) -> 1.180957 | CC14: =(CA14+CB14)/2 -> 1.1803589 | CD14: =SUMPRODUCT(($G$8:$G$694=X14)*($I$8:$I$694^CC14))-Y14 -> 0.00010196511 | CE14: =IF(CD14>0,CC14,CA14) -> 1.1803589 | CF14: =IF(CD14>0,CB14,CC14) -> 1.180957 | CG14: =(CE14+CF14)/2 -> 1.180658 | CH14: =SUMPRODUCT(($G$8:$G$694=X14)*($I$8:$I$694^CG14))-Y14 -> -5.14297e-05 | CI14: =IF(CH14>0,CG14,CE14) -> 1.1803589 | CJ14: =IF(CH14>0,CF14,CG14) -> 1.180658 | CK14: =(CI14+CJ14)/2 -> 1.1805084 | CL14: =SUMPRODUCT(($G$8:$G$694=X14)*($I$8:$I$694^CK14))-Y14 -> 2.5255978e-05 | CM14: =IF(CL14>0,CK14,CI14) -> 1.1805084 | CN14: =IF(CL14>0,CJ14,CK14) -> 1.180658 | CO14: =(CM14+CN14)/2 -> 1.1805832 | CP14: =SUMPRODUCT(($G$8:$G$694=X14)*($I$8:$I$694^CO14))-Y14 -> -1.3089792e-05 | CQ14: =IF(CP14>0,CO14,CM14) -> 1.1805084 | CR14: =IF(CP14>0,CN14,CO14) -> 1.1805832 | CS14: =(CQ14+CR14)/2 -> 1.1805458 | CT14: =SUMPRODUCT(($G$8:$G$694=X14)*($I$8:$I$694^CS14))-Y14 -> 6.0823601e-06 | CU14: =IF(CT14>0,CS14,CQ14) -> 1.1805458 | CV14: =IF(CT14>0,CR14,CS14) -> 1.1805832 | CW14: =(CU14+CV14)/2 -> 1.1805645 | CX14: =SUMPRODUCT(($G$8:$G$694=X14)*($I$8:$I$694^CW14))-Y14 -> -3.5038992e-06 | CY14: =IF(CX14>0,CW14,CU14) -> 1.1805458 | CZ14: =IF(CX14>0,CV14,CW14) -> 1.1805645 | DA14: =(CY14+CZ14)/2 -> 1.1805552 | DB14: =SUMPRODUCT(($G$8:$G$694=X14)*($I$8:$I$694^DA14))-Y14 -> 1.2891846e-06 | DC14: =IF(DB14>0,DA14,CY14) -> 1.1805552 | DD14: =IF(DB14>0,CZ14,DA14) -> 1.1805645 | DE14: =(DC14+DD14)/2 -> 1.1805598 | DF14: =SUMPRODUCT(($G$8:$G$694=X14)*($I$8:$I$694^DE14))-Y14 -> -1.1073688e-06 | DG14: =IF(DF14>0,DE14,DC14) -> 1.1805552 | DH14: =IF(DF14>0,DD14,DE14) -> 1.1805598 | DI14: =(DG14+DH14)/2 -> 1.1805575 | DJ14: =SUMPRODUCT(($G$8:$G$694=X14)*($I$8:$I$694^DI14))-Y14 -> 9.0905072e-08 | DK14: =IF(DJ14>0,DI14,DG14) -> 1.1805575 | DL14: =IF(DJ14>0,DH14,DI14) -> 1.1805598 | DM14: =(DK14+DL14)/2 -> 1.1805587 | DN14: =SUMPRODUCT(($G$8:$G$694=X14)*($I$8:$I$694^DM14))-Y14 -> -5.0823255e-07 | DO14: =IF(DN14>0,DM14,DK14) -> 1.1805575 | DP14: =IF(DN14>0,DL14,DM14) -> 1.1805587 | DQ14: =(DO14+DP14)/2 -> 1.1805581 | DR14: =SUMPRODUCT(($G$8:$G$694=X14)*($I$8:$I$694^DQ14))-Y14 -> -2.0866392e-07 | DS14: =IF(DR14>0,DQ14,DO14) -> 1.1805575 | DT14: =IF(DR14>0,DP14,DQ14) -> 1.1805581 | DU14: =(DS14+DT14)/2 -> 1.1805578 | DV14: =SUMPRODUCT(($G$8:$G$694=X14)*($I$8:$I$694^DU14))-Y14 -> -5.8879469e-08 | DW14: =IF(DV14>0,DU14,DS14) -> 1.1805575 | DX14: =IF(DV14>0,DT14,DU14) -> 1.1805578 | DY14: =(DW14+DX14)/2 -> 1.1805576 | DZ14: =SUMPRODUCT(($G$8:$G$694=X14)*($I$8:$I$694^DY14))-Y14 -> 1.6012791e-08 | EA14: =IF(DZ14>0,DY14,DW14) -> 1.1805576 | EB14: =IF(DZ14>0,DX14,DY14) -> 1.1805578 | EC14: =(EA14+EB14)/2 -> 1.1805577 | ED14: =SUMPRODUCT(($G$8:$G$694=X14)*($I$8:$I$694^EC14))-Y14 -> -2.1433342e-08 | EE14: =IF(ED14>0,EC14,EA14) -> 1.1805576 | EF14: =IF(ED14>0,EB14,EC14) -> 1.1805577 | EG14: =(EE14+EF14)/2 -> 1.1805577 | EH14: =SUMPRODUCT(($G$8:$G$694=X14)*($I$8:$I$694^EG14))-Y14 -> -2.7102763e-09 | EI14: =IF(EH14>0,EG14,EE14) -> 1.1805576 | EJ14: =IF(EH14>0,EF14,EG14) -> 1.1805577 | EK14: =(EI14+EJ14)/2 -> 1.1805577 | EL14: =SUMPRODUCT(($G$8:$G$694=X14)*($I$8:$I$694^EK14))-Y14 -> 6.6512571e-09 | EM14: =IF(EL14>0,EK14,EI14) -> 1.1805577 | EN14: =IF(EL14>0,EJ14,EK14) -> 1.1805577 | EO14: =(EM14+EN14)/2 -> 1.1805577 | EP14: =SUMPRODUCT(($G$8:$G$694=X14)*($I$8:$I$694^EO14))-Y14 -> 1.9704902e-09 | EQ14: =IF(EP14>0,EO14,EM14) -> 1.1805577 | ER14: =IF(EP14>0,EN14,EO14) -> 1.1805577 | ES14: =(EQ14+ER14)/2 -> 1.1805577 | ET14: =SUMPRODUCT(($G$8:$G$694=X14)*($I$8:$I$694^ES14))-Y14 -> -3.6989289e-10 | EU14: =IF(ET14>0,ES14,EQ14) -> 1.1805577 | EV14: =IF(ET14>0,ER14,ES14) -> 1.1805577 | EW14: =(EU14+EV14)/2 -> 1.1805577 | EX14: =SUMPRODUCT(($G$8:$G$694=X14)*($I$8:$I$694^EW14))-Y14 -> 8.0029849e-10 | EY14: =IF(EX14>0,EW14,EU14) -> 1.1805577 | EZ14: =IF(EX14>0,EV14,EW14) -> 1.1805577 | FA14: 1e-06 | FB14: 0.9999 | FC14: =(FA14+FB14)/2 -> 0.4999505 | FD14: =(SUMPRODUCT(($G$8:$G$694=X14)*SQRT(FC14^2+4*(1-FC14)*$I$8:$I$694^2/Z14))-COUNTIF($G$8:$G$694,X14)*FC14)/(2*(1-FC14))-1 -> -0.19785904 | FE14: =IF(FD14>0,FC14,FA14) -> 1e-06 | FF14: =IF(FD14>0,FB14,FC14) -> 0.4999505 | FG14: =(FE14+FF14)/2 -> 0.24997575 | FH14: =(SUMPRODUCT(($G$8:$G$694=X14)*SQRT(FG14^2+4*(1-FG14)*$I$8:$I$694^2/Z14))-COUNTIF($G$8:$G$694,X14)*FG14)/(2*(1-FG14))-1 -> -0.13414292 | FI14: =IF(FH14>0,FG14,FE14) -> 1e-06 | FJ14: =IF(FH14>0,FF14,FG14) -> 0.24997575 | FK14: =(FI14+FJ14)/2 -> 0.12498837 | FL14: =(SUMPRODUCT(($G$8:$G$694=X14)*SQRT(FK14^2+4*(1-FK14)*$I$8:$I$694^2/Z14))-COUNTIF($G$8:$G$694,X14)*FK14)/(2*(1-FK14))-1 -> -0.077577308 | FM14: =IF(FL14>0,FK14,FI14) -> 1e-06 | FN14: =IF(FL14>0,FJ14,FK14) -> 0.12498837 | FO14: =(FM14+FN14)/2 -> 0.062494687 | FP14: =(SUMPRODUCT(($G$8:$G$694=X14)*SQRT(FO14^2+4*(1-FO14)*$I$8:$I$694^2/Z14))-COUNTIF($G$8:$G$694,X14)*FO14)/(2*(1-FO14))-1 -> -0.030029939 | FQ14: =IF(FP14>0,FO14,FM14) -> 1e-06 | FR14: =IF(FP14>0,FN14,FO14) -> 0.062494687 | FS14: =(FQ14+FR14)/2 -> 0.031247844 | FT14: =(SUMPRODUCT(($G$8:$G$694=X14)*SQRT(FS14^2+4*(1-FS14)*$I$8:$I$694^2/Z14))-COUNTIF($G$8:$G$694,X14)*FS14)/(2*(1-FS14))-1 -> 0.0045236782 | FU14: =IF(FT14>0,FS14,FQ14) -> 0.031247844 | FV14: =IF(FT14>0,FR14,FS14) -> 0.062494687 | FW14: =(FU14+FV14)/2 -> 0.046871266 | FX14: =(SUMPRODUCT(($G$8:$G$694=X14)*SQRT(FW14^2+4*(1-FW14)*$I$8:$I$694^2/Z14))-COUNTIF($G$8:$G$694,X14)*FW14)/(2*(1-FW14))-1 -> -0.014118763 | FY14: =IF(FX14>0,FW14,FU14) -> 0.031247844 | FZ14: =IF(FX14>0,FV14,FW14) -> 0.046871266 | GA14: =(FY14+FZ14)/2 -> 0.039059555 | GB14: =(SUMPRODUCT(($G$8:$G$694=X14)*SQRT(GA14^2+4*(1-GA14)*$I$8:$I$694^2/Z14))-COUNTIF($G$8:$G$694,X14)*GA14)/(2*(1-GA14))-1 -> -0.0052020471 | GC14: =IF(GB14>0,GA14,FY14) -> 0.031247844 | GD14: =IF(GB14>0,FZ14,GA14) -> 0.039059555 | GE14: =(GC14+GD14)/2 -> 0.035153699 | GF14: =(SUMPRODUCT(($G$8:$G$694=X14)*SQRT(GE14^2+4*(1-GE14)*$I$8:$I$694^2/Z14))-COUNTIF($G$8:$G$694,X14)*GE14)/(2*(1-GE14))-1 -> -0.00044991887 | GG14: =IF(GF14>0,GE14,GC14) -> 0.031247844 | GH14: =IF(GF14>0,GD14,GE14) -> 0.035153699 | GI14: =(GG14+GH14)/2 -> 0.033200771 | GJ14: =(SUMPRODUCT(($G$8:$G$694=X14)*SQRT(GI14^2+4*(1-GI14)*$I$8:$I$694^2/Z14))-COUNTIF($G$8:$G$694,X14)*GI14)/(2*(1-GI14))-1 -> 0.0020078853 | GK14: =IF(GJ14>0,GI14,GG14) -> 0.033200771 | GL14: =IF(GJ14>0,GH14,GI14) -> 0.035153699 | GM14: =(GK14+GL14)/2 -> 0.034177235 | GN14: =(SUMPRODUCT(($G$8:$G$694=X14)*SQRT(GM14^2+4*(1-GM14)*$I$8:$I$694^2/Z14))-COUNTIF($G$8:$G$694,X14)*GM14)/(2*(1-GM14))-1 -> 0.00077190315 | GO14: =IF(GN14>0,GM14,GK14) -> 0.034177235 | GP14: =IF(GN14>0,GL14,GM14) -> 0.035153699 | GQ14: =(GO14+GP14)/2 -> 0.034665467 | GR14: =(SUMPRODUCT(($G$8:$G$694=X14)*SQRT(GQ14^2+4*(1-GQ14)*$I$8:$I$694^2/Z14))-COUNTIF($G$8:$G$694,X14)*GQ14)/(2*(1-GQ14))-1 -> 0.00015924279 | GS14: =IF(GR14>0,GQ14,GO14) -> 0.034665467 | GT14: =IF(GR14>0,GP14,GQ14) -> 0.035153699 | GU14: =(GS14+GT14)/2 -> 0.034909583 | GV14: =(SUMPRODUCT(($G$8:$G$694=X14)*SQRT(GU14^2+4*(1-GU14)*$I$8:$I$694^2/Z14))-COUNTIF($G$8:$G$694,X14)*GU14)/(2*(1-GU14))-1 -> -0.00014577282 | GW14: =IF(GV14>0,GU14,GS14) -> 0.034665467 | GX14: =IF(GV14>0,GT14,GU14) -> 0.034909583 | GY14: =(GW14+GX14)/2 -> 0.034787525 | GZ14: =(SUMPRODUCT(($G$8:$G$694=X14)*SQRT(GY14^2+4*(1-GY14)*$I$8:$I$694^2/Z14))-COUNTIF($G$8:$G$694,X14)*GY14)/(2*(1-GY14))-1 -> 6.6259722e-06 | HA14: =IF(GZ14>0,GY14,GW14) -> 0.034787525 | HB14: =IF(GZ14>0,GX14,GY14) -> 0.034909583 | HC14: =(HA14+HB14)/2 -> 0.034848554 | HD14: =(SUMPRODUCT(($G$8:$G$694=X14)*SQRT(HC14^2+4*(1-HC14)*$I$8:$I$694^2/Z14))-COUNTIF($G$8:$G$694,X14)*HC14)/(2*(1-HC14))-1 -> -6.9600637e-05 | HE14: =IF(HD14>0,HC14,HA14) -> 0.034787525 | HF14: =IF(HD14>0,HB14,HC14) -> 0.034848554 | HG14: =(HE14+HF14)/2 -> 0.03481804 | HH14: =(SUMPRODUCT(($G$8:$G$694=X14)*SQRT(HG14^2+4*(1-HG14)*$I$8:$I$694^2/Z14))-COUNTIF($G$8:$G$694,X14)*HG14)/(2*(1-HG14))-1 -> -3.1494141e-05 | HI14: =IF(HH14>0,HG14,HE14) -> 0.034787525 | HJ14: =IF(HH14>0,HF14,HG14) -> 0.03481804 | HK14: =(HI14+HJ14)/2 -> 0.034802783 | HL14: =(SUMPRODUCT(($G$8:$G$694=X14)*SQRT(HK14^2+4*(1-HK14)*$I$8:$I$694^2/Z14))-COUNTIF($G$8:$G$694,X14)*HK14)/(2*(1-HK14))-1 -> -1.2435787e-05 | HM14: =IF(HL14>0,HK14,HI14) -> 0.034787525 | HN14: =IF(HL14>0,HJ14,HK14) -> 0.034802783 | HO14: =(HM14+HN14)/2 -> 0.034795154 | HP14: =(SUMPRODUCT(($G$8:$G$694=X14)*SQRT(HO14^2+4*(1-HO14)*$I$8:$I$694^2/Z14))-COUNTIF($G$8:$G$694,X14)*HO14)/(2*(1-HO14))-1 -> -2.9053331e-06 | HQ14: =IF(HP14>0,HO14,HM14) -> 0.034787525 | HR14: =IF(HP14>0,HN14,HO14) -> 0.034795154 | HS14: =(HQ14+HR14)/2 -> 0.03479134 | HT14: =(SUMPRODUCT(($G$8:$G$694=X14)*SQRT(HS14^2+4*(1-HS14)*$I$8:$I$694^2/Z14))-COUNTIF($G$8:$G$694,X14)*HS14)/(2*(1-HS14))-1 -> 1.8602131e-06 | HU14: =IF(HT14>0,HS14,HQ14) -> 0.03479134 | HV14: =IF(HT14>0,HR14,HS14) -> 0.034795154 | HW14: =(HU14+HV14)/2 -> 0.034793247 | HX14: =(SUMPRODUCT(($G$8:$G$694=X14)*SQRT(HW14^2+4*(1-HW14)*$I$8:$I$694^2/Z14))-COUNTIF($G$8:$G$694,X14)*HW14)/(2*(1-HW14))-1 -> -5.2258662e-07 | HY14: =IF(HX14>0,HW14,HU14) -> 0.03479134 | HZ14: =IF(HX14>0,HV14,HW14) -> 0.034793247 | IA14: =(HY14+HZ14)/2 -> 0.034792293 | IB14: =(SUMPRODUCT(($G$8:$G$694=X14)*SQRT(IA14^2+4*(1-IA14)*$I$8:$I$694^2/Z14))-COUNTIF($G$8:$G$694,X14)*IA14)/(2*(1-IA14))-1 -> 6.6880659e-07 | IC14: =IF(IB14>0,IA14,HY14) -> 0.034792293 | ID14: =IF(IB14>0,HZ14,IA14) -> 0.034793247 | IE14: =(IC14+ID14)/2 -> 0.03479277 | IF14: =(SUMPRODUCT(($G$8:$G$694=X14)*SQRT(IE14^2+4*(1-IE14)*$I$8:$I$694^2/Z14))-COUNTIF($G$8:$G$694,X14)*IE14)/(2*(1-IE14))-1 -> 7.3108323e-08 | IG14: =IF(IF14>0,IE14,IC14) -> 0.03479277 | IH14: =IF(IF14>0,ID14,IE14) -> 0.034793247 | II14: =(IG14+IH14)/2 -> 0.034793008 | IJ14: =(SUMPRODUCT(($G$8:$G$694=X14)*SQRT(II14^2+4*(1-II14)*$I$8:$I$694^2/Z14))-COUNTIF($G$8:$G$694,X14)*II14)/(2*(1-II14))-1 -> -2.2473956e-07 | IK14: =IF(IJ14>0,II14,IG14) -> 0.03479277 | IL14: =IF(IJ14>0,IH14,II14) -> 0.034793008 | IM14: =(IK14+IL14)/2 -> 0.034792889 | IN14: =(SUMPRODUCT(($G$8:$G$694=X14)*SQRT(IM14^2+4*(1-IM14)*$I$8:$I$694^2/Z14))-COUNTIF($G$8:$G$694,X14)*IM14)/(2*(1-IM14))-1 -> -7.5815725e-08 | IO14: =IF(IN14>0,IM14,IK14) -> 0.03479277 | IP14: =IF(IN14>0,IL14,IM14) -> 0.034792889 | IQ14: =(IO14+IP14)/2 -> 0.03479283 | IR14: =(SUMPRODUCT(($G$8:$G$694=X14)*SQRT(IQ14^2+4*(1-IQ14)*$I$8:$I$694^2/Z14))-COUNTIF($G$8:$G$694,X14)*IQ14)/(2*(1-IQ14))-1 -> -1.3537267e-09 | IS14: =IF(IR14>0,IQ14,IO14) -> 0.03479277 | IT14: =IF(IR14>0,IP14,IQ14) -> 0.03479283 | IU14: =(IS14+IT14)/2 -> 0.0347928 | IV14: =(SUMPRODUCT(($G$8:$G$694=X14)*SQRT(IU14^2+4*(1-IU14)*$I$8:$I$694^2/Z14))-COUNTIF($G$8:$G$694,X14)*IU14)/(2*(1-IU14))-1 -> 3.5877292e-08 | IW14: =IF(IV14>0,IU14,IS14) -> 0.0347928 | IX14: =IF(IV14>0,IT14,IU14) -> 0.03479283 | IY14: =(IW14+IX14)/2 -> 0.034792815 | IZ14: =(SUMPRODUCT(($G$8:$G$694=X14)*SQRT(IY14^2+4*(1-IY14)*$I$8:$I$694^2/Z14))-COUNTIF($G$8:$G$694,X14)*IY14)/(2*(1-IY14))-1 -> 1.7261781e-08 | JA14: =IF(IZ14>0,IY14,IW14) -> 0.034792815 | JB14: =IF(IZ14>0,IX14,IY14) -> 0.03479283 | JC14: =(JA14+JB14)/2 -> 0.034792822 | JD14: =(SUMPRODUCT(($G$8:$G$694=X14)*SQRT(JC14^2+4*(1-JC14)*$I$8:$I$694^2/Z14))-COUNTIF($G$8:$G$694,X14)*JC14)/(2*(1-JC14))-1 -> 7.9540265e-09 | JE14: =IF(JD14>0,JC14,JA14) -> 0.034792822 | JF14: =IF(JD14>0,JB14,JC14) -> 0.03479283 | JG14: =(JE14+JF14)/2 -> 0.034792826 | JH14: =(SUMPRODUCT(($G$8:$G$694=X14)*SQRT(JG14^2+4*(1-JG14)*$I$8:$I$694^2/Z14))-COUNTIF($G$8:$G$694,X14)*JG14)/(2*(1-JG14))-1 -> 3.3001499e-09 | JI14: =IF(JH14>0,JG14,JE14) -> 0.034792826 | JJ14: =IF(JH14>0,JF14,JG14) -> 0.03479283 | JK14: =(JI14+JJ14)/2 -> 0.034792828 | JL14: =(SUMPRODUCT(($G$8:$G$694=X14)*SQRT(JK14^2+4*(1-JK14)*$I$8:$I$694^2/Z14))-COUNTIF($G$8:$G$694,X14)*JK14)/(2*(1-JK14))-1 -> 9.7321129e-10 | JM14: =IF(JL14>0,JK14,JI14) -> 0.034792828 | JN14: =IF(JL14>0,JJ14,JK14) -> 0.03479283 | JO14: =(JM14+JN14)/2 -> 0.034792829 | JP14: =(SUMPRODUCT(($G$8:$G$694=X14)*SQRT(JO14^2+4*(1-JO14)*$I$8:$I$694^2/Z14))-COUNTIF($G$8:$G$694,X14)*JO14)/(2*(1-JO14))-1 -> -1.9025759e-10 | JQ14: =IF(JP14>0,JO14,JM14) -> 0.034792828 | JR14: =IF(JP14>0,JN14,JO14) -> 0.034792829 | JS14: =(JQ14+JR14)/2 -> 0.034792828 | JT14: =(SUMPRODUCT(($G$8:$G$694=X14)*SQRT(JS14^2+4*(1-JS14)*$I$8:$I$694^2/Z14))-COUNTIF($G$8:$G$694,X14)*JS14)/(2*(1-JS14))-1 -> 3.9147685e-10 | JU14: =IF(JT14>0,JS14,JQ14) -> 0.034792828 | JV14: =IF(JT14>0,JR14,JS14) -> 0.034792829 | JW14: =(JU14+JV14)/2 -> 0.034792828 | JX14: =(SUMPRODUCT(($G$8:$G$694=X14)*SQRT(JW14^2+4*(1-JW14)*$I$8:$I$694^2/Z14))-COUNTIF($G$8:$G$694,X14)*JW14)/(2*(1-JW14))-1 -> 1.0060974e-10 | JY14: =IF(JX14>0,JW14,JU14) -> 0.034792828 | JZ14: =IF(JX14>0,JV14,JW14) -> 0.034792829 | KA14: =(EY14+EZ14)/2 -> 1.1805577 | KB14: =(JY14+JZ14)/2 -> 0.034792828
A15: =Odds_Input!A15 -> 7 | B15: =Odds_Input!B15 -> TITLE | C15: =Odds_Input!C15 -> Denver Nuggets | D15: =Odds_Input!D15 -> YES | E15: =Odds_Input!E15 -> - | F15: =Odds_Input!F15 -> 2700 | G15: =IF(OR(B15="WINS",B15="PLAYOFFS"),B15&"|"&C15&IF(B15="WINS","|"&TEXT(E15,"0.0"),""),B15) -> TITLE | H15: =IF(F15>0,1+F15/100,1+100/ABS(F15)) -> 28 | I15: =1/H15 -> 0.035714286 | J15: =IF(LEFT(B15,6)="PLAYIN",A_playin_slots,1) -> 1 | K15: =COUNTIF($G$8:$G$694,G15) -> 30 | L15: =SUMIF($G$8:$G$694,G15,$I$8:$I$694) -> 1.2525652 | M15: =L15/J15-1 -> 0.25256519 | N15: =I15*J15/L15 -> 0.028512916 | O15: =I15^R15 -> 0.025660299 | P15: =IF(J15<>1,O15,IF(L15<=1,I15/L15,(SQRT(S15^2+4*(1-S15)*I15^2/L15)-S15)/(2*(1-S15)))) -> 0.026984058 | Q15: =IF(A_devig="Multiplicative",N15,IF(A_devig="Power",O15,P15)) -> 0.026984058 | R15: =INDEX($KA$8:$KA$96,MATCH(G15,$X$8:$X$96,0)) -> 1.0992153 | S15: =INDEX($KB$8:$KB$96,MATCH(G15,$X$8:$X$96,0)) -> 0.011051948 | X15: DIV_PACIFIC | Y15: =IF(LEFT(X15,6)="PLAYIN",A_playin_slots,1) -> 1 | Z15: =SUMIF($G$8:$G$694,X15,$I$8:$I$694) -> 1.118322 | AA15: 0.2 | AB15: 10 | AC15: =(AA15+AB15)/2 -> 5.1 | AD15: =SUMPRODUCT(($G$8:$G$694=X15)*($I$8:$I$694^AC15))-Y15 -> -0.89935702 | AE15: =IF(AD15>0,AC15,AA15) -> 0.2 | AF15: =IF(AD15>0,AB15,AC15) -> 5.1 | AG15: =(AE15+AF15)/2 -> 2.65 | AH15: =SUMPRODUCT(($G$8:$G$694=X15)*($I$8:$I$694^AG15))-Y15 -> -0.66225359 | AI15: =IF(AH15>0,AG15,AE15) -> 0.2 | AJ15: =IF(AH15>0,AF15,AG15) -> 2.65 | AK15: =(AI15+AJ15)/2 -> 1.425 | AL15: =SUMPRODUCT(($G$8:$G$694=X15)*($I$8:$I$694^AK15))-Y15 -> -0.23557945 | AM15: =IF(AL15>0,AK15,AI15) -> 0.2 | AN15: =IF(AL15>0,AJ15,AK15) -> 1.425 | AO15: =(AM15+AN15)/2 -> 0.8125 | AP15: =SUMPRODUCT(($G$8:$G$694=X15)*($I$8:$I$694^AO15))-Y15 -> 0.36141076 | AQ15: =IF(AP15>0,AO15,AM15) -> 0.8125 | AR15: =IF(AP15>0,AN15,AO15) -> 1.425 | AS15: =(AQ15+AR15)/2 -> 1.11875 | AT15: =SUMPRODUCT(($G$8:$G$694=X15)*($I$8:$I$694^AS15))-Y15 -> -0.0024441806 | AU15: =IF(AT15>0,AS15,AQ15) -> 0.8125 | AV15: =IF(AT15>0,AR15,AS15) -> 1.11875 | AW15: =(AU15+AV15)/2 -> 0.965625 | AX15: =SUMPRODUCT(($G$8:$G$694=X15)*($I$8:$I$694^AW15))-Y15 -> 0.15753658 | AY15: =IF(AX15>0,AW15,AU15) -> 0.965625 | AZ15: =IF(AX15>0,AV15,AW15) -> 1.11875 | BA15: =(AY15+AZ15)/2 -> 1.0421875 | BB15: =SUMPRODUCT(($G$8:$G$694=X15)*($I$8:$I$694^BA15))-Y15 -> 0.072947826 | BC15: =IF(BB15>0,BA15,AY15) -> 1.0421875 | BD15: =IF(BB15>0,AZ15,BA15) -> 1.11875 | BE15: =(BC15+BD15)/2 -> 1.0804687 | BF15: =SUMPRODUCT(($G$8:$G$694=X15)*($I$8:$I$694^BE15))-Y15 -> 0.03419303 | BG15: =IF(BF15>0,BE15,BC15) -> 1.0804687 | BH15: =IF(BF15>0,BD15,BE15) -> 1.11875 | BI15: =(BG15+BH15)/2 -> 1.0996094 | BJ15: =SUMPRODUCT(($G$8:$G$694=X15)*($I$8:$I$694^BI15))-Y15 -> 0.015620054 | BK15: =IF(BJ15>0,BI15,BG15) -> 1.0996094 | BL15: =IF(BJ15>0,BH15,BI15) -> 1.11875 | BM15: =(BK15+BL15)/2 -> 1.1091797 | BN15: =SUMPRODUCT(($G$8:$G$694=X15)*($I$8:$I$694^BM15))-Y15 -> 0.0065255769 | BO15: =IF(BN15>0,BM15,BK15) -> 1.1091797 | BP15: =IF(BN15>0,BL15,BM15) -> 1.11875 | BQ15: =(BO15+BP15)/2 -> 1.1139648 | BR15: =SUMPRODUCT(($G$8:$G$694=X15)*($I$8:$I$694^BQ15))-Y15 -> 0.002025259 | BS15: =IF(BR15>0,BQ15,BO15) -> 1.1139648 | BT15: =IF(BR15>0,BP15,BQ15) -> 1.11875 | BU15: =(BS15+BT15)/2 -> 1.1163574 | BV15: =SUMPRODUCT(($G$8:$G$694=X15)*($I$8:$I$694^BU15))-Y15 -> -0.00021330198 | BW15: =IF(BV15>0,BU15,BS15) -> 1.1139648 | BX15: =IF(BV15>0,BT15,BU15) -> 1.1163574 | BY15: =(BW15+BX15)/2 -> 1.1151611 | BZ15: =SUMPRODUCT(($G$8:$G$694=X15)*($I$8:$I$694^BY15))-Y15 -> 0.00090501588 | CA15: =IF(BZ15>0,BY15,BW15) -> 1.1151611 | CB15: =IF(BZ15>0,BX15,BY15) -> 1.1163574 | CC15: =(CA15+CB15)/2 -> 1.1157593 | CD15: =SUMPRODUCT(($G$8:$G$694=X15)*($I$8:$I$694^CC15))-Y15 -> 0.00034561659 | CE15: =IF(CD15>0,CC15,CA15) -> 1.1157593 | CF15: =IF(CD15>0,CB15,CC15) -> 1.1163574 | CG15: =(CE15+CF15)/2 -> 1.1160583 | CH15: =SUMPRODUCT(($G$8:$G$694=X15)*($I$8:$I$694^CG15))-Y15 -> 6.6097249e-05 | CI15: =IF(CH15>0,CG15,CE15) -> 1.1160583 | CJ15: =IF(CH15>0,CF15,CG15) -> 1.1163574 | CK15: =(CI15+CJ15)/2 -> 1.1162079 | CL15: =SUMPRODUCT(($G$8:$G$694=X15)*($I$8:$I$694^CK15))-Y15 -> -7.3617375e-05 | CM15: =IF(CL15>0,CK15,CI15) -> 1.1160583 | CN15: =IF(CL15>0,CJ15,CK15) -> 1.1162079 | CO15: =(CM15+CN15)/2 -> 1.1161331 | CP15: =SUMPRODUCT(($G$8:$G$694=X15)*($I$8:$I$694^CO15))-Y15 -> -3.7638161e-06 | CQ15: =IF(CP15>0,CO15,CM15) -> 1.1160583 | CR15: =IF(CP15>0,CN15,CO15) -> 1.1161331 | CS15: =(CQ15+CR15)/2 -> 1.1160957 | CT15: =SUMPRODUCT(($G$8:$G$694=X15)*($I$8:$I$694^CS15))-Y15 -> 3.1165778e-05 | CU15: =IF(CT15>0,CS15,CQ15) -> 1.1160957 | CV15: =IF(CT15>0,CR15,CS15) -> 1.1161331 | CW15: =(CU15+CV15)/2 -> 1.1161144 | CX15: =SUMPRODUCT(($G$8:$G$694=X15)*($I$8:$I$694^CW15))-Y15 -> 1.3700746e-05 | CY15: =IF(CX15>0,CW15,CU15) -> 1.1161144 | CZ15: =IF(CX15>0,CV15,CW15) -> 1.1161331 | DA15: =(CY15+CZ15)/2 -> 1.1161238 | DB15: =SUMPRODUCT(($G$8:$G$694=X15)*($I$8:$I$694^DA15))-Y15 -> 4.9684065e-06 | DC15: =IF(DB15>0,DA15,CY15) -> 1.1161238 | DD15: =IF(DB15>0,CZ15,DA15) -> 1.1161331 | DE15: =(DC15+DD15)/2 -> 1.1161284 | DF15: =SUMPRODUCT(($G$8:$G$694=X15)*($I$8:$I$694^DE15))-Y15 -> 6.0228054e-07 | DG15: =IF(DF15>0,DE15,DC15) -> 1.1161284 | DH15: =IF(DF15>0,DD15,DE15) -> 1.1161331 | DI15: =(DG15+DH15)/2 -> 1.1161308 | DJ15: =SUMPRODUCT(($G$8:$G$694=X15)*($I$8:$I$694^DI15))-Y15 -> -1.5807714e-06 | DK15: =IF(DJ15>0,DI15,DG15) -> 1.1161284 | DL15: =IF(DJ15>0,DH15,DI15) -> 1.1161308 | DM15: =(DK15+DL15)/2 -> 1.1161296 | DN15: =SUMPRODUCT(($G$8:$G$694=X15)*($I$8:$I$694^DM15))-Y15 -> -4.8924637e-07 | DO15: =IF(DN15>0,DM15,DK15) -> 1.1161284 | DP15: =IF(DN15>0,DL15,DM15) -> 1.1161296 | DQ15: =(DO15+DP15)/2 -> 1.116129 | DR15: =SUMPRODUCT(($G$8:$G$694=X15)*($I$8:$I$694^DQ15))-Y15 -> 5.6516855e-08 | DS15: =IF(DR15>0,DQ15,DO15) -> 1.116129 | DT15: =IF(DR15>0,DP15,DQ15) -> 1.1161296 | DU15: =(DS15+DT15)/2 -> 1.1161293 | DV15: =SUMPRODUCT(($G$8:$G$694=X15)*($I$8:$I$694^DU15))-Y15 -> -2.1636482e-07 | DW15: =IF(DV15>0,DU15,DS15) -> 1.116129 | DX15: =IF(DV15>0,DT15,DU15) -> 1.1161293 | DY15: =(DW15+DX15)/2 -> 1.1161292 | DZ15: =SUMPRODUCT(($G$8:$G$694=X15)*($I$8:$I$694^DY15))-Y15 -> -7.9923995e-08 | EA15: =IF(DZ15>0,DY15,DW15) -> 1.116129 | EB15: =IF(DZ15>0,DX15,DY15) -> 1.1161292 | EC15: =(EA15+EB15)/2 -> 1.1161291 | ED15: =SUMPRODUCT(($G$8:$G$694=X15)*($I$8:$I$694^EC15))-Y15 -> -1.1703574e-08 | EE15: =IF(ED15>0,EC15,EA15) -> 1.116129 | EF15: =IF(ED15>0,EB15,EC15) -> 1.1161291 | EG15: =(EE15+EF15)/2 -> 1.1161291 | EH15: =SUMPRODUCT(($G$8:$G$694=X15)*($I$8:$I$694^EG15))-Y15 -> 2.240664e-08 | EI15: =IF(EH15>0,EG15,EE15) -> 1.1161291 | EJ15: =IF(EH15>0,EF15,EG15) -> 1.1161291 | EK15: =(EI15+EJ15)/2 -> 1.1161291 | EL15: =SUMPRODUCT(($G$8:$G$694=X15)*($I$8:$I$694^EK15))-Y15 -> 5.3515328e-09 | EM15: =IF(EL15>0,EK15,EI15) -> 1.1161291 | EN15: =IF(EL15>0,EJ15,EK15) -> 1.1161291 | EO15: =(EM15+EN15)/2 -> 1.1161291 | EP15: =SUMPRODUCT(($G$8:$G$694=X15)*($I$8:$I$694^EO15))-Y15 -> -3.1760204e-09 | EQ15: =IF(EP15>0,EO15,EM15) -> 1.1161291 | ER15: =IF(EP15>0,EN15,EO15) -> 1.1161291 | ES15: =(EQ15+ER15)/2 -> 1.1161291 | ET15: =SUMPRODUCT(($G$8:$G$694=X15)*($I$8:$I$694^ES15))-Y15 -> 1.0877561e-09 | EU15: =IF(ET15>0,ES15,EQ15) -> 1.1161291 | EV15: =IF(ET15>0,ER15,ES15) -> 1.1161291 | EW15: =(EU15+EV15)/2 -> 1.1161291 | EX15: =SUMPRODUCT(($G$8:$G$694=X15)*($I$8:$I$694^EW15))-Y15 -> -1.0441321e-09 | EY15: =IF(EX15>0,EW15,EU15) -> 1.1161291 | EZ15: =IF(EX15>0,EV15,EW15) -> 1.1161291 | FA15: 1e-06 | FB15: 0.9999 | FC15: =(FA15+FB15)/2 -> 0.4999505 | FD15: =(SUMPRODUCT(($G$8:$G$694=X15)*SQRT(FC15^2+4*(1-FC15)*$I$8:$I$694^2/Z15))-COUNTIF($G$8:$G$694,X15)*FC15)/(2*(1-FC15))-1 -> -0.35210132 | FE15: =IF(FD15>0,FC15,FA15) -> 1e-06 | FF15: =IF(FD15>0,FB15,FC15) -> 0.4999505 | FG15: =(FE15+FF15)/2 -> 0.24997575 | FH15: =(SUMPRODUCT(($G$8:$G$694=X15)*SQRT(FG15^2+4*(1-FG15)*$I$8:$I$694^2/Z15))-COUNTIF($G$8:$G$694,X15)*FG15)/(2*(1-FG15))-1 -> -0.19848555 | FI15: =IF(FH15>0,FG15,FE15) -> 1e-06 | FJ15: =IF(FH15>0,FF15,FG15) -> 0.24997575 | FK15: =(FI15+FJ15)/2 -> 0.12498837 | FL15: =(SUMPRODUCT(($G$8:$G$694=X15)*SQRT(FK15^2+4*(1-FK15)*$I$8:$I$694^2/Z15))-COUNTIF($G$8:$G$694,X15)*FK15)/(2*(1-FK15))-1 -> -0.092926292 | FM15: =IF(FL15>0,FK15,FI15) -> 1e-06 | FN15: =IF(FL15>0,FJ15,FK15) -> 0.12498837 | FO15: =(FM15+FN15)/2 -> 0.062494687 | FP15: =(SUMPRODUCT(($G$8:$G$694=X15)*SQRT(FO15^2+4*(1-FO15)*$I$8:$I$694^2/Z15))-COUNTIF($G$8:$G$694,X15)*FO15)/(2*(1-FO15))-1 -> -0.028141441 | FQ15: =IF(FP15>0,FO15,FM15) -> 1e-06 | FR15: =IF(FP15>0,FN15,FO15) -> 0.062494687 | FS15: =(FQ15+FR15)/2 -> 0.031247844 | FT15: =(SUMPRODUCT(($G$8:$G$694=X15)*SQRT(FS15^2+4*(1-FS15)*$I$8:$I$694^2/Z15))-COUNTIF($G$8:$G$694,X15)*FS15)/(2*(1-FS15))-1 -> 0.0098980414 | FU15: =IF(FT15>0,FS15,FQ15) -> 0.031247844 | FV15: =IF(FT15>0,FR15,FS15) -> 0.062494687 | FW15: =(FU15+FV15)/2 -> 0.046871266 | FX15: =(SUMPRODUCT(($G$8:$G$694=X15)*SQRT(FW15^2+4*(1-FW15)*$I$8:$I$694^2/Z15))-COUNTIF($G$8:$G$694,X15)*FW15)/(2*(1-FW15))-1 -> -0.0097857063 | FY15: =IF(FX15>0,FW15,FU15) -> 0.031247844 | FZ15: =IF(FX15>0,FV15,FW15) -> 0.046871266 | GA15: =(FY15+FZ15)/2 -> 0.039059555 | GB15: =(SUMPRODUCT(($G$8:$G$694=X15)*SQRT(GA15^2+4*(1-GA15)*$I$8:$I$694^2/Z15))-COUNTIF($G$8:$G$694,X15)*GA15)/(2*(1-GA15))-1 -> -0.00013365994 | GC15: =IF(GB15>0,GA15,FY15) -> 0.031247844 | GD15: =IF(GB15>0,FZ15,GA15) -> 0.039059555 | GE15: =(GC15+GD15)/2 -> 0.035153699 | GF15: =(SUMPRODUCT(($G$8:$G$694=X15)*SQRT(GE15^2+4*(1-GE15)*$I$8:$I$694^2/Z15))-COUNTIF($G$8:$G$694,X15)*GE15)/(2*(1-GE15))-1 -> 0.0048308883 | GG15: =IF(GF15>0,GE15,GC15) -> 0.035153699 | GH15: =IF(GF15>0,GD15,GE15) -> 0.039059555 | GI15: =(GG15+GH15)/2 -> 0.037106627 | GJ15: =(SUMPRODUCT(($G$8:$G$694=X15)*SQRT(GI15^2+4*(1-GI15)*$I$8:$I$694^2/Z15))-COUNTIF($G$8:$G$694,X15)*GI15)/(2*(1-GI15))-1 -> 0.002336329 | GK15: =IF(GJ15>0,GI15,GG15) -> 0.037106627 | GL15: =IF(GJ15>0,GH15,GI15) -> 0.039059555 | GM15: =(GK15+GL15)/2 -> 0.038083091 | GN15: =(SUMPRODUCT(($G$8:$G$694=X15)*SQRT(GM15^2+4*(1-GM15)*$I$8:$I$694^2/Z15))-COUNTIF($G$8:$G$694,X15)*GM15)/(2*(1-GM15))-1 -> 0.0010983245 | GO15: =IF(GN15>0,GM15,GK15) -> 0.038083091 | GP15: =IF(GN15>0,GL15,GM15) -> 0.039059555 | GQ15: =(GO15+GP15)/2 -> 0.038571323 | GR15: =(SUMPRODUCT(($G$8:$G$694=X15)*SQRT(GQ15^2+4*(1-GQ15)*$I$8:$I$694^2/Z15))-COUNTIF($G$8:$G$694,X15)*GQ15)/(2*(1-GQ15))-1 -> 0.00048158713 | GS15: =IF(GR15>0,GQ15,GO15) -> 0.038571323 | GT15: =IF(GR15>0,GP15,GQ15) -> 0.039059555 | GU15: =(GS15+GT15)/2 -> 0.038815439 | GV15: =(SUMPRODUCT(($G$8:$G$694=X15)*SQRT(GU15^2+4*(1-GU15)*$I$8:$I$694^2/Z15))-COUNTIF($G$8:$G$694,X15)*GU15)/(2*(1-GU15))-1 -> 0.0001737782 | GW15: =IF(GV15>0,GU15,GS15) -> 0.038815439 | GX15: =IF(GV15>0,GT15,GU15) -> 0.039059555 | GY15: =(GW15+GX15)/2 -> 0.038937497 | GZ15: =(SUMPRODUCT(($G$8:$G$694=X15)*SQRT(GY15^2+4*(1-GY15)*$I$8:$I$694^2/Z15))-COUNTIF($G$8:$G$694,X15)*GY15)/(2*(1-GY15))-1 -> 2.001289e-05 | HA15: =IF(GZ15>0,GY15,GW15) -> 0.038937497 | HB15: =IF(GZ15>0,GX15,GY15) -> 0.039059555 | HC15: =(HA15+HB15)/2 -> 0.038998526 | HD15: =(SUMPRODUCT(($G$8:$G$694=X15)*SQRT(HC15^2+4*(1-HC15)*$I$8:$I$694^2/Z15))-COUNTIF($G$8:$G$694,X15)*HC15)/(2*(1-HC15))-1 -> -5.6835073e-05 | HE15: =IF(HD15>0,HC15,HA15) -> 0.038937497 | HF15: =IF(HD15>0,HB15,HC15) -> 0.038998526 | HG15: =(HE15+HF15)/2 -> 0.038968011 | HH15: =(SUMPRODUCT(($G$8:$G$694=X15)*SQRT(HG15^2+4*(1-HG15)*$I$8:$I$694^2/Z15))-COUNTIF($G$8:$G$694,X15)*HG15)/(2*(1-HG15))-1 -> -1.841398e-05 | HI15: =IF(HH15>0,HG15,HE15) -> 0.038937497 | HJ15: =IF(HH15>0,HF15,HG15) -> 0.038968011 | HK15: =(HI15+HJ15)/2 -> 0.038952754 | HL15: =(SUMPRODUCT(($G$8:$G$694=X15)*SQRT(HK15^2+4*(1-HK15)*$I$8:$I$694^2/Z15))-COUNTIF($G$8:$G$694,X15)*HK15)/(2*(1-HK15))-1 -> 7.9873286e-07 | HM15: =IF(HL15>0,HK15,HI15) -> 0.038952754 | HN15: =IF(HL15>0,HJ15,HK15) -> 0.038968011 | HO15: =(HM15+HN15)/2 -> 0.038960383 | HP15: =(SUMPRODUCT(($G$8:$G$694=X15)*SQRT(HO15^2+4*(1-HO15)*$I$8:$I$694^2/Z15))-COUNTIF($G$8:$G$694,X15)*HO15)/(2*(1-HO15))-1 -> -8.8078039e-06 | HQ15: =IF(HP15>0,HO15,HM15) -> 0.038952754 | HR15: =IF(HP15>0,HN15,HO15) -> 0.038960383 | HS15: =(HQ15+HR15)/2 -> 0.038956568 | HT15: =(SUMPRODUCT(($G$8:$G$694=X15)*SQRT(HS15^2+4*(1-HS15)*$I$8:$I$694^2/Z15))-COUNTIF($G$8:$G$694,X15)*HS15)/(2*(1-HS15))-1 -> -4.0045807e-06 | HU15: =IF(HT15>0,HS15,HQ15) -> 0.038952754 | HV15: =IF(HT15>0,HR15,HS15) -> 0.038956568 | HW15: =(HU15+HV15)/2 -> 0.038954661 | HX15: =(SUMPRODUCT(($G$8:$G$694=X15)*SQRT(HW15^2+4*(1-HW15)*$I$8:$I$694^2/Z15))-COUNTIF($G$8:$G$694,X15)*HW15)/(2*(1-HW15))-1 -> -1.6029352e-06 | HY15: =IF(HX15>0,HW15,HU15) -> 0.038952754 | HZ15: =IF(HX15>0,HV15,HW15) -> 0.038954661 | IA15: =(HY15+HZ15)/2 -> 0.038953708 | IB15: =(SUMPRODUCT(($G$8:$G$694=X15)*SQRT(IA15^2+4*(1-IA15)*$I$8:$I$694^2/Z15))-COUNTIF($G$8:$G$694,X15)*IA15)/(2*(1-IA15))-1 -> -4.0210399e-07 | IC15: =IF(IB15>0,IA15,HY15) -> 0.038952754 | ID15: =IF(IB15>0,HZ15,IA15) -> 0.038953708 | IE15: =(IC15+ID15)/2 -> 0.038953231 | IF15: =(SUMPRODUCT(($G$8:$G$694=X15)*SQRT(IE15^2+4*(1-IE15)*$I$8:$I$694^2/Z15))-COUNTIF($G$8:$G$694,X15)*IE15)/(2*(1-IE15))-1 -> 1.9831373e-07 | IG15: =IF(IF15>0,IE15,IC15) -> 0.038953231 | IH15: =IF(IF15>0,ID15,IE15) -> 0.038953708 | II15: =(IG15+IH15)/2 -> 0.038953469 | IJ15: =(SUMPRODUCT(($G$8:$G$694=X15)*SQRT(II15^2+4*(1-II15)*$I$8:$I$694^2/Z15))-COUNTIF($G$8:$G$694,X15)*II15)/(2*(1-II15))-1 -> -1.018953e-07 | IK15: =IF(IJ15>0,II15,IG15) -> 0.038953231 | IL15: =IF(IJ15>0,IH15,II15) -> 0.038953469 | IM15: =(IK15+IL15)/2 -> 0.03895335 | IN15: =(SUMPRODUCT(($G$8:$G$694=X15)*SQRT(IM15^2+4*(1-IM15)*$I$8:$I$694^2/Z15))-COUNTIF($G$8:$G$694,X15)*IM15)/(2*(1-IM15))-1 -> 4.8209168e-08 | IO15: =IF(IN15>0,IM15,IK15) -> 0.03895335 | IP15: =IF(IN15>0,IL15,IM15) -> 0.038953469 | IQ15: =(IO15+IP15)/2 -> 0.03895341 | IR15: =(SUMPRODUCT(($G$8:$G$694=X15)*SQRT(IQ15^2+4*(1-IQ15)*$I$8:$I$694^2/Z15))-COUNTIF($G$8:$G$694,X15)*IQ15)/(2*(1-IQ15))-1 -> -2.6843079e-08 | IS15: =IF(IR15>0,IQ15,IO15) -> 0.03895335 | IT15: =IF(IR15>0,IP15,IQ15) -> 0.03895341 | IU15: =(IS15+IT15)/2 -> 0.03895338 | IV15: =(SUMPRODUCT(($G$8:$G$694=X15)*SQRT(IU15^2+4*(1-IU15)*$I$8:$I$694^2/Z15))-COUNTIF($G$8:$G$694,X15)*IU15)/(2*(1-IU15))-1 -> 1.0683042e-08 | IW15: =IF(IV15>0,IU15,IS15) -> 0.03895338 | IX15: =IF(IV15>0,IT15,IU15) -> 0.03895341 | IY15: =(IW15+IX15)/2 -> 0.038953395 | IZ15: =(SUMPRODUCT(($G$8:$G$694=X15)*SQRT(IY15^2+4*(1-IY15)*$I$8:$I$694^2/Z15))-COUNTIF($G$8:$G$694,X15)*IY15)/(2*(1-IY15))-1 -> -8.0800195e-09 | JA15: =IF(IZ15>0,IY15,IW15) -> 0.03895338 | JB15: =IF(IZ15>0,IX15,IY15) -> 0.038953395 | JC15: =(JA15+JB15)/2 -> 0.038953387 | JD15: =(SUMPRODUCT(($G$8:$G$694=X15)*SQRT(JC15^2+4*(1-JC15)*$I$8:$I$694^2/Z15))-COUNTIF($G$8:$G$694,X15)*JC15)/(2*(1-JC15))-1 -> 1.3015109e-09 | JE15: =IF(JD15>0,JC15,JA15) -> 0.038953387 | JF15: =IF(JD15>0,JB15,JC15) -> 0.038953395 | JG15: =(JE15+JF15)/2 -> 0.038953391 | JH15: =(SUMPRODUCT(($G$8:$G$694=X15)*SQRT(JG15^2+4*(1-JG15)*$I$8:$I$694^2/Z15))-COUNTIF($G$8:$G$694,X15)*JG15)/(2*(1-JG15))-1 -> -3.3892541e-09 | JI15: =IF(JH15>0,JG15,JE15) -> 0.038953387 | JJ15: =IF(JH15>0,JF15,JG15) -> 0.038953391 | JK15: =(JI15+JJ15)/2 -> 0.038953389 | JL15: =(SUMPRODUCT(($G$8:$G$694=X15)*SQRT(JK15^2+4*(1-JK15)*$I$8:$I$694^2/Z15))-COUNTIF($G$8:$G$694,X15)*JK15)/(2*(1-JK15))-1 -> -1.0438715e-09 | JM15: =IF(JL15>0,JK15,JI15) -> 0.038953387 | JN15: =IF(JL15>0,JJ15,JK15) -> 0.038953389 | JO15: =(JM15+JN15)/2 -> 0.038953388 | JP15: =(SUMPRODUCT(($G$8:$G$694=X15)*SQRT(JO15^2+4*(1-JO15)*$I$8:$I$694^2/Z15))-COUNTIF($G$8:$G$694,X15)*JO15)/(2*(1-JO15))-1 -> 1.288194e-10 | JQ15: =IF(JP15>0,JO15,JM15) -> 0.038953388 | JR15: =IF(JP15>0,JN15,JO15) -> 0.038953389 | JS15: =(JQ15+JR15)/2 -> 0.038953389 | JT15: =(SUMPRODUCT(($G$8:$G$694=X15)*SQRT(JS15^2+4*(1-JS15)*$I$8:$I$694^2/Z15))-COUNTIF($G$8:$G$694,X15)*JS15)/(2*(1-JS15))-1 -> -4.5752591e-10 | JU15: =IF(JT15>0,JS15,JQ15) -> 0.038953388 | JV15: =IF(JT15>0,JR15,JS15) -> 0.038953389 | JW15: =(JU15+JV15)/2 -> 0.038953388 | JX15: =(SUMPRODUCT(($G$8:$G$694=X15)*SQRT(JW15^2+4*(1-JW15)*$I$8:$I$694^2/Z15))-COUNTIF($G$8:$G$694,X15)*JW15)/(2*(1-JW15))-1 -> -1.643532e-10 | JY15: =IF(JX15>0,JW15,JU15) -> 0.038953388 | JZ15: =IF(JX15>0,JV15,JW15) -> 0.038953388 | KA15: =(EY15+EZ15)/2 -> 1.1161291 | KB15: =(JY15+JZ15)/2 -> 0.038953388
A16: =Odds_Input!A16 -> 8 | B16: =Odds_Input!B16 -> TITLE | C16: =Odds_Input!C16 -> Detroit Pistons | D16: =Odds_Input!D16 -> YES | E16: =Odds_Input!E16 -> - | F16: =Odds_Input!F16 -> 3000 | G16: =IF(OR(B16="WINS",B16="PLAYOFFS"),B16&"|"&C16&IF(B16="WINS","|"&TEXT(E16,"0.0"),""),B16) -> TITLE | H16: =IF(F16>0,1+F16/100,1+100/ABS(F16)) -> 31 | I16: =1/H16 -> 0.032258065 | J16: =IF(LEFT(B16,6)="PLAYIN",A_playin_slots,1) -> 1 | K16: =COUNTIF($G$8:$G$694,G16) -> 30 | L16: =SUMIF($G$8:$G$694,G16,$I$8:$I$694) -> 1.2525652 | M16: =L16/J16-1 -> 0.25256519 | N16: =I16*J16/L16 -> 0.025753601 | O16: =I16^R16 -> 0.022944171 | P16: =IF(J16<>1,O16,IF(L16<=1,I16/L16,(SQRT(S16^2+4*(1-S16)*I16^2/L16)-S16)/(2*(1-S16)))) -> 0.023929523 | Q16: =IF(A_devig="Multiplicative",N16,IF(A_devig="Power",O16,P16)) -> 0.023929523 | R16: =INDEX($KA$8:$KA$96,MATCH(G16,$X$8:$X$96,0)) -> 1.0992153 | S16: =INDEX($KB$8:$KB$96,MATCH(G16,$X$8:$X$96,0)) -> 0.011051948 | X16: DIV_SOUTHWEST | Y16: =IF(LEFT(X16,6)="PLAYIN",A_playin_slots,1) -> 1 | Z16: =SUMIF($G$8:$G$694,X16,$I$8:$I$694) -> 1.1290383 | AA16: 0.2 | AB16: 10 | AC16: =(AA16+AB16)/2 -> 5.1 | AD16: =SUMPRODUCT(($G$8:$G$694=X16)*($I$8:$I$694^AC16))-Y16 -> -0.38480101 | AE16: =IF(AD16>0,AC16,AA16) -> 0.2 | AF16: =IF(AD16>0,AB16,AC16) -> 5.1 | AG16: =(AE16+AF16)/2 -> 2.65 | AH16: =SUMPRODUCT(($G$8:$G$694=X16)*($I$8:$I$694^AG16))-Y16 -> -0.21220744 | AI16: =IF(AH16>0,AG16,AE16) -> 0.2 | AJ16: =IF(AH16>0,AF16,AG16) -> 2.65 | AK16: =(AI16+AJ16)/2 -> 1.425 | AL16: =SUMPRODUCT(($G$8:$G$694=X16)*($I$8:$I$694^AK16))-Y16 -> -0.031733296 | AM16: =IF(AL16>0,AK16,AI16) -> 0.2 | AN16: =IF(AL16>0,AJ16,AK16) -> 1.425 | AO16: =(AM16+AN16)/2 -> 0.8125 | AP16: =SUMPRODUCT(($G$8:$G$694=X16)*($I$8:$I$694^AO16))-Y16 -> 0.25793837 | AQ16: =IF(AP16>0,AO16,AM16) -> 0.8125 | AR16: =IF(AP16>0,AN16,AO16) -> 1.425 | AS16: =(AQ16+AR16)/2 -> 1.11875 | AT16: =SUMPRODUCT(($G$8:$G$694=X16)*($I$8:$I$694^AS16))-Y16 -> 0.071048589 | AU16: =IF(AT16>0,AS16,AQ16) -> 1.11875 | AV16: =IF(AT16>0,AR16,AS16) -> 1.425 | AW16: =(AU16+AV16)/2 -> 1.271875 | AX16: =SUMPRODUCT(($G$8:$G$694=X16)*($I$8:$I$694^AW16))-Y16 -> 0.013177384 | AY16: =IF(AX16>0,AW16,AU16) -> 1.271875 | AZ16: =IF(AX16>0,AV16,AW16) -> 1.425 | BA16: =(AY16+AZ16)/2 -> 1.3484375 | BB16: =SUMPRODUCT(($G$8:$G$694=X16)*($I$8:$I$694^BA16))-Y16 -> -0.010595577 | BC16: =IF(BB16>0,BA16,AY16) -> 1.271875 | BD16: =IF(BB16>0,AZ16,BA16) -> 1.3484375 | BE16: =(BC16+BD16)/2 -> 1.3101563 | BF16: =SUMPRODUCT(($G$8:$G$694=X16)*($I$8:$I$694^BE16))-Y16 -> 0.00092941957 | BG16: =IF(BF16>0,BE16,BC16) -> 1.3101563 | BH16: =IF(BF16>0,BD16,BE16) -> 1.3484375 | BI16: =(BG16+BH16)/2 -> 1.3292969 | BJ16: =SUMPRODUCT(($G$8:$G$694=X16)*($I$8:$I$694^BI16))-Y16 -> -0.0049191381 | BK16: =IF(BJ16>0,BI16,BG16) -> 1.3101563 | BL16: =IF(BJ16>0,BH16,BI16) -> 1.3292969 | BM16: =(BK16+BL16)/2 -> 1.3197266 | BN16: =SUMPRODUCT(($G$8:$G$694=X16)*($I$8:$I$694^BM16))-Y16 -> -0.0020168927 | BO16: =IF(BN16>0,BM16,BK16) -> 1.3101563 | BP16: =IF(BN16>0,BL16,BM16) -> 1.3197266 | BQ16: =(BO16+BP16)/2 -> 1.3149414 | BR16: =SUMPRODUCT(($G$8:$G$694=X16)*($I$8:$I$694^BQ16))-Y16 -> -0.00054931149 | BS16: =IF(BR16>0,BQ16,BO16) -> 1.3101563 | BT16: =IF(BR16>0,BP16,BQ16) -> 1.3149414 | BU16: =(BS16+BT16)/2 -> 1.3125488 | BV16: =SUMPRODUCT(($G$8:$G$694=X16)*($I$8:$I$694^BU16))-Y16 -> 0.00018865189 | BW16: =IF(BV16>0,BU16,BS16) -> 1.3125488 | BX16: =IF(BV16>0,BT16,BU16) -> 1.3149414 | BY16: =(BW16+BX16)/2 -> 1.3137451 | BZ16: =SUMPRODUCT(($G$8:$G$694=X16)*($I$8:$I$694^BY16))-Y16 -> -0.00018067928 | CA16: =IF(BZ16>0,BY16,BW16) -> 1.3125488 | CB16: =IF(BZ16>0,BX16,BY16) -> 1.3137451 | CC16: =(CA16+CB16)/2 -> 1.313147 | CD16: =SUMPRODUCT(($G$8:$G$694=X16)*($I$8:$I$694^CC16))-Y16 -> 3.8988003e-06 | CE16: =IF(CD16>0,CC16,CA16) -> 1.313147 | CF16: =IF(CD16>0,CB16,CC16) -> 1.3137451 | CG16: =(CE16+CF16)/2 -> 1.313446 | CH16: =SUMPRODUCT(($G$8:$G$694=X16)*($I$8:$I$694^CG16))-Y16 -> -8.8412099e-05 | CI16: =IF(CH16>0,CG16,CE16) -> 1.313147 | CJ16: =IF(CH16>0,CF16,CG16) -> 1.313446 | CK16: =(CI16+CJ16)/2 -> 1.3132965 | CL16: =SUMPRODUCT(($G$8:$G$694=X16)*($I$8:$I$694^CK16))-Y16 -> -4.2262116e-05 | CM16: =IF(CL16>0,CK16,CI16) -> 1.313147 | CN16: =IF(CL16>0,CJ16,CK16) -> 1.3132965 | CO16: =(CM16+CN16)/2 -> 1.3132217 | CP16: =SUMPRODUCT(($G$8:$G$694=X16)*($I$8:$I$694^CO16))-Y16 -> -1.9183025e-05 | CQ16: =IF(CP16>0,CO16,CM16) -> 1.313147 | CR16: =IF(CP16>0,CN16,CO16) -> 1.3132217 | CS16: =(CQ16+CR16)/2 -> 1.3131844 | CT16: =SUMPRODUCT(($G$8:$G$694=X16)*($I$8:$I$694^CS16))-Y16 -> -7.6424541e-06 | CU16: =IF(CT16>0,CS16,CQ16) -> 1.313147 | CV16: =IF(CT16>0,CR16,CS16) -> 1.3131844 | CW16: =(CU16+CV16)/2 -> 1.3131657 | CX16: =SUMPRODUCT(($G$8:$G$694=X16)*($I$8:$I$694^CW16))-Y16 -> -1.8719124e-06 | CY16: =IF(CX16>0,CW16,CU16) -> 1.313147 | CZ16: =IF(CX16>0,CV16,CW16) -> 1.3131657 | DA16: =(CY16+CZ16)/2 -> 1.3131563 | DB16: =SUMPRODUCT(($G$8:$G$694=X16)*($I$8:$I$694^DA16))-Y16 -> 1.0134226e-06 | DC16: =IF(DB16>0,DA16,CY16) -> 1.3131563 | DD16: =IF(DB16>0,CZ16,DA16) -> 1.3131657 | DE16: =(DC16+DD16)/2 -> 1.313161 | DF16: =SUMPRODUCT(($G$8:$G$694=X16)*($I$8:$I$694^DE16))-Y16 -> -4.2925022e-07 | DG16: =IF(DF16>0,DE16,DC16) -> 1.3131563 | DH16: =IF(DF16>0,DD16,DE16) -> 1.313161 | DI16: =(DG16+DH16)/2 -> 1.3131587 | DJ16: =SUMPRODUCT(($G$8:$G$694=X16)*($I$8:$I$694^DI16))-Y16 -> 2.9208486e-07 | DK16: =IF(DJ16>0,DI16,DG16) -> 1.3131587 | DL16: =IF(DJ16>0,DH16,DI16) -> 1.313161 | DM16: =(DK16+DL16)/2 -> 1.3131598 | DN16: =SUMPRODUCT(($G$8:$G$694=X16)*($I$8:$I$694^DM16))-Y16 -> -6.8583011e-08 | DO16: =IF(DN16>0,DM16,DK16) -> 1.3131587 | DP16: =IF(DN16>0,DL16,DM16) -> 1.3131598 | DQ16: =(DO16+DP16)/2 -> 1.3131592 | DR16: =SUMPRODUCT(($G$8:$G$694=X16)*($I$8:$I$694^DQ16))-Y16 -> 1.1175084e-07 | DS16: =IF(DR16>0,DQ16,DO16) -> 1.3131592 | DT16: =IF(DR16>0,DP16,DQ16) -> 1.3131598 | DU16: =(DS16+DT16)/2 -> 1.3131595 | DV16: =SUMPRODUCT(($G$8:$G$694=X16)*($I$8:$I$694^DU16))-Y16 -> 2.1583894e-08 | DW16: =IF(DV16>0,DU16,DS16) -> 1.3131595 | DX16: =IF(DV16>0,DT16,DU16) -> 1.3131598 | DY16: =(DW16+DX16)/2 -> 1.3131597 | DZ16: =SUMPRODUCT(($G$8:$G$694=X16)*($I$8:$I$694^DY16))-Y16 -> -2.3499564e-08 | EA16: =IF(DZ16>0,DY16,DW16) -> 1.3131595 | EB16: =IF(DZ16>0,DX16,DY16) -> 1.3131597 | EC16: =(EA16+EB16)/2 -> 1.3131596 | ED16: =SUMPRODUCT(($G$8:$G$694=X16)*($I$8:$I$694^EC16))-Y16 -> -9.5783648e-10 | EE16: =IF(ED16>0,EC16,EA16) -> 1.3131595 | EF16: =IF(ED16>0,EB16,EC16) -> 1.3131596 | EG16: =(EE16+EF16)/2 -> 1.3131596 | EH16: =SUMPRODUCT(($G$8:$G$694=X16)*($I$8:$I$694^EG16))-Y16 -> 1.0313028e-08 | EI16: =IF(EH16>0,EG16,EE16) -> 1.3131596 | EJ16: =IF(EH16>0,EF16,EG16) -> 1.3131596 | EK16: =(EI16+EJ16)/2 -> 1.3131596 | EL16: =SUMPRODUCT(($G$8:$G$694=X16)*($I$8:$I$694^EK16))-Y16 -> 4.6775959e-09 | EM16: =IF(EL16>0,EK16,EI16) -> 1.3131596 | EN16: =IF(EL16>0,EJ16,EK16) -> 1.3131596 | EO16: =(EM16+EN16)/2 -> 1.3131596 | EP16: =SUMPRODUCT(($G$8:$G$694=X16)*($I$8:$I$694^EO16))-Y16 -> 1.8598796e-09 | EQ16: =IF(EP16>0,EO16,EM16) -> 1.3131596 | ER16: =IF(EP16>0,EN16,EO16) -> 1.3131596 | ES16: =(EQ16+ER16)/2 -> 1.3131596 | ET16: =SUMPRODUCT(($G$8:$G$694=X16)*($I$8:$I$694^ES16))-Y16 -> 4.5102166e-10 | EU16: =IF(ET16>0,ES16,EQ16) -> 1.3131596 | EV16: =IF(ET16>0,ER16,ES16) -> 1.3131596 | EW16: =(EU16+EV16)/2 -> 1.3131596 | EX16: =SUMPRODUCT(($G$8:$G$694=X16)*($I$8:$I$694^EW16))-Y16 -> -2.5340752e-10 | EY16: =IF(EX16>0,EW16,EU16) -> 1.3131596 | EZ16: =IF(EX16>0,EV16,EW16) -> 1.3131596 | FA16: 1e-06 | FB16: 0.9999 | FC16: =(FA16+FB16)/2 -> 0.4999505 | FD16: =(SUMPRODUCT(($G$8:$G$694=X16)*SQRT(FC16^2+4*(1-FC16)*$I$8:$I$694^2/Z16))-COUNTIF($G$8:$G$694,X16)*FC16)/(2*(1-FC16))-1 -> -0.13385657 | FE16: =IF(FD16>0,FC16,FA16) -> 1e-06 | FF16: =IF(FD16>0,FB16,FC16) -> 0.4999505 | FG16: =(FE16+FF16)/2 -> 0.24997575 | FH16: =(SUMPRODUCT(($G$8:$G$694=X16)*SQRT(FG16^2+4*(1-FG16)*$I$8:$I$694^2/Z16))-COUNTIF($G$8:$G$694,X16)*FG16)/(2*(1-FG16))-1 -> -0.070052165 | FI16: =IF(FH16>0,FG16,FE16) -> 1e-06 | FJ16: =IF(FH16>0,FF16,FG16) -> 0.24997575 | FK16: =(FI16+FJ16)/2 -> 0.12498837 | FL16: =(SUMPRODUCT(($G$8:$G$694=X16)*SQRT(FK16^2+4*(1-FK16)*$I$8:$I$694^2/Z16))-COUNTIF($G$8:$G$694,X16)*FK16)/(2*(1-FK16))-1 -> -0.023398886 | FM16: =IF(FL16>0,FK16,FI16) -> 1e-06 | FN16: =IF(FL16>0,FJ16,FK16) -> 0.12498837 | FO16: =(FM16+FN16)/2 -> 0.062494687 | FP16: =(SUMPRODUCT(($G$8:$G$694=X16)*SQRT(FO16^2+4*(1-FO16)*$I$8:$I$694^2/Z16))-COUNTIF($G$8:$G$694,X16)*FO16)/(2*(1-FO16))-1 -> 0.007748447 | FQ16: =IF(FP16>0,FO16,FM16) -> 0.062494687 | FR16: =IF(FP16>0,FN16,FO16) -> 0.12498837 | FS16: =(FQ16+FR16)/2 -> 0.093741531 | FT16: =(SUMPRODUCT(($G$8:$G$694=X16)*SQRT(FS16^2+4*(1-FS16)*$I$8:$I$694^2/Z16))-COUNTIF($G$8:$G$694,X16)*FS16)/(2*(1-FS16))-1 -> -0.0088439541 | FU16: =IF(FT16>0,FS16,FQ16) -> 0.062494687 | FV16: =IF(FT16>0,FR16,FS16) -> 0.093741531 | FW16: =(FU16+FV16)/2 -> 0.078118109 | FX16: =(SUMPRODUCT(($G$8:$G$694=X16)*SQRT(FW16^2+4*(1-FW16)*$I$8:$I$694^2/Z16))-COUNTIF($G$8:$G$694,X16)*FW16)/(2*(1-FW16))-1 -> -0.00087066342 | FY16: =IF(FX16>0,FW16,FU16) -> 0.062494687 | FZ16: =IF(FX16>0,FV16,FW16) -> 0.078118109 | GA16: =(FY16+FZ16)/2 -> 0.070306398 | GB16: =(SUMPRODUCT(($G$8:$G$694=X16)*SQRT(GA16^2+4*(1-GA16)*$I$8:$I$694^2/Z16))-COUNTIF($G$8:$G$694,X16)*GA16)/(2*(1-GA16))-1 -> 0.0033452894 | GC16: =IF(GB16>0,GA16,FY16) -> 0.070306398 | GD16: =IF(GB16>0,FZ16,GA16) -> 0.078118109 | GE16: =(GC16+GD16)/2 -> 0.074212254 | GF16: =(SUMPRODUCT(($G$8:$G$694=X16)*SQRT(GE16^2+4*(1-GE16)*$I$8:$I$694^2/Z16))-COUNTIF($G$8:$G$694,X16)*GE16)/(2*(1-GE16))-1 -> 0.0012157973 | GG16: =IF(GF16>0,GE16,GC16) -> 0.074212254 | GH16: =IF(GF16>0,GD16,GE16) -> 0.078118109 | GI16: =(GG16+GH16)/2 -> 0.076165182 | GJ16: =(SUMPRODUCT(($G$8:$G$694=X16)*SQRT(GI16^2+4*(1-GI16)*$I$8:$I$694^2/Z16))-COUNTIF($G$8:$G$694,X16)*GI16)/(2*(1-GI16))-1 -> 0.00016739621 | GK16: =IF(GJ16>0,GI16,GG16) -> 0.076165182 | GL16: =IF(GJ16>0,GH16,GI16) -> 0.078118109 | GM16: =(GK16+GL16)/2 -> 0.077141646 | GN16: =(SUMPRODUCT(($G$8:$G$694=X16)*SQRT(GM16^2+4*(1-GM16)*$I$8:$I$694^2/Z16))-COUNTIF($G$8:$G$694,X16)*GM16)/(2*(1-GM16))-1 -> -0.0003529018 | GO16: =IF(GN16>0,GM16,GK16) -> 0.076165182 | GP16: =IF(GN16>0,GL16,GM16) -> 0.077141646 | GQ16: =(GO16+GP16)/2 -> 0.076653414 | GR16: =(SUMPRODUCT(($G$8:$G$694=X16)*SQRT(GQ16^2+4*(1-GQ16)*$I$8:$I$694^2/Z16))-COUNTIF($G$8:$G$694,X16)*GQ16)/(2*(1-GQ16))-1 -> -9.3072842e-05 | GS16: =IF(GR16>0,GQ16,GO16) -> 0.076165182 | GT16: =IF(GR16>0,GP16,GQ16) -> 0.076653414 | GU16: =(GS16+GT16)/2 -> 0.076409298 | GV16: =(SUMPRODUCT(($G$8:$G$694=X16)*SQRT(GU16^2+4*(1-GU16)*$I$8:$I$694^2/Z16))-COUNTIF($G$8:$G$694,X16)*GU16)/(2*(1-GU16))-1 -> 3.708129e-05 | GW16: =IF(GV16>0,GU16,GS16) -> 0.076409298 | GX16: =IF(GV16>0,GT16,GU16) -> 0.076653414 | GY16: =(GW16+GX16)/2 -> 0.076531356 | GZ16: =(SUMPRODUCT(($G$8:$G$694=X16)*SQRT(GY16^2+4*(1-GY16)*$I$8:$I$694^2/Z16))-COUNTIF($G$8:$G$694,X16)*GY16)/(2*(1-GY16))-1 -> -2.8015826e-05 | HA16: =IF(GZ16>0,GY16,GW16) -> 0.076409298 | HB16: =IF(GZ16>0,GX16,GY16) -> 0.076531356 | HC16: =(HA16+HB16)/2 -> 0.076470327 | HD16: =(SUMPRODUCT(($G$8:$G$694=X16)*SQRT(HC16^2+4*(1-HC16)*$I$8:$I$694^2/Z16))-COUNTIF($G$8:$G$694,X16)*HC16)/(2*(1-HC16))-1 -> 4.5277137e-06 | HE16: =IF(HD16>0,HC16,HA16) -> 0.076470327 | HF16: =IF(HD16>0,HB16,HC16) -> 0.076531356 | HG16: =(HE16+HF16)/2 -> 0.076500841 | HH16: =(SUMPRODUCT(($G$8:$G$694=X16)*SQRT(HG16^2+4*(1-HG16)*$I$8:$I$694^2/Z16))-COUNTIF($G$8:$G$694,X16)*HG16)/(2*(1-HG16))-1 -> -1.174531e-05 | HI16: =IF(HH16>0,HG16,HE16) -> 0.076470327 | HJ16: =IF(HH16>0,HF16,HG16) -> 0.076500841 | HK16: =(HI16+HJ16)/2 -> 0.076485584 | HL16: =(SUMPRODUCT(($G$8:$G$694=X16)*SQRT(HK16^2+4*(1-HK16)*$I$8:$I$694^2/Z16))-COUNTIF($G$8:$G$694,X16)*HK16)/(2*(1-HK16))-1 -> -3.6091117e-06 | HM16: =IF(HL16>0,HK16,HI16) -> 0.076470327 | HN16: =IF(HL16>0,HJ16,HK16) -> 0.076485584 | HO16: =(HM16+HN16)/2 -> 0.076477955 | HP16: =(SUMPRODUCT(($G$8:$G$694=X16)*SQRT(HO16^2+4*(1-HO16)*$I$8:$I$694^2/Z16))-COUNTIF($G$8:$G$694,X16)*HO16)/(2*(1-HO16))-1 -> 4.5922256e-07 | HQ16: =IF(HP16>0,HO16,HM16) -> 0.076477955 | HR16: =IF(HP16>0,HN16,HO16) -> 0.076485584 | HS16: =(HQ16+HR16)/2 -> 0.07648177 | HT16: =(SUMPRODUCT(($G$8:$G$694=X16)*SQRT(HS16^2+4*(1-HS16)*$I$8:$I$694^2/Z16))-COUNTIF($G$8:$G$694,X16)*HS16)/(2*(1-HS16))-1 -> -1.5749642e-06 | HU16: =IF(HT16>0,HS16,HQ16) -> 0.076477955 | HV16: =IF(HT16>0,HR16,HS16) -> 0.07648177 | HW16: =(HU16+HV16)/2 -> 0.076479862 | HX16: =(SUMPRODUCT(($G$8:$G$694=X16)*SQRT(HW16^2+4*(1-HW16)*$I$8:$I$694^2/Z16))-COUNTIF($G$8:$G$694,X16)*HW16)/(2*(1-HW16))-1 -> -5.5787571e-07 | HY16: =IF(HX16>0,HW16,HU16) -> 0.076477955 | HZ16: =IF(HX16>0,HV16,HW16) -> 0.076479862 | IA16: =(HY16+HZ16)/2 -> 0.076478909 | IB16: =(SUMPRODUCT(($G$8:$G$694=X16)*SQRT(IA16^2+4*(1-IA16)*$I$8:$I$694^2/Z16))-COUNTIF($G$8:$G$694,X16)*IA16)/(2*(1-IA16))-1 -> -4.9327799e-08 | IC16: =IF(IB16>0,IA16,HY16) -> 0.076477955 | ID16: =IF(IB16>0,HZ16,IA16) -> 0.076478909 | IE16: =(IC16+ID16)/2 -> 0.076478432 | IF16: =(SUMPRODUCT(($G$8:$G$694=X16)*SQRT(IE16^2+4*(1-IE16)*$I$8:$I$694^2/Z16))-COUNTIF($G$8:$G$694,X16)*IE16)/(2*(1-IE16))-1 -> 2.0494708e-07 | IG16: =IF(IF16>0,IE16,IC16) -> 0.076478432 | IH16: =IF(IF16>0,ID16,IE16) -> 0.076478909 | II16: =(IG16+IH16)/2 -> 0.07647867 | IJ16: =(SUMPRODUCT(($G$8:$G$694=X16)*SQRT(II16^2+4*(1-II16)*$I$8:$I$694^2/Z16))-COUNTIF($G$8:$G$694,X16)*II16)/(2*(1-II16))-1 -> 7.7809561e-08 | IK16: =IF(IJ16>0,II16,IG16) -> 0.07647867 | IL16: =IF(IJ16>0,IH16,II16) -> 0.076478909 | IM16: =(IK16+IL16)/2 -> 0.07647879 | IN16: =(SUMPRODUCT(($G$8:$G$694=X16)*SQRT(IM16^2+4*(1-IM16)*$I$8:$I$694^2/Z16))-COUNTIF($G$8:$G$694,X16)*IM16)/(2*(1-IM16))-1 -> 1.4240862e-08 | IO16: =IF(IN16>0,IM16,IK16) -> 0.07647879 | IP16: =IF(IN16>0,IL16,IM16) -> 0.076478909 | IQ16: =(IO16+IP16)/2 -> 0.076478849 | IR16: =(SUMPRODUCT(($G$8:$G$694=X16)*SQRT(IQ16^2+4*(1-IQ16)*$I$8:$I$694^2/Z16))-COUNTIF($G$8:$G$694,X16)*IQ16)/(2*(1-IQ16))-1 -> -1.7543474e-08 | IS16: =IF(IR16>0,IQ16,IO16) -> 0.07647879 | IT16: =IF(IR16>0,IP16,IQ16) -> 0.076478849 | IU16: =(IS16+IT16)/2 -> 0.076478819 | IV16: =(SUMPRODUCT(($G$8:$G$694=X16)*SQRT(IU16^2+4*(1-IU16)*$I$8:$I$694^2/Z16))-COUNTIF($G$8:$G$694,X16)*IU16)/(2*(1-IU16))-1 -> -1.651307e-09 | IW16: =IF(IV16>0,IU16,IS16) -> 0.07647879 | IX16: =IF(IV16>0,IT16,IU16) -> 0.076478819 | IY16: =(IW16+IX16)/2 -> 0.076478805 | IZ16: =(SUMPRODUCT(($G$8:$G$694=X16)*SQRT(IY16^2+4*(1-IY16)*$I$8:$I$694^2/Z16))-COUNTIF($G$8:$G$694,X16)*IY16)/(2*(1-IY16))-1 -> 6.2947771e-09 | JA16: =IF(IZ16>0,IY16,IW16) -> 0.076478805 | JB16: =IF(IZ16>0,IX16,IY16) -> 0.076478819 | JC16: =(JA16+JB16)/2 -> 0.076478812 | JD16: =(SUMPRODUCT(($G$8:$G$694=X16)*SQRT(JC16^2+4*(1-JC16)*$I$8:$I$694^2/Z16))-COUNTIF($G$8:$G$694,X16)*JC16)/(2*(1-JC16))-1 -> 2.321735e-09 | JE16: =IF(JD16>0,JC16,JA16) -> 0.076478812 | JF16: =IF(JD16>0,JB16,JC16) -> 0.076478819 | JG16: =(JE16+JF16)/2 -> 0.076478816 | JH16: =(SUMPRODUCT(($G$8:$G$694=X16)*SQRT(JG16^2+4*(1-JG16)*$I$8:$I$694^2/Z16))-COUNTIF($G$8:$G$694,X16)*JG16)/(2*(1-JG16))-1 -> 3.3521408e-10 | JI16: =IF(JH16>0,JG16,JE16) -> 0.076478816 | JJ16: =IF(JH16>0,JF16,JG16) -> 0.076478819 | JK16: =(JI16+JJ16)/2 -> 0.076478818 | JL16: =(SUMPRODUCT(($G$8:$G$694=X16)*SQRT(JK16^2+4*(1-JK16)*$I$8:$I$694^2/Z16))-COUNTIF($G$8:$G$694,X16)*JK16)/(2*(1-JK16))-1 -> -6.5804673e-10 | JM16: =IF(JL16>0,JK16,JI16) -> 0.076478816 | JN16: =IF(JL16>0,JJ16,JK16) -> 0.076478818 | JO16: =(JM16+JN16)/2 -> 0.076478817 | JP16: =(SUMPRODUCT(($G$8:$G$694=X16)*SQRT(JO16^2+4*(1-JO16)*$I$8:$I$694^2/Z16))-COUNTIF($G$8:$G$694,X16)*JO16)/(2*(1-JO16))-1 -> -1.6141621e-10 | JQ16: =IF(JP16>0,JO16,JM16) -> 0.076478816 | JR16: =IF(JP16>0,JN16,JO16) -> 0.076478817 | JS16: =(JQ16+JR16)/2 -> 0.076478816 | JT16: =(SUMPRODUCT(($G$8:$G$694=X16)*SQRT(JS16^2+4*(1-JS16)*$I$8:$I$694^2/Z16))-COUNTIF($G$8:$G$694,X16)*JS16)/(2*(1-JS16))-1 -> 8.6898932e-11 | JU16: =IF(JT16>0,JS16,JQ16) -> 0.076478816 | JV16: =IF(JT16>0,JR16,JS16) -> 0.076478817 | JW16: =(JU16+JV16)/2 -> 0.076478816 | JX16: =(SUMPRODUCT(($G$8:$G$694=X16)*SQRT(JW16^2+4*(1-JW16)*$I$8:$I$694^2/Z16))-COUNTIF($G$8:$G$694,X16)*JW16)/(2*(1-JW16))-1 -> -3.7258641e-11 | JY16: =IF(JX16>0,JW16,JU16) -> 0.076478816 | JZ16: =IF(JX16>0,JV16,JW16) -> 0.076478816 | KA16: =(EY16+EZ16)/2 -> 1.3131596 | KB16: =(JY16+JZ16)/2 -> 0.076478816
A17: =Odds_Input!A17 -> 9 | B17: =Odds_Input!B17 -> TITLE | C17: =Odds_Input!C17 -> Golden State Warriors | D17: =Odds_Input!D17 -> YES | E17: =Odds_Input!E17 -> - | F17: =Odds_Input!F17 -> 5300 | G17: =IF(OR(B17="WINS",B17="PLAYOFFS"),B17&"|"&C17&IF(B17="WINS","|"&TEXT(E17,"0.0"),""),B17) -> TITLE | H17: =IF(F17>0,1+F17/100,1+100/ABS(F17)) -> 54 | I17: =1/H17 -> 0.018518519 | J17: =IF(LEFT(B17,6)="PLAYIN",A_playin_slots,1) -> 1 | K17: =COUNTIF($G$8:$G$694,G17) -> 30 | L17: =SUMIF($G$8:$G$694,G17,$I$8:$I$694) -> 1.2525652 | M17: =L17/J17-1 -> 0.25256519 | N17: =I17*J17/L17 -> 0.014784475 | O17: =I17^R17 -> 0.012465974 | P17: =IF(J17<>1,O17,IF(L17<=1,I17/L17,(SQRT(S17^2+4*(1-S17)*I17^2/L17)-S17)/(2*(1-S17)))) -> 0.011964164 | Q17: =IF(A_devig="Multiplicative",N17,IF(A_devig="Power",O17,P17)) -> 0.011964164 | R17: =INDEX($KA$8:$KA$96,MATCH(G17,$X$8:$X$96,0)) -> 1.0992153 | S17: =INDEX($KB$8:$KB$96,MATCH(G17,$X$8:$X$96,0)) -> 0.011051948 | X17: PLAYIN_EAST | Y17: =IF(LEFT(X17,6)="PLAYIN",A_playin_slots,1) -> 4 | Z17: =SUMIF($G$8:$G$694,X17,$I$8:$I$694) -> 4.3710402 | AA17: 0.2 | AB17: 10 | AC17: =(AA17+AB17)/2 -> 5.1 | AD17: =SUMPRODUCT(($G$8:$G$694=X17)*($I$8:$I$694^AC17))-Y17 -> -3.9055106 | AE17: =IF(AD17>0,AC17,AA17) -> 0.2 | AF17: =IF(AD17>0,AB17,AC17) -> 5.1 | AG17: =(AE17+AF17)/2 -> 2.65 | AH17: =SUMPRODUCT(($G$8:$G$694=X17)*($I$8:$I$694^AG17))-Y17 -> -3.1722974 | AI17: =IF(AH17>0,AG17,AE17) -> 0.2 | AJ17: =IF(AH17>0,AF17,AG17) -> 2.65 | AK17: =(AI17+AJ17)/2 -> 1.425 | AL17: =SUMPRODUCT(($G$8:$G$694=X17)*($I$8:$I$694^AK17))-Y17 -> -1.2342469 | AM17: =IF(AL17>0,AK17,AI17) -> 0.2 | AN17: =IF(AL17>0,AJ17,AK17) -> 1.425 | AO17: =(AM17+AN17)/2 -> 0.8125 | AP17: =SUMPRODUCT(($G$8:$G$694=X17)*($I$8:$I$694^AO17))-Y17 -> 1.4023173 | AQ17: =IF(AP17>0,AO17,AM17) -> 0.8125 | AR17: =IF(AP17>0,AN17,AO17) -> 1.425 | AS17: =(AQ17+AR17)/2 -> 1.11875 | AT17: =SUMPRODUCT(($G$8:$G$694=X17)*($I$8:$I$694^AS17))-Y17 -> -0.16474533 | AU17: =IF(AT17>0,AS17,AQ17) -> 0.8125 | AV17: =IF(AT17>0,AR17,AS17) -> 1.11875 | AW17: =(AU17+AV17)/2 -> 0.965625 | AX17: =SUMPRODUCT(($G$8:$G$694=X17)*($I$8:$I$694^AW17))-Y17 -> 0.54180565 | AY17: =IF(AX17>0,AW17,AU17) -> 0.965625 | AZ17: =IF(AX17>0,AV17,AW17) -> 1.11875 | BA17: =(AY17+AZ17)/2 -> 1.0421875 | BB17: =SUMPRODUCT(($G$8:$G$694=X17)*($I$8:$I$694^BA17))-Y17 -> 0.1714435 | BC17: =IF(BB17>0,BA17,AY17) -> 1.0421875 | BD17: =IF(BB17>0,AZ17,BA17) -> 1.11875 | BE17: =(BC17+BD17)/2 -> 1.0804687 | BF17: =SUMPRODUCT(($G$8:$G$694=X17)*($I$8:$I$694^BE17))-Y17 -> -0.00068363087 | BG17: =IF(BF17>0,BE17,BC17) -> 1.0421875 | BH17: =IF(BF17>0,BD17,BE17) -> 1.0804687 | BI17: =(BG17+BH17)/2 -> 1.0613281 | BJ17: =SUMPRODUCT(($G$8:$G$694=X17)*($I$8:$I$694^BI17))-Y17 -> 0.084343129 | BK17: =IF(BJ17>0,BI17,BG17) -> 1.0613281 | BL17: =IF(BJ17>0,BH17,BI17) -> 1.0804687 | BM17: =(BK17+BL17)/2 -> 1.0708984 | BN17: =SUMPRODUCT(($G$8:$G$694=X17)*($I$8:$I$694^BM17))-Y17 -> 0.0415742 | BO17: =IF(BN17>0,BM17,BK17) -> 1.0708984 | BP17: =IF(BN17>0,BL17,BM17) -> 1.0804687 | BQ17: =(BO17+BP17)/2 -> 1.0756836 | BR17: =SUMPRODUCT(($G$8:$G$694=X17)*($I$8:$I$694^BQ17))-Y17 -> 0.020381848 | BS17: =IF(BR17>0,BQ17,BO17) -> 1.0756836 | BT17: =IF(BR17>0,BP17,BQ17) -> 1.0804687 | BU17: =(BS17+BT17)/2 -> 1.0780762 | BV17: =SUMPRODUCT(($G$8:$G$694=X17)*($I$8:$I$694^BU17))-Y17 -> 0.0098333048 | BW17: =IF(BV17>0,BU17,BS17) -> 1.0780762 | BX17: =IF(BV17>0,BT17,BU17) -> 1.0804687 | BY17: =(BW17+BX17)/2 -> 1.0792725 | BZ17: =SUMPRODUCT(($G$8:$G$694=X17)*($I$8:$I$694^BY17))-Y17 -> 0.0045708931 | CA17: =IF(BZ17>0,BY17,BW17) -> 1.0792725 | CB17: =IF(BZ17>0,BX17,BY17) -> 1.0804687 | CC17: =(CA17+CB17)/2 -> 1.0798706 | CD17: =SUMPRODUCT(($G$8:$G$694=X17)*($I$8:$I$694^CC17))-Y17 -> 0.001942646 | CE17: =IF(CD17>0,CC17,CA17) -> 1.0798706 | CF17: =IF(CD17>0,CB17,CC17) -> 1.0804687 | CG17: =(CE17+CF17)/2 -> 1.0801697 | CH17: =SUMPRODUCT(($G$8:$G$694=X17)*($I$8:$I$694^CG17))-Y17 -> 0.00062926139 | CI17: =IF(CH17>0,CG17,CE17) -> 1.0801697 | CJ17: =IF(CH17>0,CF17,CG17) -> 1.0804687 | CK17: =(CI17+CJ17)/2 -> 1.0803192 | CL17: =SUMPRODUCT(($G$8:$G$694=X17)*($I$8:$I$694^CK17))-Y17 -> -2.7246272e-05 | CM17: =IF(CL17>0,CK17,CI17) -> 1.0801697 | CN17: =IF(CL17>0,CJ17,CK17) -> 1.0803192 | CO17: =(CM17+CN17)/2 -> 1.0802444 | CP17: =SUMPRODUCT(($G$8:$G$694=X17)*($I$8:$I$694^CO17))-Y17 -> 0.00030099217 | CQ17: =IF(CP17>0,CO17,CM17) -> 1.0802444 | CR17: =IF(CP17>0,CN17,CO17) -> 1.0803192 | CS17: =(CQ17+CR17)/2 -> 1.0802818 | CT17: =SUMPRODUCT(($G$8:$G$694=X17)*($I$8:$I$694^CS17))-Y17 -> 0.0001368691 | CU17: =IF(CT17>0,CS17,CQ17) -> 1.0802818 | CV17: =IF(CT17>0,CR17,CS17) -> 1.0803192 | CW17: =(CU17+CV17)/2 -> 1.0803005 | CX17: =SUMPRODUCT(($G$8:$G$694=X17)*($I$8:$I$694^CW17))-Y17 -> 5.4810455e-05 | CY17: =IF(CX17>0,CW17,CU17) -> 1.0803005 | CZ17: =IF(CX17>0,CV17,CW17) -> 1.0803192 | DA17: =(CY17+CZ17)/2 -> 1.0803099 | DB17: =SUMPRODUCT(($G$8:$G$694=X17)*($I$8:$I$694^DA17))-Y17 -> 1.3781851e-05 | DC17: =IF(DB17>0,DA17,CY17) -> 1.0803099 | DD17: =IF(DB17>0,CZ17,DA17) -> 1.0803192 | DE17: =(DC17+DD17)/2 -> 1.0803145 | DF17: =SUMPRODUCT(($G$8:$G$694=X17)*($I$8:$I$694^DE17))-Y17 -> -6.7322709e-06 | DG17: =IF(DF17>0,DE17,DC17) -> 1.0803099 | DH17: =IF(DF17>0,DD17,DE17) -> 1.0803145 | DI17: =(DG17+DH17)/2 -> 1.0803122 | DJ17: =SUMPRODUCT(($G$8:$G$694=X17)*($I$8:$I$694^DI17))-Y17 -> 3.5247749e-06 | DK17: =IF(DJ17>0,DI17,DG17) -> 1.0803122 | DL17: =IF(DJ17>0,DH17,DI17) -> 1.0803145 | DM17: =(DK17+DL17)/2 -> 1.0803134 | DN17: =SUMPRODUCT(($G$8:$G$694=X17)*($I$8:$I$694^DM17))-Y17 -> -1.6037518e-06 | DO17: =IF(DN17>0,DM17,DK17) -> 1.0803122 | DP17: =IF(DN17>0,DL17,DM17) -> 1.0803134 | DQ17: =(DO17+DP17)/2 -> 1.0803128 | DR17: =SUMPRODUCT(($G$8:$G$694=X17)*($I$8:$I$694^DQ17))-Y17 -> 9.6051064e-07 | DS17: =IF(DR17>0,DQ17,DO17) -> 1.0803128 | DT17: =IF(DR17>0,DP17,DQ17) -> 1.0803134 | DU17: =(DS17+DT17)/2 -> 1.0803131 | DV17: =SUMPRODUCT(($G$8:$G$694=X17)*($I$8:$I$694^DU17))-Y17 -> -3.2162079e-07 | DW17: =IF(DV17>0,DU17,DS17) -> 1.0803128 | DX17: =IF(DV17>0,DT17,DU17) -> 1.0803131 | DY17: =(DW17+DX17)/2 -> 1.0803129 | DZ17: =SUMPRODUCT(($G$8:$G$694=X17)*($I$8:$I$694^DY17))-Y17 -> 3.1944487e-07 | EA17: =IF(DZ17>0,DY17,DW17) -> 1.0803129 | EB17: =IF(DZ17>0,DX17,DY17) -> 1.0803131 | EC17: =(EA17+EB17)/2 -> 1.080313 | ED17: =SUMPRODUCT(($G$8:$G$694=X17)*($I$8:$I$694^EC17))-Y17 -> -1.0879773e-09 | EE17: =IF(ED17>0,EC17,EA17) -> 1.0803129 | EF17: =IF(ED17>0,EB17,EC17) -> 1.080313 | EG17: =(EE17+EF17)/2 -> 1.080313 | EH17: =SUMPRODUCT(($G$8:$G$694=X17)*($I$8:$I$694^EG17))-Y17 -> 1.5917844e-07 | EI17: =IF(EH17>0,EG17,EE17) -> 1.080313 | EJ17: =IF(EH17>0,EF17,EG17) -> 1.080313 | EK17: =(EI17+EJ17)/2 -> 1.080313 | EL17: =SUMPRODUCT(($G$8:$G$694=X17)*($I$8:$I$694^EK17))-Y17 -> 7.9045231e-08 | EM17: =IF(EL17>0,EK17,EI17) -> 1.080313 | EN17: =IF(EL17>0,EJ17,EK17) -> 1.080313 | EO17: =(EM17+EN17)/2 -> 1.080313 | EP17: =SUMPRODUCT(($G$8:$G$694=X17)*($I$8:$I$694^EO17))-Y17 -> 3.8978627e-08 | EQ17: =IF(EP17>0,EO17,EM17) -> 1.080313 | ER17: =IF(EP17>0,EN17,EO17) -> 1.080313 | ES17: =(EQ17+ER17)/2 -> 1.080313 | ET17: =SUMPRODUCT(($G$8:$G$694=X17)*($I$8:$I$694^ES17))-Y17 -> 1.8945325e-08 | EU17: =IF(ET17>0,ES17,EQ17) -> 1.080313 | EV17: =IF(ET17>0,ER17,ES17) -> 1.080313 | EW17: =(EU17+EV17)/2 -> 1.080313 | EX17: =SUMPRODUCT(($G$8:$G$694=X17)*($I$8:$I$694^EW17))-Y17 -> 8.9286747e-09 | EY17: =IF(EX17>0,EW17,EU17) -> 1.080313 | EZ17: =IF(EX17>0,EV17,EW17) -> 1.080313 | FA17: 1e-06 | FB17: 0.9999 | FC17: =(FA17+FB17)/2 -> 0.4999505 | FD17: =(SUMPRODUCT(($G$8:$G$694=X17)*SQRT(FC17^2+4*(1-FC17)*$I$8:$I$694^2/Z17))-COUNTIF($G$8:$G$694,X17)*FC17)/(2*(1-FC17))-1 -> -0.33725413 | FE17: =IF(FD17>0,FC17,FA17) -> 1e-06 | FF17: =IF(FD17>0,FB17,FC17) -> 0.4999505 | FG17: =(FE17+FF17)/2 -> 0.24997575 | FH17: =(SUMPRODUCT(($G$8:$G$694=X17)*SQRT(FG17^2+4*(1-FG17)*$I$8:$I$694^2/Z17))-COUNTIF($G$8:$G$694,X17)*FG17)/(2*(1-FG17))-1 -> 0.079058658 | FI17: =IF(FH17>0,FG17,FE17) -> 0.24997575 | FJ17: =IF(FH17>0,FF17,FG17) -> 0.4999505 | FK17: =(FI17+FJ17)/2 -> 0.37496313 | FL17: =(SUMPRODUCT(($G$8:$G$694=X17)*SQRT(FK17^2+4*(1-FK17)*$I$8:$I$694^2/Z17))-COUNTIF($G$8:$G$694,X17)*FK17)/(2*(1-FK17))-1 -> -0.17073115 | FM17: =IF(FL17>0,FK17,FI17) -> 0.24997575 | FN17: =IF(FL17>0,FJ17,FK17) -> 0.37496313 | FO17: =(FM17+FN17)/2 -> 0.31246944 | FP17: =(SUMPRODUCT(($G$8:$G$694=X17)*SQRT(FO17^2+4*(1-FO17)*$I$8:$I$694^2/Z17))-COUNTIF($G$8:$G$694,X17)*FO17)/(2*(1-FO17))-1 -> -0.058981435 | FQ17: =IF(FP17>0,FO17,FM17) -> 0.24997575 | FR17: =IF(FP17>0,FN17,FO17) -> 0.31246944 | FS17: =(FQ17+FR17)/2 -> 0.28122259 | FT17: =(SUMPRODUCT(($G$8:$G$694=X17)*SQRT(FS17^2+4*(1-FS17)*$I$8:$I$694^2/Z17))-COUNTIF($G$8:$G$694,X17)*FS17)/(2*(1-FS17))-1 -> 0.0063306128 | FU17: =IF(FT17>0,FS17,FQ17) -> 0.28122259 | FV17: =IF(FT17>0,FR17,FS17) -> 0.31246944 | FW17: =(FU17+FV17)/2 -> 0.29684602 | FX17: =(SUMPRODUCT(($G$8:$G$694=X17)*SQRT(FW17^2+4*(1-FW17)*$I$8:$I$694^2/Z17))-COUNTIF($G$8:$G$694,X17)*FW17)/(2*(1-FW17))-1 -> -0.027195674 | FY17: =IF(FX17>0,FW17,FU17) -> 0.28122259 | FZ17: =IF(FX17>0,FV17,FW17) -> 0.29684602 | GA17: =(FY17+FZ17)/2 -> 0.2890343 | GB17: =(SUMPRODUCT(($G$8:$G$694=X17)*SQRT(GA17^2+4*(1-GA17)*$I$8:$I$694^2/Z17))-COUNTIF($G$8:$G$694,X17)*GA17)/(2*(1-GA17))-1 -> -0.010656924 | GC17: =IF(GB17>0,GA17,FY17) -> 0.28122259 | GD17: =IF(GB17>0,FZ17,GA17) -> 0.2890343 | GE17: =(GC17+GD17)/2 -> 0.28512845 | GF17: =(SUMPRODUCT(($G$8:$G$694=X17)*SQRT(GE17^2+4*(1-GE17)*$I$8:$I$694^2/Z17))-COUNTIF($G$8:$G$694,X17)*GE17)/(2*(1-GE17))-1 -> -0.0022201296 | GG17: =IF(GF17>0,GE17,GC17) -> 0.28122259 | GH17: =IF(GF17>0,GD17,GE17) -> 0.28512845 | GI17: =(GG17+GH17)/2 -> 0.28317552 | GJ17: =(SUMPRODUCT(($G$8:$G$694=X17)*SQRT(GI17^2+4*(1-GI17)*$I$8:$I$694^2/Z17))-COUNTIF($G$8:$G$694,X17)*GI17)/(2*(1-GI17))-1 -> 0.0020408871 | GK17: =IF(GJ17>0,GI17,GG17) -> 0.28317552 | GL17: =IF(GJ17>0,GH17,GI17) -> 0.28512845 | GM17: =(GK17+GL17)/2 -> 0.28415199 | GN17: =(SUMPRODUCT(($G$8:$G$694=X17)*SQRT(GM17^2+4*(1-GM17)*$I$8:$I$694^2/Z17))-COUNTIF($G$8:$G$694,X17)*GM17)/(2*(1-GM17))-1 -> -9.3195908e-05 | GO17: =IF(GN17>0,GM17,GK17) -> 0.28317552 | GP17: =IF(GN17>0,GL17,GM17) -> 0.28415199 | GQ17: =(GO17+GP17)/2 -> 0.28366375 | GR17: =(SUMPRODUCT(($G$8:$G$694=X17)*SQRT(GQ17^2+4*(1-GQ17)*$I$8:$I$694^2/Z17))-COUNTIF($G$8:$G$694,X17)*GQ17)/(2*(1-GQ17))-1 -> 0.0009729502 | GS17: =IF(GR17>0,GQ17,GO17) -> 0.28366375 | GT17: =IF(GR17>0,GP17,GQ17) -> 0.28415199 | GU17: =(GS17+GT17)/2 -> 0.28390787 | GV17: =(SUMPRODUCT(($G$8:$G$694=X17)*SQRT(GU17^2+4*(1-GU17)*$I$8:$I$694^2/Z17))-COUNTIF($G$8:$G$694,X17)*GU17)/(2*(1-GU17))-1 -> 0.00043965351 | GW17: =IF(GV17>0,GU17,GS17) -> 0.28390787 | GX17: =IF(GV17>0,GT17,GU17) -> 0.28415199 | GY17: =(GW17+GX17)/2 -> 0.28402993 | GZ17: =(SUMPRODUCT(($G$8:$G$694=X17)*SQRT(GY17^2+4*(1-GY17)*$I$8:$I$694^2/Z17))-COUNTIF($G$8:$G$694,X17)*GY17)/(2*(1-GY17))-1 -> 0.00017317292 | HA17: =IF(GZ17>0,GY17,GW17) -> 0.28402993 | HB17: =IF(GZ17>0,GX17,GY17) -> 0.28415199 | HC17: =(HA17+HB17)/2 -> 0.28409096 | HD17: =(SUMPRODUCT(($G$8:$G$694=X17)*SQRT(HC17^2+4*(1-HC17)*$I$8:$I$694^2/Z17))-COUNTIF($G$8:$G$694,X17)*HC17)/(2*(1-HC17))-1 -> 3.997454e-05 | HE17: =IF(HD17>0,HC17,HA17) -> 0.28409096 | HF17: =IF(HD17>0,HB17,HC17) -> 0.28415199 | HG17: =(HE17+HF17)/2 -> 0.28412147 | HH17: =(SUMPRODUCT(($G$8:$G$694=X17)*SQRT(HG17^2+4*(1-HG17)*$I$8:$I$694^2/Z17))-COUNTIF($G$8:$G$694,X17)*HG17)/(2*(1-HG17))-1 -> -2.6614175e-05 | HI17: =IF(HH17>0,HG17,HE17) -> 0.28409096 | HJ17: =IF(HH17>0,HF17,HG17) -> 0.28412147 | HK17: =(HI17+HJ17)/2 -> 0.28410621 | HL17: =(SUMPRODUCT(($G$8:$G$694=X17)*SQRT(HK17^2+4*(1-HK17)*$I$8:$I$694^2/Z17))-COUNTIF($G$8:$G$694,X17)*HK17)/(2*(1-HK17))-1 -> 6.6793093e-06 | HM17: =IF(HL17>0,HK17,HI17) -> 0.28410621 | HN17: =IF(HL17>0,HJ17,HK17) -> 0.28412147 | HO17: =(HM17+HN17)/2 -> 0.28411384 | HP17: =(SUMPRODUCT(($G$8:$G$694=X17)*SQRT(HO17^2+4*(1-HO17)*$I$8:$I$694^2/Z17))-COUNTIF($G$8:$G$694,X17)*HO17)/(2*(1-HO17))-1 -> -9.9676512e-06 | HQ17: =IF(HP17>0,HO17,HM17) -> 0.28410621 | HR17: =IF(HP17>0,HN17,HO17) -> 0.28411384 | HS17: =(HQ17+HR17)/2 -> 0.28411003 | HT17: =(SUMPRODUCT(($G$8:$G$694=X17)*SQRT(HS17^2+4*(1-HS17)*$I$8:$I$694^2/Z17))-COUNTIF($G$8:$G$694,X17)*HS17)/(2*(1-HS17))-1 -> -1.6442255e-06 | HU17: =IF(HT17>0,HS17,HQ17) -> 0.28410621 | HV17: =IF(HT17>0,HR17,HS17) -> 0.28411003 | HW17: =(HU17+HV17)/2 -> 0.28410812 | HX17: =(SUMPRODUCT(($G$8:$G$694=X17)*SQRT(HW17^2+4*(1-HW17)*$I$8:$I$694^2/Z17))-COUNTIF($G$8:$G$694,X17)*HW17)/(2*(1-HW17))-1 -> 2.5175282e-06 | HY17: =IF(HX17>0,HW17,HU17) -> 0.28410812 | HZ17: =IF(HX17>0,HV17,HW17) -> 0.28411003 | IA17: =(HY17+HZ17)/2 -> 0.28410907 | IB17: =(SUMPRODUCT(($G$8:$G$694=X17)*SQRT(IA17^2+4*(1-IA17)*$I$8:$I$694^2/Z17))-COUNTIF($G$8:$G$694,X17)*IA17)/(2*(1-IA17))-1 -> 4.3664795e-07 | IC17: =IF(IB17>0,IA17,HY17) -> 0.28410907 | ID17: =IF(IB17>0,HZ17,IA17) -> 0.28411003 | IE17: =(IC17+ID17)/2 -> 0.28410955 | IF17: =(SUMPRODUCT(($G$8:$G$694=X17)*SQRT(IE17^2+4*(1-IE17)*$I$8:$I$694^2/Z17))-COUNTIF($G$8:$G$694,X17)*IE17)/(2*(1-IE17))-1 -> -6.0378964e-07 | IG17: =IF(IF17>0,IE17,IC17) -> 0.28410907 | IH17: =IF(IF17>0,ID17,IE17) -> 0.28410955 | II17: =(IG17+IH17)/2 -> 0.28410931 | IJ17: =(SUMPRODUCT(($G$8:$G$694=X17)*SQRT(II17^2+4*(1-II17)*$I$8:$I$694^2/Z17))-COUNTIF($G$8:$G$694,X17)*II17)/(2*(1-II17))-1 -> -8.3571057e-08 | IK17: =IF(IJ17>0,II17,IG17) -> 0.28410907 | IL17: =IF(IJ17>0,IH17,II17) -> 0.28410931 | IM17: =(IK17+IL17)/2 -> 0.28410919 | IN17: =(SUMPRODUCT(($G$8:$G$694=X17)*SQRT(IM17^2+4*(1-IM17)*$I$8:$I$694^2/Z17))-COUNTIF($G$8:$G$694,X17)*IM17)/(2*(1-IM17))-1 -> 1.7653839e-07 | IO17: =IF(IN17>0,IM17,IK17) -> 0.28410919 | IP17: =IF(IN17>0,IL17,IM17) -> 0.28410931 | IQ17: =(IO17+IP17)/2 -> 0.28410925 | IR17: =(SUMPRODUCT(($G$8:$G$694=X17)*SQRT(IQ17^2+4*(1-IQ17)*$I$8:$I$694^2/Z17))-COUNTIF($G$8:$G$694,X17)*IQ17)/(2*(1-IQ17))-1 -> 4.6483654e-08 | IS17: =IF(IR17>0,IQ17,IO17) -> 0.28410925 | IT17: =IF(IR17>0,IP17,IQ17) -> 0.28410931 | IU17: =(IS17+IT17)/2 -> 0.28410928 | IV17: =(SUMPRODUCT(($G$8:$G$694=X17)*SQRT(IU17^2+4*(1-IU17)*$I$8:$I$694^2/Z17))-COUNTIF($G$8:$G$694,X17)*IU17)/(2*(1-IU17))-1 -> -1.8543706e-08 | IW17: =IF(IV17>0,IU17,IS17) -> 0.28410925 | IX17: =IF(IV17>0,IT17,IU17) -> 0.28410928 | IY17: =(IW17+IX17)/2 -> 0.28410927 | IZ17: =(SUMPRODUCT(($G$8:$G$694=X17)*SQRT(IY17^2+4*(1-IY17)*$I$8:$I$694^2/Z17))-COUNTIF($G$8:$G$694,X17)*IY17)/(2*(1-IY17))-1 -> 1.3969973e-08 | JA17: =IF(IZ17>0,IY17,IW17) -> 0.28410927 | JB17: =IF(IZ17>0,IX17,IY17) -> 0.28410928 | JC17: =(JA17+JB17)/2 -> 0.28410928 | JD17: =(SUMPRODUCT(($G$8:$G$694=X17)*SQRT(JC17^2+4*(1-JC17)*$I$8:$I$694^2/Z17))-COUNTIF($G$8:$G$694,X17)*JC17)/(2*(1-JC17))-1 -> -2.286866e-09 | JE17: =IF(JD17>0,JC17,JA17) -> 0.28410927 | JF17: =IF(JD17>0,JB17,JC17) -> 0.28410928 | JG17: =(JE17+JF17)/2 -> 0.28410927 | JH17: =(SUMPRODUCT(($G$8:$G$694=X17)*SQRT(JG17^2+4*(1-JG17)*$I$8:$I$694^2/Z17))-COUNTIF($G$8:$G$694,X17)*JG17)/(2*(1-JG17))-1 -> 5.8415532e-09 | JI17: =IF(JH17>0,JG17,JE17) -> 0.28410927 | JJ17: =IF(JH17>0,JF17,JG17) -> 0.28410928 | JK17: =(JI17+JJ17)/2 -> 0.28410927 | JL17: =(SUMPRODUCT(($G$8:$G$694=X17)*SQRT(JK17^2+4*(1-JK17)*$I$8:$I$694^2/Z17))-COUNTIF($G$8:$G$694,X17)*JK17)/(2*(1-JK17))-1 -> 1.7773432e-09 | JM17: =IF(JL17>0,JK17,JI17) -> 0.28410927 | JN17: =IF(JL17>0,JJ17,JK17) -> 0.28410928 | JO17: =(JM17+JN17)/2 -> 0.28410927 | JP17: =(SUMPRODUCT(($G$8:$G$694=X17)*SQRT(JO17^2+4*(1-JO17)*$I$8:$I$694^2/Z17))-COUNTIF($G$8:$G$694,X17)*JO17)/(2*(1-JO17))-1 -> -2.5476177e-10 | JQ17: =IF(JP17>0,JO17,JM17) -> 0.28410927 | JR17: =IF(JP17>0,JN17,JO17) -> 0.28410927 | JS17: =(JQ17+JR17)/2 -> 0.28410927 | JT17: =(SUMPRODUCT(($G$8:$G$694=X17)*SQRT(JS17^2+4*(1-JS17)*$I$8:$I$694^2/Z17))-COUNTIF($G$8:$G$694,X17)*JS17)/(2*(1-JS17))-1 -> 7.6129147e-10 | JU17: =IF(JT17>0,JS17,JQ17) -> 0.28410927 | JV17: =IF(JT17>0,JR17,JS17) -> 0.28410927 | JW17: =(JU17+JV17)/2 -> 0.28410927 | JX17: =(SUMPRODUCT(($G$8:$G$694=X17)*SQRT(JW17^2+4*(1-JW17)*$I$8:$I$694^2/Z17))-COUNTIF($G$8:$G$694,X17)*JW17)/(2*(1-JW17))-1 -> 2.5326452e-10 | JY17: =IF(JX17>0,JW17,JU17) -> 0.28410927 | JZ17: =IF(JX17>0,JV17,JW17) -> 0.28410927 | KA17: =(EY17+EZ17)/2 -> 1.080313 | KB17: =(JY17+JZ17)/2 -> 0.28410927
A18: =Odds_Input!A18 -> 10 | B18: =Odds_Input!B18 -> TITLE | C18: =Odds_Input!C18 -> Houston Rockets | D18: =Odds_Input!D18 -> YES | E18: =Odds_Input!E18 -> - | F18: =Odds_Input!F18 -> 4900 | G18: =IF(OR(B18="WINS",B18="PLAYOFFS"),B18&"|"&C18&IF(B18="WINS","|"&TEXT(E18,"0.0"),""),B18) -> TITLE | H18: =IF(F18>0,1+F18/100,1+100/ABS(F18)) -> 50 | I18: =1/H18 -> 0.02 | J18: =IF(LEFT(B18,6)="PLAYIN",A_playin_slots,1) -> 1 | K18: =COUNTIF($G$8:$G$694,G18) -> 30 | L18: =SUMIF($G$8:$G$694,G18,$I$8:$I$694) -> 1.2525652 | M18: =L18/J18-1 -> 0.25256519 | N18: =I18*J18/L18 -> 0.015967233 | O18: =I18^R18 -> 0.013566447 | P18: =IF(J18<>1,O18,IF(L18<=1,I18/L18,(SQRT(S18^2+4*(1-S18)*I18^2/L18)-S18)/(2*(1-S18)))) -> 0.013230777 | Q18: =IF(A_devig="Multiplicative",N18,IF(A_devig="Power",O18,P18)) -> 0.013230777 | R18: =INDEX($KA$8:$KA$96,MATCH(G18,$X$8:$X$96,0)) -> 1.0992153 | S18: =INDEX($KB$8:$KB$96,MATCH(G18,$X$8:$X$96,0)) -> 0.011051948 | X18: PLAYIN_WEST | Y18: =IF(LEFT(X18,6)="PLAYIN",A_playin_slots,1) -> 4 | Z18: =SUMIF($G$8:$G$694,X18,$I$8:$I$694) -> 4.4014552 | AA18: 0.2 | AB18: 10 | AC18: =(AA18+AB18)/2 -> 5.1 | AD18: =SUMPRODUCT(($G$8:$G$694=X18)*($I$8:$I$694^AC18))-Y18 -> -3.863155 | AE18: =IF(AD18>0,AC18,AA18) -> 0.2 | AF18: =IF(AD18>0,AB18,AC18) -> 5.1 | AG18: =(AE18+AF18)/2 -> 2.65 | AH18: =SUMPRODUCT(($G$8:$G$694=X18)*($I$8:$I$694^AG18))-Y18 -> -3.0440318 | AI18: =IF(AH18>0,AG18,AE18) -> 0.2 | AJ18: =IF(AH18>0,AF18,AG18) -> 2.65 | AK18: =(AI18+AJ18)/2 -> 1.425 | AL18: =SUMPRODUCT(($G$8:$G$694=X18)*($I$8:$I$694^AK18))-Y18 -> -1.119694 | AM18: =IF(AL18>0,AK18,AI18) -> 0.2 | AN18: =IF(AL18>0,AJ18,AK18) -> 1.425 | AO18: =(AM18+AN18)/2 -> 0.8125 | AP18: =SUMPRODUCT(($G$8:$G$694=X18)*($I$8:$I$694^AO18))-Y18 -> 1.3691402 | AQ18: =IF(AP18>0,AO18,AM18) -> 0.8125 | AR18: =IF(AP18>0,AN18,AO18) -> 1.425 | AS18: =(AQ18+AR18)/2 -> 1.11875 | AT18: =SUMPRODUCT(($G$8:$G$694=X18)*($I$8:$I$694^AS18))-Y18 -> -0.10298183 | AU18: =IF(AT18>0,AS18,AQ18) -> 0.8125 | AV18: =IF(AT18>0,AR18,AS18) -> 1.11875 | AW18: =(AU18+AV18)/2 -> 0.965625 | AX18: =SUMPRODUCT(($G$8:$G$694=X18)*($I$8:$I$694^AW18))-Y18 -> 0.56185957 | AY18: =IF(AX18>0,AW18,AU18) -> 0.965625 | AZ18: =IF(AX18>0,AV18,AW18) -> 1.11875 | BA18: =(AY18+AZ18)/2 -> 1.0421875 | BB18: =SUMPRODUCT(($G$8:$G$694=X18)*($I$8:$I$694^BA18))-Y18 -> 0.21377538 | BC18: =IF(BB18>0,BA18,AY18) -> 1.0421875 | BD18: =IF(BB18>0,AZ18,BA18) -> 1.11875 | BE18: =(BC18+BD18)/2 -> 1.0804687 | BF18: =SUMPRODUCT(($G$8:$G$694=X18)*($I$8:$I$694^BE18))-Y18 -> 0.051712022 | BG18: =IF(BF18>0,BE18,BC18) -> 1.0804687 | BH18: =IF(BF18>0,BD18,BE18) -> 1.11875 | BI18: =(BG18+BH18)/2 -> 1.0996094 | BJ18: =SUMPRODUCT(($G$8:$G$694=X18)*($I$8:$I$694^BI18))-Y18 -> -0.026529153 | BK18: =IF(BJ18>0,BI18,BG18) -> 1.0804687 | BL18: =IF(BJ18>0,BH18,BI18) -> 1.0996094 | BM18: =(BK18+BL18)/2 -> 1.0900391 | BN18: =SUMPRODUCT(($G$8:$G$694=X18)*($I$8:$I$694^BM18))-Y18 -> 0.012364586 | BO18: =IF(BN18>0,BM18,BK18) -> 1.0900391 | BP18: =IF(BN18>0,BL18,BM18) -> 1.0996094 | BQ18: =(BO18+BP18)/2 -> 1.0948242 | BR18: =SUMPRODUCT(($G$8:$G$694=X18)*($I$8:$I$694^BQ18))-Y18 -> -0.0071385797 | BS18: =IF(BR18>0,BQ18,BO18) -> 1.0900391 | BT18: =IF(BR18>0,BP18,BQ18) -> 1.0948242 | BU18: =(BS18+BT18)/2 -> 1.0924316 | BV18: =SUMPRODUCT(($G$8:$G$694=X18)*($I$8:$I$694^BU18))-Y18 -> 0.0025988775 | BW18: =IF(BV18>0,BU18,BS18) -> 1.0924316 | BX18: =IF(BV18>0,BT18,BU18) -> 1.0948242 | BY18: =(BW18+BX18)/2 -> 1.0936279 | BZ18: =SUMPRODUCT(($G$8:$G$694=X18)*($I$8:$I$694^BY18))-Y18 -> -0.002273376 | CA18: =IF(BZ18>0,BY18,BW18) -> 1.0924316 | CB18: =IF(BZ18>0,BX18,BY18) -> 1.0936279 | CC18: =(CA18+CB18)/2 -> 1.0930298 | CD18: =SUMPRODUCT(($G$8:$G$694=X18)*($I$8:$I$694^CC18))-Y18 -> 0.0001618687 | CE18: =IF(CD18>0,CC18,CA18) -> 1.0930298 | CF18: =IF(CD18>0,CB18,CC18) -> 1.0936279 | CG18: =(CE18+CF18)/2 -> 1.0933289 | CH18: =SUMPRODUCT(($G$8:$G$694=X18)*($I$8:$I$694^CG18))-Y18 -> -0.0010559741 | CI18: =IF(CH18>0,CG18,CE18) -> 1.0930298 | CJ18: =IF(CH18>0,CF18,CG18) -> 1.0933289 | CK18: =(CI18+CJ18)/2 -> 1.0931793 | CL18: =SUMPRODUCT(($G$8:$G$694=X18)*($I$8:$I$694^CK18))-Y18 -> -0.00044710781 | CM18: =IF(CL18>0,CK18,CI18) -> 1.0930298 | CN18: =IF(CL18>0,CJ18,CK18) -> 1.0931793 | CO18: =(CM18+CN18)/2 -> 1.0931046 | CP18: =SUMPRODUCT(($G$8:$G$694=X18)*($I$8:$I$694^CO18))-Y18 -> -0.00014263334 | CQ18: =IF(CP18>0,CO18,CM18) -> 1.0930298 | CR18: =IF(CP18>0,CN18,CO18) -> 1.0931046 | CS18: =(CQ18+CR18)/2 -> 1.0930672 | CT18: =SUMPRODUCT(($G$8:$G$694=X18)*($I$8:$I$694^CS18))-Y18 -> 9.614233e-06 | CU18: =IF(CT18>0,CS18,CQ18) -> 1.0930672 | CV18: =IF(CT18>0,CR18,CS18) -> 1.0931046 | CW18: =(CU18+CV18)/2 -> 1.0930859 | CX18: =SUMPRODUCT(($G$8:$G$694=X18)*($I$8:$I$694^CW18))-Y18 -> -6.6510414e-05 | CY18: =IF(CX18>0,CW18,CU18) -> 1.0930672 | CZ18: =IF(CX18>0,CV18,CW18) -> 1.0930859 | DA18: =(CY18+CZ18)/2 -> 1.0930765 | DB18: =SUMPRODUCT(($G$8:$G$694=X18)*($I$8:$I$694^DA18))-Y18 -> -2.8448306e-05 | DC18: =IF(DB18>0,DA18,CY18) -> 1.0930672 | DD18: =IF(DB18>0,CZ18,DA18) -> 1.0930765 | DE18: =(DC18+DD18)/2 -> 1.0930718 | DF18: =SUMPRODUCT(($G$8:$G$694=X18)*($I$8:$I$694^DE18))-Y18 -> -9.4170903e-06 | DG18: =IF(DF18>0,DE18,DC18) -> 1.0930672 | DH18: =IF(DF18>0,DD18,DE18) -> 1.0930718 | DI18: =(DG18+DH18)/2 -> 1.0930695 | DJ18: =SUMPRODUCT(($G$8:$G$694=X18)*($I$8:$I$694^DI18))-Y18 -> 9.8557893e-08 | DK18: =IF(DJ18>0,DI18,DG18) -> 1.0930695 | DL18: =IF(DJ18>0,DH18,DI18) -> 1.0930718 | DM18: =(DK18+DL18)/2 -> 1.0930707 | DN18: =SUMPRODUCT(($G$8:$G$694=X18)*($I$8:$I$694^DM18))-Y18 -> -4.6592696e-06 | DO18: =IF(DN18>0,DM18,DK18) -> 1.0930695 | DP18: =IF(DN18>0,DL18,DM18) -> 1.0930707 | DQ18: =(DO18+DP18)/2 -> 1.0930701 | DR18: =SUMPRODUCT(($G$8:$G$694=X18)*($I$8:$I$694^DQ18))-Y18 -> -2.2803567e-06 | DS18: =IF(DR18>0,DQ18,DO18) -> 1.0930695 | DT18: =IF(DR18>0,DP18,DQ18) -> 1.0930701 | DU18: =(DS18+DT18)/2 -> 1.0930698 | DV18: =SUMPRODUCT(($G$8:$G$694=X18)*($I$8:$I$694^DU18))-Y18 -> -1.0908996e-06 | DW18: =IF(DV18>0,DU18,DS18) -> 1.0930695 | DX18: =IF(DV18>0,DT18,DU18) -> 1.0930698 | DY18: =(DW18+DX18)/2 -> 1.0930697 | DZ18: =SUMPRODUCT(($G$8:$G$694=X18)*($I$8:$I$694^DY18))-Y18 -> -4.9617091e-07 | EA18: =IF(DZ18>0,DY18,DW18) -> 1.0930695 | EB18: =IF(DZ18>0,DX18,DY18) -> 1.0930697 | EC18: =(EA18+EB18)/2 -> 1.0930696 | ED18: =SUMPRODUCT(($G$8:$G$694=X18)*($I$8:$I$694^EC18))-Y18 -> -1.9880652e-07 | EE18: =IF(ED18>0,EC18,EA18) -> 1.0930695 | EF18: =IF(ED18>0,EB18,EC18) -> 1.0930696 | EG18: =(EE18+EF18)/2 -> 1.0930695 | EH18: =SUMPRODUCT(($G$8:$G$694=X18)*($I$8:$I$694^EG18))-Y18 -> -5.0124317e-08 | EI18: =IF(EH18>0,EG18,EE18) -> 1.0930695 | EJ18: =IF(EH18>0,EF18,EG18) -> 1.0930695 | EK18: =(EI18+EJ18)/2 -> 1.0930695 | EL18: =SUMPRODUCT(($G$8:$G$694=X18)*($I$8:$I$694^EK18))-Y18 -> 2.4216788e-08 | EM18: =IF(EL18>0,EK18,EI18) -> 1.0930695 | EN18: =IF(EL18>0,EJ18,EK18) -> 1.0930695 | EO18: =(EM18+EN18)/2 -> 1.0930695 | EP18: =SUMPRODUCT(($G$8:$G$694=X18)*($I$8:$I$694^EO18))-Y18 -> -1.2953765e-08 | EQ18: =IF(EP18>0,EO18,EM18) -> 1.0930695 | ER18: =IF(EP18>0,EN18,EO18) -> 1.0930695 | ES18: =(EQ18+ER18)/2 -> 1.0930695 | ET18: =SUMPRODUCT(($G$8:$G$694=X18)*($I$8:$I$694^ES18))-Y18 -> 5.6315113e-09 | EU18: =IF(ET18>0,ES18,EQ18) -> 1.0930695 | EV18: =IF(ET18>0,ER18,ES18) -> 1.0930695 | EW18: =(EU18+EV18)/2 -> 1.0930695 | EX18: =SUMPRODUCT(($G$8:$G$694=X18)*($I$8:$I$694^EW18))-Y18 -> -3.6611274e-09 | EY18: =IF(EX18>0,EW18,EU18) -> 1.0930695 | EZ18: =IF(EX18>0,EV18,EW18) -> 1.0930695 | FA18: 1e-06 | FB18: 0.9999 | FC18: =(FA18+FB18)/2 -> 0.4999505 | FD18: =(SUMPRODUCT(($G$8:$G$694=X18)*SQRT(FC18^2+4*(1-FC18)*$I$8:$I$694^2/Z18))-COUNTIF($G$8:$G$694,X18)*FC18)/(2*(1-FC18))-1 -> -0.28840217 | FE18: =IF(FD18>0,FC18,FA18) -> 1e-06 | FF18: =IF(FD18>0,FB18,FC18) -> 0.4999505 | FG18: =(FE18+FF18)/2 -> 0.24997575 | FH18: =(SUMPRODUCT(($G$8:$G$694=X18)*SQRT(FG18^2+4*(1-FG18)*$I$8:$I$694^2/Z18))-COUNTIF($G$8:$G$694,X18)*FG18)/(2*(1-FG18))-1 -> 0.13478946 | FI18: =IF(FH18>0,FG18,FE18) -> 0.24997575 | FJ18: =IF(FH18>0,FF18,FG18) -> 0.4999505 | FK18: =(FI18+FJ18)/2 -> 0.37496313 | FL18: =(SUMPRODUCT(($G$8:$G$694=X18)*SQRT(FK18^2+4*(1-FK18)*$I$8:$I$694^2/Z18))-COUNTIF($G$8:$G$694,X18)*FK18)/(2*(1-FK18))-1 -> -0.11667192 | FM18: =IF(FL18>0,FK18,FI18) -> 0.24997575 | FN18: =IF(FL18>0,FJ18,FK18) -> 0.37496313 | FO18: =(FM18+FN18)/2 -> 0.31246944 | FP18: =(SUMPRODUCT(($G$8:$G$694=X18)*SQRT(FO18^2+4*(1-FO18)*$I$8:$I$694^2/Z18))-COUNTIF($G$8:$G$694,X18)*FO18)/(2*(1-FO18))-1 -> -0.003330809 | FQ18: =IF(FP18>0,FO18,FM18) -> 0.24997575 | FR18: =IF(FP18>0,FN18,FO18) -> 0.31246944 | FS18: =(FQ18+FR18)/2 -> 0.28122259 | FT18: =(SUMPRODUCT(($G$8:$G$694=X18)*SQRT(FS18^2+4*(1-FS18)*$I$8:$I$694^2/Z18))-COUNTIF($G$8:$G$694,X18)*FS18)/(2*(1-FS18))-1 -> 0.062264562 | FU18: =IF(FT18>0,FS18,FQ18) -> 0.28122259 | FV18: =IF(FT18>0,FR18,FS18) -> 0.31246944 | FW18: =(FU18+FV18)/2 -> 0.29684602 | FX18: =(SUMPRODUCT(($G$8:$G$694=X18)*SQRT(FW18^2+4*(1-FW18)*$I$8:$I$694^2/Z18))-COUNTIF($G$8:$G$694,X18)*FW18)/(2*(1-FW18))-1 -> 0.028649778 | FY18: =IF(FX18>0,FW18,FU18) -> 0.29684602 | FZ18: =IF(FX18>0,FV18,FW18) -> 0.31246944 | GA18: =(FY18+FZ18)/2 -> 0.30465773 | GB18: =(SUMPRODUCT(($G$8:$G$694=X18)*SQRT(GA18^2+4*(1-GA18)*$I$8:$I$694^2/Z18))-COUNTIF($G$8:$G$694,X18)*GA18)/(2*(1-GA18))-1 -> 0.012461062 | GC18: =IF(GB18>0,GA18,FY18) -> 0.30465773 | GD18: =IF(GB18>0,FZ18,GA18) -> 0.31246944 | GE18: =(GC18+GD18)/2 -> 0.30856358 | GF18: =(SUMPRODUCT(($G$8:$G$694=X18)*SQRT(GE18^2+4*(1-GE18)*$I$8:$I$694^2/Z18))-COUNTIF($G$8:$G$694,X18)*GE18)/(2*(1-GE18))-1 -> 0.0045162352 | GG18: =IF(GF18>0,GE18,GC18) -> 0.30856358 | GH18: =IF(GF18>0,GD18,GE18) -> 0.31246944 | GI18: =(GG18+GH18)/2 -> 0.31051651 | GJ18: =(SUMPRODUCT(($G$8:$G$694=X18)*SQRT(GI18^2+4*(1-GI18)*$I$8:$I$694^2/Z18))-COUNTIF($G$8:$G$694,X18)*GI18)/(2*(1-GI18))-1 -> 0.00058057844 | GK18: =IF(GJ18>0,GI18,GG18) -> 0.31051651 | GL18: =IF(GJ18>0,GH18,GI18) -> 0.31246944 | GM18: =(GK18+GL18)/2 -> 0.31149297 | GN18: =(SUMPRODUCT(($G$8:$G$694=X18)*SQRT(GM18^2+4*(1-GM18)*$I$8:$I$694^2/Z18))-COUNTIF($G$8:$G$694,X18)*GM18)/(2*(1-GM18))-1 -> -0.001378138 | GO18: =IF(GN18>0,GM18,GK18) -> 0.31051651 | GP18: =IF(GN18>0,GL18,GM18) -> 0.31149297 | GQ18: =(GO18+GP18)/2 -> 0.31100474 | GR18: =(SUMPRODUCT(($G$8:$G$694=X18)*SQRT(GQ18^2+4*(1-GQ18)*$I$8:$I$694^2/Z18))-COUNTIF($G$8:$G$694,X18)*GQ18)/(2*(1-GQ18))-1 -> -0.00039953682 | GS18: =IF(GR18>0,GQ18,GO18) -> 0.31051651 | GT18: =IF(GR18>0,GP18,GQ18) -> 0.31100474 | GU18: =(GS18+GT18)/2 -> 0.31076063 | GV18: =(SUMPRODUCT(($G$8:$G$694=X18)*SQRT(GU18^2+4*(1-GU18)*$I$8:$I$694^2/Z18))-COUNTIF($G$8:$G$694,X18)*GU18)/(2*(1-GU18))-1 -> 9.0331373e-05 | GW18: =IF(GV18>0,GU18,GS18) -> 0.31076063 | GX18: =IF(GV18>0,GT18,GU18) -> 0.31100474 | GY18: =(GW18+GX18)/2 -> 0.31088268 | GZ18: =(SUMPRODUCT(($G$8:$G$694=X18)*SQRT(GY18^2+4*(1-GY18)*$I$8:$I$694^2/Z18))-COUNTIF($G$8:$G$694,X18)*GY18)/(2*(1-GY18))-1 -> -0.00015465006 | HA18: =IF(GZ18>0,GY18,GW18) -> 0.31076063 | HB18: =IF(GZ18>0,GX18,GY18) -> 0.31088268 | HC18: =(HA18+HB18)/2 -> 0.31082165 | HD18: =(SUMPRODUCT(($G$8:$G$694=X18)*SQRT(HC18^2+4*(1-HC18)*$I$8:$I$694^2/Z18))-COUNTIF($G$8:$G$694,X18)*HC18)/(2*(1-HC18))-1 -> -3.2171181e-05 | HE18: =IF(HD18>0,HC18,HA18) -> 0.31076063 | HF18: =IF(HD18>0,HB18,HC18) -> 0.31082165 | HG18: =(HE18+HF18)/2 -> 0.31079114 | HH18: =(SUMPRODUCT(($G$8:$G$694=X18)*SQRT(HG18^2+4*(1-HG18)*$I$8:$I$694^2/Z18))-COUNTIF($G$8:$G$694,X18)*HG18)/(2*(1-HG18))-1 -> 2.9077137e-05 | HI18: =IF(HH18>0,HG18,HE18) -> 0.31079114 | HJ18: =IF(HH18>0,HF18,HG18) -> 0.31082165 | HK18: =(HI18+HJ18)/2 -> 0.3108064 | HL18: =(SUMPRODUCT(($G$8:$G$694=X18)*SQRT(HK18^2+4*(1-HK18)*$I$8:$I$694^2/Z18))-COUNTIF($G$8:$G$694,X18)*HK18)/(2*(1-HK18))-1 -> -1.5477622e-06 | HM18: =IF(HL18>0,HK18,HI18) -> 0.31079114 | HN18: =IF(HL18>0,HJ18,HK18) -> 0.3108064 | HO18: =(HM18+HN18)/2 -> 0.31079877 | HP18: =(SUMPRODUCT(($G$8:$G$694=X18)*SQRT(HO18^2+4*(1-HO18)*$I$8:$I$694^2/Z18))-COUNTIF($G$8:$G$694,X18)*HO18)/(2*(1-HO18))-1 -> 1.3764502e-05 | HQ18: =IF(HP18>0,HO18,HM18) -> 0.31079877 | HR18: =IF(HP18>0,HN18,HO18) -> 0.3108064 | HS18: =(HQ18+HR18)/2 -> 0.31080258 | HT18: =(SUMPRODUCT(($G$8:$G$694=X18)*SQRT(HS18^2+4*(1-HS18)*$I$8:$I$694^2/Z18))-COUNTIF($G$8:$G$694,X18)*HS18)/(2*(1-HS18))-1 -> 6.1083238e-06 | HU18: =IF(HT18>0,HS18,HQ18) -> 0.31080258 | HV18: =IF(HT18>0,HR18,HS18) -> 0.3108064 | HW18: =(HU18+HV18)/2 -> 0.31080449 | HX18: =(SUMPRODUCT(($G$8:$G$694=X18)*SQRT(HW18^2+4*(1-HW18)*$I$8:$I$694^2/Z18))-COUNTIF($G$8:$G$694,X18)*HW18)/(2*(1-HW18))-1 -> 2.2802692e-06 | HY18: =IF(HX18>0,HW18,HU18) -> 0.31080449 | HZ18: =IF(HX18>0,HV18,HW18) -> 0.3108064 | IA18: =(HY18+HZ18)/2 -> 0.31080544 | IB18: =(SUMPRODUCT(($G$8:$G$694=X18)*SQRT(IA18^2+4*(1-IA18)*$I$8:$I$694^2/Z18))-COUNTIF($G$8:$G$694,X18)*IA18)/(2*(1-IA18))-1 -> 3.6625064e-07 | IC18: =IF(IB18>0,IA18,HY18) -> 0.31080544 | ID18: =IF(IB18>0,HZ18,IA18) -> 0.3108064 | IE18: =(IC18+ID18)/2 -> 0.31080592 | IF18: =(SUMPRODUCT(($G$8:$G$694=X18)*SQRT(IE18^2+4*(1-IE18)*$I$8:$I$694^2/Z18))-COUNTIF($G$8:$G$694,X18)*IE18)/(2*(1-IE18))-1 -> -5.9075649e-07 | IG18: =IF(IF18>0,IE18,IC18) -> 0.31080544 | IH18: =IF(IF18>0,ID18,IE18) -> 0.31080592 | II18: =(IG18+IH18)/2 -> 0.31080568 | IJ18: =(SUMPRODUCT(($G$8:$G$694=X18)*SQRT(II18^2+4*(1-II18)*$I$8:$I$694^2/Z18))-COUNTIF($G$8:$G$694,X18)*II18)/(2*(1-II18))-1 -> -1.1225311e-07 | IK18: =IF(IJ18>0,II18,IG18) -> 0.31080544 | IL18: =IF(IJ18>0,IH18,II18) -> 0.31080568 | IM18: =(IK18+IL18)/2 -> 0.31080556 | IN18: =(SUMPRODUCT(($G$8:$G$694=X18)*SQRT(IM18^2+4*(1-IM18)*$I$8:$I$694^2/Z18))-COUNTIF($G$8:$G$694,X18)*IM18)/(2*(1-IM18))-1 -> 1.2699872e-07 | IO18: =IF(IN18>0,IM18,IK18) -> 0.31080556 | IP18: =IF(IN18>0,IL18,IM18) -> 0.31080568 | IQ18: =(IO18+IP18)/2 -> 0.31080562 | IR18: =(SUMPRODUCT(($G$8:$G$694=X18)*SQRT(IQ18^2+4*(1-IQ18)*$I$8:$I$694^2/Z18))-COUNTIF($G$8:$G$694,X18)*IQ18)/(2*(1-IQ18))-1 -> 7.3727922e-09 | IS18: =IF(IR18>0,IQ18,IO18) -> 0.31080562 | IT18: =IF(IR18>0,IP18,IQ18) -> 0.31080568 | IU18: =(IS18+IT18)/2 -> 0.31080565 | IV18: =(SUMPRODUCT(($G$8:$G$694=X18)*SQRT(IU18^2+4*(1-IU18)*$I$8:$I$694^2/Z18))-COUNTIF($G$8:$G$694,X18)*IU18)/(2*(1-IU18))-1 -> -5.2440161e-08 | IW18: =IF(IV18>0,IU18,IS18) -> 0.31080562 | IX18: =IF(IV18>0,IT18,IU18) -> 0.31080565 | IY18: =(IW18+IX18)/2 -> 0.31080564 | IZ18: =(SUMPRODUCT(($G$8:$G$694=X18)*SQRT(IY18^2+4*(1-IY18)*$I$8:$I$694^2/Z18))-COUNTIF($G$8:$G$694,X18)*IY18)/(2*(1-IY18))-1 -> -2.2533685e-08 | JA18: =IF(IZ18>0,IY18,IW18) -> 0.31080562 | JB18: =IF(IZ18>0,IX18,IY18) -> 0.31080564 | JC18: =(JA18+JB18)/2 -> 0.31080563 | JD18: =(SUMPRODUCT(($G$8:$G$694=X18)*SQRT(JC18^2+4*(1-JC18)*$I$8:$I$694^2/Z18))-COUNTIF($G$8:$G$694,X18)*JC18)/(2*(1-JC18))-1 -> -7.5804454e-09 | JE18: =IF(JD18>0,JC18,JA18) -> 0.31080562 | JF18: =IF(JD18>0,JB18,JC18) -> 0.31080563 | JG18: =(JE18+JF18)/2 -> 0.31080563 | JH18: =(SUMPRODUCT(($G$8:$G$694=X18)*SQRT(JG18^2+4*(1-JG18)*$I$8:$I$694^2/Z18))-COUNTIF($G$8:$G$694,X18)*JG18)/(2*(1-JG18))-1 -> -1.038265e-10 | JI18: =IF(JH18>0,JG18,JE18) -> 0.31080562 | JJ18: =IF(JH18>0,JF18,JG18) -> 0.31080563 | JK18: =(JI18+JJ18)/2 -> 0.31080562 | JL18: =(SUMPRODUCT(($G$8:$G$694=X18)*SQRT(JK18^2+4*(1-JK18)*$I$8:$I$694^2/Z18))-COUNTIF($G$8:$G$694,X18)*JK18)/(2*(1-JK18))-1 -> 3.6344827e-09 | JM18: =IF(JL18>0,JK18,JI18) -> 0.31080562 | JN18: =IF(JL18>0,JJ18,JK18) -> 0.31080563 | JO18: =(JM18+JN18)/2 -> 0.31080563 | JP18: =(SUMPRODUCT(($G$8:$G$694=X18)*SQRT(JO18^2+4*(1-JO18)*$I$8:$I$694^2/Z18))-COUNTIF($G$8:$G$694,X18)*JO18)/(2*(1-JO18))-1 -> 1.7653268e-09 | JQ18: =IF(JP18>0,JO18,JM18) -> 0.31080563 | JR18: =IF(JP18>0,JN18,JO18) -> 0.31080563 | JS18: =(JQ18+JR18)/2 -> 0.31080563 | JT18: =(SUMPRODUCT(($G$8:$G$694=X18)*SQRT(JS18^2+4*(1-JS18)*$I$8:$I$694^2/Z18))-COUNTIF($G$8:$G$694,X18)*JS18)/(2*(1-JS18))-1 -> 8.3075036e-10 | JU18: =IF(JT18>0,JS18,JQ18) -> 0.31080563 | JV18: =IF(JT18>0,JR18,JS18) -> 0.31080563 | JW18: =(JU18+JV18)/2 -> 0.31080563 | JX18: =(SUMPRODUCT(($G$8:$G$694=X18)*SQRT(JW18^2+4*(1-JW18)*$I$8:$I$694^2/Z18))-COUNTIF($G$8:$G$694,X18)*JW18)/(2*(1-JW18))-1 -> 3.6346193e-10 | JY18: =IF(JX18>0,JW18,JU18) -> 0.31080563 | JZ18: =IF(JX18>0,JV18,JW18) -> 0.31080563 | KA18: =(EY18+EZ18)/2 -> 1.0930695 | KB18: =(JY18+JZ18)/2 -> 0.31080563
